Workbook

Sheet Tools
A2: EoC Check
A3: Choose Date | B3: 46098
A4: Departure Airport Code | B4: lcy
A5: Arrival Airport Code | B5: ber | AB5: =IFERROR(__xludf.DUMMYFUNCTION("ifna(FILTER('EOC DB'!B3:C2875,'EOC DB'!A3:A2875=$B$3),ifna(ifna(FILTER('EOC DB'!F2:G2875,'EOC DB'!E2:E2875=VLOOKUP(B4,'Airports DB'!B1:E2875,3,0),$B$3>'EOC DB'!D2:D2875),ifna(FILTER('EOC DB'!K2:L2875,'EOC DB'!H2:H2875=$B$3&VLOOKUP(B4,'Airports DB'!B1:E287"&"5,3,0)),FILTER('EOC DB'!P2:Q2875,'EOC DB'!M2:M2875=$B$3&B4))),""No Extra Ordinary Circumstances""))"),"No Extra Ordinary Circumstances") -> No Extra Ordinary Circumstances
A6: Eligibility Check | B6: =IF(AB16+AK16=2,"Under EC 261/2004",if(AB16=1,"Under EC 261/2004",IF(AK16=1,"Please check the airline if the operator is an EU airline then it's under EC 261/2004","Not Under EC 261/2004"))) -> Under EC 261/2004 | AB6: =IFERROR(__xludf.DUMMYFUNCTION("ifna(FILTER('EOC DB'!B4:C2875,'EOC DB'!A4:A2875=$B$3),ifna(ifna(FILTER('EOC DB'!F3:G2875,'EOC DB'!E3:E2875=VLOOKUP(B5,'Airports DB'!B2:E2875,3,0),$B$3>'EOC DB'!D3:D2875),ifna(FILTER('EOC DB'!K3:L2875,'EOC DB'!H3:H2875=$B$3&VLOOKUP(B5,'Airports DB'!B2:E287"&"5,3,0)),FILTER('EOC DB'!P3:Q2875,'EOC DB'!M3:M2875=$B$3&B5))),""No Extra Ordinary Circumstances""))"),"No Extra Ordinary Circumstances") -> No Extra Ordinary Circumstances
A7: Notes | B7: =ifna(ifna("- Departure Country (" &VLOOKUP(AB26,'Countries DB'!$G:$G,1,0)&") is under EC261/2004","- Departure country ("&AB26&") Is Not under EC261")&" " &ifna("- Destination Country (" &VLOOKUP(AK26,'Countries DB'!$G:$G,1,0)&") is under EC261/2004","- Destination Country ("&AK26&") Is Not under EC261"),"") -> - Departure Country (United Kingdom) is under EC261/2004 - Destination Country (Germany) is under EC261/2004
A8: EoC Check | B8: =IF(AC5="reject","Reject Because "&B4&" airport had an EoC: "&AB5,IF(AC6="reject","Reject Because "&B5&" airport had an EoC: "&AB6,"No Extra Ordinary Circumstances")) -> No Extra Ordinary Circumstances
A13: Airlines Data
A14: Airline Name | B14: Air New Zealand (NZ)
A15: {=TRANSPOSE('Airline DB'!B1:H1)} | B15: =IFERROR(__xludf.DUMMYFUNCTION("TRANSPOSE(FILTER('Airline DB'!B:J,'Airline DB'!A:A=$B$14))"),"") | AK15: Des
A16: MAIN E-MAIL | B16: =IFERROR(__xludf.DUMMYFUNCTION("""COMPUTED_VALUE"""),"cro@airnz.co.nz") -> cro@airnz.co.nz | AB16: =IF(IFERROR(FIND("Not",AB19,1),1)=1,1,0) -> 1 | AK16: =IF(IFERROR(FIND("Not",AK19,1),1)=1,1,0) -> 1
A17: WAY OF SUBMISSION
A18: ( Links/ webform) | B18: =IFERROR(__xludf.DUMMYFUNCTION("""COMPUTED_VALUE"""),"https://www.airnewzealand.co.nz/feedback/complaint/") -> https://www.airnewzealand.co.nz/feedback/complaint/
A19: Mandatory | AB19: =ifna("Departure Country (" &VLOOKUP(AB26,'Countries DB'!$G:$G,1,0)&") is under EC261/2004","Departure country ("&AB26&") Is Not under EC261") -> Departure Country (United Kingdom) is under EC261/2004 | AK19: =ifna("Destination Country (" &VLOOKUP(AK26,'Countries DB'!$G:$G,1,0)&") is under EC261/2004","Destination Country ("&AK26&") Is Not under EC261") -> Destination Country (Germany) is under EC261/2004
A20: Other Links/ Address
A21: Remarks
A23: Jurisdictions
A24: Jurisdictions | B24: Romania
A25: RANK | B25: =IFERROR(__xludf.DUMMYFUNCTION("TRANSPOSE(FILTER(JR!O:W,JR!A:A=$B$24))"),2.0) -> 2
A26: EXPIRATION PERIOD | B26: =IFERROR(__xludf.DUMMYFUNCTION("""COMPUTED_VALUE"""),"3 years") -> 3 years | AB26: =VLOOKUP(Tools!B4,'Airports DB'!B1:D2875,3,0) -> United Kingdom | AC26: =IFERROR(__xludf.DUMMYFUNCTION("FILTER('Airports DB'!A1:F2875,'Airports DB'!D1:D2875=AB26)"),"Aberdeen") -> Aberdeen | AD26: =IFERROR(__xludf.DUMMYFUNCTION("""COMPUTED_VALUE"""),"ABZ") -> ABZ | AE26: =IFERROR(__xludf.DUMMYFUNCTION("""COMPUTED_VALUE"""),"Dyce") -> Dyce | AF26: =IFERROR(__xludf.DUMMYFUNCTION("""COMPUTED_VALUE"""),"United Kingdom") -> United Kingdom | AK26: =VLOOKUP(Tools!B5,'Airports DB'!B1:D2875,3,0) -> Germany | AL26: =IFERROR(__xludf.DUMMYFUNCTION("FILTER('Airports DB'!A1:F2875,'Airports DB'!D1:D2875=AK26)"),"Aachen") -> Aachen | AM26: =IFERROR(__xludf.DUMMYFUNCTION("""COMPUTED_VALUE"""),"AAH") -> AAH | AN26: =IFERROR(__xludf.DUMMYFUNCTION("""COMPUTED_VALUE"""),"Aachen/Merzbruck") -> Aachen/Merzbruck | AO26: =IFERROR(__xludf.DUMMYFUNCTION("""COMPUTED_VALUE"""),"Germany") -> Germany
A27: Assignment Form / POA | B27: =IFERROR(__xludf.DUMMYFUNCTION("""COMPUTED_VALUE"""),"Yes") -> Yes | AC27: =IFERROR(__xludf.DUMMYFUNCTION("""COMPUTED_VALUE"""),"Abingdon") -> Abingdon | AD27: =IFERROR(__xludf.DUMMYFUNCTION("""COMPUTED_VALUE"""),"ABB") -> ABB | AE27: =IFERROR(__xludf.DUMMYFUNCTION("""COMPUTED_VALUE"""),"RAF Station") -> RAF Station | AF27: =IFERROR(__xludf.DUMMYFUNCTION("""COMPUTED_VALUE"""),"United Kingdom") -> United Kingdom | AL27: =IFERROR(__xludf.DUMMYFUNCTION("""COMPUTED_VALUE"""),"Aachen") -> Aachen | AM27: =IFERROR(__xludf.DUMMYFUNCTION("""COMPUTED_VALUE"""),"ZIU") -> ZIU | AN27: =IFERROR(__xludf.DUMMYFUNCTION("""COMPUTED_VALUE"""),"Railway") -> Railway | AO27: =IFERROR(__xludf.DUMMYFUNCTION("""COMPUTED_VALUE"""),"Germany") -> Germany
A28: TKT/ BP | B28: =IFERROR(__xludf.DUMMYFUNCTION("""COMPUTED_VALUE"""),"Yes") -> Yes | AC28: =IFERROR(__xludf.DUMMYFUNCTION("""COMPUTED_VALUE"""),"Alconbury") -> Alconbury | AD28: =IFERROR(__xludf.DUMMYFUNCTION("""COMPUTED_VALUE"""),"AYH") -> AYH | AE28: =IFERROR(__xludf.DUMMYFUNCTION("""COMPUTED_VALUE"""),"RAF Station") -> RAF Station | AF28: =IFERROR(__xludf.DUMMYFUNCTION("""COMPUTED_VALUE"""),"United Kingdom") -> United Kingdom | AL28: =IFERROR(__xludf.DUMMYFUNCTION("""COMPUTED_VALUE"""),"Aix La Chapelle") -> Aix La Chapelle | AM28: =IFERROR(__xludf.DUMMYFUNCTION("""COMPUTED_VALUE"""),"XHJ") -> XHJ | AN28: =IFERROR(__xludf.DUMMYFUNCTION("""COMPUTED_VALUE"""),"Railway Station") -> Railway Station | AO28: =IFERROR(__xludf.DUMMYFUNCTION("""COMPUTED_VALUE"""),"Germany") -> Germany
A29: ID | B29: =IFERROR(__xludf.DUMMYFUNCTION("""COMPUTED_VALUE"""),"No") -> No | AC29: =IFERROR(__xludf.DUMMYFUNCTION("""COMPUTED_VALUE"""),"Alderney") -> Alderney | AD29: =IFERROR(__xludf.DUMMYFUNCTION("""COMPUTED_VALUE"""),"ACI") -> ACI | AE29: =IFERROR(__xludf.DUMMYFUNCTION("""COMPUTED_VALUE"""),"The Blaye") -> The Blaye | AF29: =IFERROR(__xludf.DUMMYFUNCTION("""COMPUTED_VALUE"""),"United Kingdom") -> United Kingdom | AL29: =IFERROR(__xludf.DUMMYFUNCTION("""COMPUTED_VALUE"""),"Altenburg") -> Altenburg | AM29: =IFERROR(__xludf.DUMMYFUNCTION("""COMPUTED_VALUE"""),"AOC") -> AOC | AN29: =IFERROR(__xludf.DUMMYFUNCTION("""COMPUTED_VALUE"""),"Altenburg Nobitz") -> Altenburg Nobitz | AO29: =IFERROR(__xludf.DUMMYFUNCTION("""COMPUTED_VALUE"""),"Germany") -> Germany
A30: Claim Email | B30: =IFERROR(__xludf.DUMMYFUNCTION("""COMPUTED_VALUE"""),"Yes") -> Yes | AC30: =IFERROR(__xludf.DUMMYFUNCTION("""COMPUTED_VALUE"""),"Andover") -> Andover | AD30: =IFERROR(__xludf.DUMMYFUNCTION("""COMPUTED_VALUE"""),"ADV") -> ADV | AE30: =IFERROR(__xludf.DUMMYFUNCTION("""COMPUTED_VALUE"""),"Andover") -> Andover | AF30: =IFERROR(__xludf.DUMMYFUNCTION("""COMPUTED_VALUE"""),"United Kingdom") -> United Kingdom | AL30: =IFERROR(__xludf.DUMMYFUNCTION("""COMPUTED_VALUE"""),"Aue") -> Aue | AM30: =IFERROR(__xludf.DUMMYFUNCTION("""COMPUTED_VALUE"""),"ZAU") -> ZAU | AN30: =IFERROR(__xludf.DUMMYFUNCTION("""COMPUTED_VALUE"""),"Sachsen Railway Stn.") -> Sachsen Railway Stn. | AO30: =IFERROR(__xludf.DUMMYFUNCTION("""COMPUTED_VALUE"""),"Germany") -> Germany
A31: Rerouted Tkt (missed leg) | B31: =IFERROR(__xludf.DUMMYFUNCTION("""COMPUTED_VALUE"""),"Yes") -> Yes | AC31: =IFERROR(__xludf.DUMMYFUNCTION("""COMPUTED_VALUE"""),"Bally Kelly") -> Bally Kelly | AD31: =IFERROR(__xludf.DUMMYFUNCTION("""COMPUTED_VALUE"""),"BOL") -> BOL | AE31: =IFERROR(__xludf.DUMMYFUNCTION("""COMPUTED_VALUE"""),"Bally Kelly") -> Bally Kelly | AF31: =IFERROR(__xludf.DUMMYFUNCTION("""COMPUTED_VALUE"""),"United Kingdom") -> United Kingdom | AL31: =IFERROR(__xludf.DUMMYFUNCTION("""COMPUTED_VALUE"""),"Baltrum") -> Baltrum | AM31: =IFERROR(__xludf.DUMMYFUNCTION("""COMPUTED_VALUE"""),"BMR") -> BMR | AN31: =IFERROR(__xludf.DUMMYFUNCTION("""COMPUTED_VALUE"""),"Baltrum") -> Baltrum | AO31: =IFERROR(__xludf.DUMMYFUNCTION("""COMPUTED_VALUE"""),"Germany") -> Germany
A32: Disruption Proof | B32: =IFERROR(__xludf.DUMMYFUNCTION("""COMPUTED_VALUE"""),"No") -> No | AC32: =IFERROR(__xludf.DUMMYFUNCTION("""COMPUTED_VALUE"""),"Barra") -> Barra | AD32: =IFERROR(__xludf.DUMMYFUNCTION("""COMPUTED_VALUE"""),"BRR") -> BRR | AE32: =IFERROR(__xludf.DUMMYFUNCTION("""COMPUTED_VALUE"""),"North Bay") -> North Bay | AF32: =IFERROR(__xludf.DUMMYFUNCTION("""COMPUTED_VALUE"""),"United Kingdom") -> United Kingdom | AL32: =IFERROR(__xludf.DUMMYFUNCTION("""COMPUTED_VALUE"""),"Barth") -> Barth | AM32: =IFERROR(__xludf.DUMMYFUNCTION("""COMPUTED_VALUE"""),"BBH") -> BBH | AN32: =IFERROR(__xludf.DUMMYFUNCTION("""COMPUTED_VALUE"""),"Barth") -> Barth | AO32: =IFERROR(__xludf.DUMMYFUNCTION("""COMPUTED_VALUE"""),"Germany") -> Germany
A33: Note | B33: =IFERROR(__xludf.DUMMYFUNCTION("""COMPUTED_VALUE"""),"Goal: 100 claims a week No legal assessment necessary: we should only check the disruption and EOC Documents required: AF, BP/eticket, claim, proof of sending the claim to airline") -> Goal: 100 claims a week No legal assessment necessary: we should only check the disruption and EOC Documents required: AF, BP/eticket, claim, proof of sending the claim to airline | AC33: =IFERROR(__xludf.DUMMYFUNCTION("""COMPUTED_VALUE"""),"Barrow-In-Furness") -> Barrow-In-Furness | AD33: =IFERROR(__xludf.DUMMYFUNCTION("""COMPUTED_VALUE"""),"BWF") -> BWF | AE33: =IFERROR(__xludf.DUMMYFUNCTION("""COMPUTED_VALUE"""),"Walney Island") -> Walney Island | AF33: =IFERROR(__xludf.DUMMYFUNCTION("""COMPUTED_VALUE"""),"United Kingdom") -> United Kingdom | AL33: =IFERROR(__xludf.DUMMYFUNCTION("""COMPUTED_VALUE"""),"Bayreuth") -> Bayreuth | AM33: =IFERROR(__xludf.DUMMYFUNCTION("""COMPUTED_VALUE"""),"BYU") -> BYU | AN33: =IFERROR(__xludf.DUMMYFUNCTION("""COMPUTED_VALUE"""),"Bindlacher-Berg") -> Bindlacher-Berg | AO33: =IFERROR(__xludf.DUMMYFUNCTION("""COMPUTED_VALUE"""),"Germany") -> Germany
AC34: =IFERROR(__xludf.DUMMYFUNCTION("""COMPUTED_VALUE"""),"Belfast") -> Belfast | AD34: =IFERROR(__xludf.DUMMYFUNCTION("""COMPUTED_VALUE"""),"BHD") -> BHD | AE34: =IFERROR(__xludf.DUMMYFUNCTION("""COMPUTED_VALUE"""),"Belfast City Airport") -> Belfast City Airport | AF34: =IFERROR(__xludf.DUMMYFUNCTION("""COMPUTED_VALUE"""),"United Kingdom") -> United Kingdom | AL34: =IFERROR(__xludf.DUMMYFUNCTION("""COMPUTED_VALUE"""),"Berlin") -> Berlin | AM34: =IFERROR(__xludf.DUMMYFUNCTION("""COMPUTED_VALUE"""),"QWC") -> QWC | AN34: =IFERROR(__xludf.DUMMYFUNCTION("""COMPUTED_VALUE"""),"Berlin Zoo") -> Berlin Zoo | AO34: =IFERROR(__xludf.DUMMYFUNCTION("""COMPUTED_VALUE"""),"Germany") -> Germany
AC35: =IFERROR(__xludf.DUMMYFUNCTION("""COMPUTED_VALUE"""),"Belfast") -> Belfast | AD35: =IFERROR(__xludf.DUMMYFUNCTION("""COMPUTED_VALUE"""),"BFS") -> BFS | AE35: =IFERROR(__xludf.DUMMYFUNCTION("""COMPUTED_VALUE"""),"Belfast Aldergrove International") -> Belfast Aldergrove International | AF35: =IFERROR(__xludf.DUMMYFUNCTION("""COMPUTED_VALUE"""),"United Kingdom") -> United Kingdom | AL35: =IFERROR(__xludf.DUMMYFUNCTION("""COMPUTED_VALUE"""),"Berlin") -> Berlin | AM35: =IFERROR(__xludf.DUMMYFUNCTION("""COMPUTED_VALUE"""),"GWW") -> GWW | AN35: =IFERROR(__xludf.DUMMYFUNCTION("""COMPUTED_VALUE"""),"RAF Gatow") -> RAF Gatow | AO35: =IFERROR(__xludf.DUMMYFUNCTION("""COMPUTED_VALUE"""),"Germany") -> Germany
AC36: =IFERROR(__xludf.DUMMYFUNCTION("""COMPUTED_VALUE"""),"Bembridge") -> Bembridge | AD36: =IFERROR(__xludf.DUMMYFUNCTION("""COMPUTED_VALUE"""),"BBP") -> BBP | AE36: =IFERROR(__xludf.DUMMYFUNCTION("""COMPUTED_VALUE"""),"Bembridge") -> Bembridge | AF36: =IFERROR(__xludf.DUMMYFUNCTION("""COMPUTED_VALUE"""),"United Kingdom") -> United Kingdom | AL36: =IFERROR(__xludf.DUMMYFUNCTION("""COMPUTED_VALUE"""),"Berlin") -> Berlin | AM36: =IFERROR(__xludf.DUMMYFUNCTION("""COMPUTED_VALUE"""),"SXF") -> SXF | AN36: =IFERROR(__xludf.DUMMYFUNCTION("""COMPUTED_VALUE"""),"Schoenefeld") -> Schoenefeld | AO36: =IFERROR(__xludf.DUMMYFUNCTION("""COMPUTED_VALUE"""),"Germany") -> Germany
AC37: =IFERROR(__xludf.DUMMYFUNCTION("""COMPUTED_VALUE"""),"Benbecula") -> Benbecula | AD37: =IFERROR(__xludf.DUMMYFUNCTION("""COMPUTED_VALUE"""),"BEB") -> BEB | AE37: =IFERROR(__xludf.DUMMYFUNCTION("""COMPUTED_VALUE"""),"Benbecula") -> Benbecula | AF37: =IFERROR(__xludf.DUMMYFUNCTION("""COMPUTED_VALUE"""),"United Kingdom") -> United Kingdom | AL37: =IFERROR(__xludf.DUMMYFUNCTION("""COMPUTED_VALUE"""),"Berlin") -> Berlin | AM37: =IFERROR(__xludf.DUMMYFUNCTION("""COMPUTED_VALUE"""),"TXL") -> TXL | AN37: =IFERROR(__xludf.DUMMYFUNCTION("""COMPUTED_VALUE"""),"Tegel") -> Tegel | AO37: =IFERROR(__xludf.DUMMYFUNCTION("""COMPUTED_VALUE"""),"Germany") -> Germany
AC38: =IFERROR(__xludf.DUMMYFUNCTION("""COMPUTED_VALUE"""),"Benson") -> Benson | AD38: =IFERROR(__xludf.DUMMYFUNCTION("""COMPUTED_VALUE"""),"BEX") -> BEX | AE38: =IFERROR(__xludf.DUMMYFUNCTION("""COMPUTED_VALUE"""),"RAF Station") -> RAF Station | AF38: =IFERROR(__xludf.DUMMYFUNCTION("""COMPUTED_VALUE"""),"United Kingdom") -> United Kingdom | AL38: =IFERROR(__xludf.DUMMYFUNCTION("""COMPUTED_VALUE"""),"Berlin") -> Berlin | AM38: =IFERROR(__xludf.DUMMYFUNCTION("""COMPUTED_VALUE"""),"THF") -> THF | AN38: =IFERROR(__xludf.DUMMYFUNCTION("""COMPUTED_VALUE"""),"Tempelhof") -> Tempelhof | AO38: =IFERROR(__xludf.DUMMYFUNCTION("""COMPUTED_VALUE"""),"Germany") -> Germany
AC39: =IFERROR(__xludf.DUMMYFUNCTION("""COMPUTED_VALUE"""),"Birmingham") -> Birmingham | AD39: =IFERROR(__xludf.DUMMYFUNCTION("""COMPUTED_VALUE"""),"ZBC") -> ZBC | AE39: =IFERROR(__xludf.DUMMYFUNCTION("""COMPUTED_VALUE"""),"Colmore Row Bus Stn") -> Colmore Row Bus Stn | AF39: =IFERROR(__xludf.DUMMYFUNCTION("""COMPUTED_VALUE"""),"United Kingdom") -> United Kingdom | AL39: =IFERROR(__xludf.DUMMYFUNCTION("""COMPUTED_VALUE"""),"Bielefeld") -> Bielefeld | AM39: =IFERROR(__xludf.DUMMYFUNCTION("""COMPUTED_VALUE"""),"BFE") -> BFE | AN39: =IFERROR(__xludf.DUMMYFUNCTION("""COMPUTED_VALUE"""),"Bielefeld") -> Bielefeld | AO39: =IFERROR(__xludf.DUMMYFUNCTION("""COMPUTED_VALUE"""),"Germany") -> Germany
AC40: =IFERROR(__xludf.DUMMYFUNCTION("""COMPUTED_VALUE"""),"Birmingham") -> Birmingham | AD40: =IFERROR(__xludf.DUMMYFUNCTION("""COMPUTED_VALUE"""),"BHX") -> BHX | AE40: =IFERROR(__xludf.DUMMYFUNCTION("""COMPUTED_VALUE"""),"Birmingham International") -> Birmingham International | AF40: =IFERROR(__xludf.DUMMYFUNCTION("""COMPUTED_VALUE"""),"United Kingdom") -> United Kingdom | AL40: =IFERROR(__xludf.DUMMYFUNCTION("""COMPUTED_VALUE"""),"Bitburg") -> Bitburg | AM40: =IFERROR(__xludf.DUMMYFUNCTION("""COMPUTED_VALUE"""),"BBJ") -> BBJ | AN40: =IFERROR(__xludf.DUMMYFUNCTION("""COMPUTED_VALUE"""),"Bitburg Air Base") -> Bitburg Air Base | AO40: =IFERROR(__xludf.DUMMYFUNCTION("""COMPUTED_VALUE"""),"Germany") -> Germany
AC41: =IFERROR(__xludf.DUMMYFUNCTION("""COMPUTED_VALUE"""),"Yateley") -> Yateley | AD41: =IFERROR(__xludf.DUMMYFUNCTION("""COMPUTED_VALUE"""),"BBS") -> BBS | AE41: =IFERROR(__xludf.DUMMYFUNCTION("""COMPUTED_VALUE"""),"Blackbushe") -> Blackbushe | AF41: =IFERROR(__xludf.DUMMYFUNCTION("""COMPUTED_VALUE"""),"United Kingdom") -> United Kingdom | AL41: =IFERROR(__xludf.DUMMYFUNCTION("""COMPUTED_VALUE"""),"Boeblingen") -> Boeblingen | AM41: =IFERROR(__xludf.DUMMYFUNCTION("""COMPUTED_VALUE"""),"PHM") -> PHM | AN41: =IFERROR(__xludf.DUMMYFUNCTION("""COMPUTED_VALUE"""),"Boeblingen") -> Boeblingen | AO41: =IFERROR(__xludf.DUMMYFUNCTION("""COMPUTED_VALUE"""),"Germany") -> Germany
AC42: =IFERROR(__xludf.DUMMYFUNCTION("""COMPUTED_VALUE"""),"Blackpool") -> Blackpool | AD42: =IFERROR(__xludf.DUMMYFUNCTION("""COMPUTED_VALUE"""),"BLK") -> BLK | AE42: =IFERROR(__xludf.DUMMYFUNCTION("""COMPUTED_VALUE"""),"Blackpool") -> Blackpool | AF42: =IFERROR(__xludf.DUMMYFUNCTION("""COMPUTED_VALUE"""),"United Kingdom") -> United Kingdom | AL42: =IFERROR(__xludf.DUMMYFUNCTION("""COMPUTED_VALUE"""),"Borkum") -> Borkum | AM42: =IFERROR(__xludf.DUMMYFUNCTION("""COMPUTED_VALUE"""),"BMK") -> BMK | AN42: =IFERROR(__xludf.DUMMYFUNCTION("""COMPUTED_VALUE"""),"Borkum") -> Borkum | AO42: =IFERROR(__xludf.DUMMYFUNCTION("""COMPUTED_VALUE"""),"Germany") -> Germany
AC43: =IFERROR(__xludf.DUMMYFUNCTION("""COMPUTED_VALUE"""),"Bournemouth") -> Bournemouth | AD43: =IFERROR(__xludf.DUMMYFUNCTION("""COMPUTED_VALUE"""),"BOH") -> BOH | AE43: =IFERROR(__xludf.DUMMYFUNCTION("""COMPUTED_VALUE"""),"Bournemouth International") -> Bournemouth International | AF43: =IFERROR(__xludf.DUMMYFUNCTION("""COMPUTED_VALUE"""),"United Kingdom") -> United Kingdom | AL43: =IFERROR(__xludf.DUMMYFUNCTION("""COMPUTED_VALUE"""),"Braunschweig") -> Braunschweig | AM43: =IFERROR(__xludf.DUMMYFUNCTION("""COMPUTED_VALUE"""),"BWE") -> BWE | AN43: =IFERROR(__xludf.DUMMYFUNCTION("""COMPUTED_VALUE"""),"Braunschweig") -> Braunschweig | AO43: =IFERROR(__xludf.DUMMYFUNCTION("""COMPUTED_VALUE"""),"Germany") -> Germany
AC44: =IFERROR(__xludf.DUMMYFUNCTION("""COMPUTED_VALUE"""),"Bradford") -> Bradford | AD44: =IFERROR(__xludf.DUMMYFUNCTION("""COMPUTED_VALUE"""),"BRF") -> BRF | AE44: =IFERROR(__xludf.DUMMYFUNCTION("""COMPUTED_VALUE"""),"Bradford") -> Bradford | AF44: =IFERROR(__xludf.DUMMYFUNCTION("""COMPUTED_VALUE"""),"United Kingdom") -> United Kingdom | AL44: =IFERROR(__xludf.DUMMYFUNCTION("""COMPUTED_VALUE"""),"Bremen") -> Bremen | AM44: =IFERROR(__xludf.DUMMYFUNCTION("""COMPUTED_VALUE"""),"BRE") -> BRE | AN44: =IFERROR(__xludf.DUMMYFUNCTION("""COMPUTED_VALUE"""),"Bremen") -> Bremen | AO44: =IFERROR(__xludf.DUMMYFUNCTION("""COMPUTED_VALUE"""),"Germany") -> Germany
AC45: =IFERROR(__xludf.DUMMYFUNCTION("""COMPUTED_VALUE"""),"Bradford") -> Bradford | AD45: =IFERROR(__xludf.DUMMYFUNCTION("""COMPUTED_VALUE"""),"ZFC") -> ZFC | AE45: =IFERROR(__xludf.DUMMYFUNCTION("""COMPUTED_VALUE"""),"Bus Station") -> Bus Station | AF45: =IFERROR(__xludf.DUMMYFUNCTION("""COMPUTED_VALUE"""),"United Kingdom") -> United Kingdom | AL45: =IFERROR(__xludf.DUMMYFUNCTION("""COMPUTED_VALUE"""),"Bremerhaven") -> Bremerhaven | AM45: =IFERROR(__xludf.DUMMYFUNCTION("""COMPUTED_VALUE"""),"BRV") -> BRV | AN45: =IFERROR(__xludf.DUMMYFUNCTION("""COMPUTED_VALUE"""),"Bremerhaven") -> Bremerhaven | AO45: =IFERROR(__xludf.DUMMYFUNCTION("""COMPUTED_VALUE"""),"Germany") -> Germany
AC46: =IFERROR(__xludf.DUMMYFUNCTION("""COMPUTED_VALUE"""),"Braintree") -> Braintree | AD46: =IFERROR(__xludf.DUMMYFUNCTION("""COMPUTED_VALUE"""),"WXF") -> WXF | AE46: =IFERROR(__xludf.DUMMYFUNCTION("""COMPUTED_VALUE"""),"Wether Fld RAF") -> Wether Fld RAF | AF46: =IFERROR(__xludf.DUMMYFUNCTION("""COMPUTED_VALUE"""),"United Kingdom") -> United Kingdom | AL46: =IFERROR(__xludf.DUMMYFUNCTION("""COMPUTED_VALUE"""),"Brueggen") -> Brueggen | AM46: =IFERROR(__xludf.DUMMYFUNCTION("""COMPUTED_VALUE"""),"BGN") -> BGN | AN46: =IFERROR(__xludf.DUMMYFUNCTION("""COMPUTED_VALUE"""),"R.A.F.") -> R.A.F. | AO46: =IFERROR(__xludf.DUMMYFUNCTION("""COMPUTED_VALUE"""),"Germany") -> Germany
AC47: =IFERROR(__xludf.DUMMYFUNCTION("""COMPUTED_VALUE"""),"Brandon") -> Brandon | AD47: =IFERROR(__xludf.DUMMYFUNCTION("""COMPUTED_VALUE"""),"LKZ") -> LKZ | AE47: =IFERROR(__xludf.DUMMYFUNCTION("""COMPUTED_VALUE"""),"Lakenheath RAF") -> Lakenheath RAF | AF47: =IFERROR(__xludf.DUMMYFUNCTION("""COMPUTED_VALUE"""),"United Kingdom") -> United Kingdom | AL47: =IFERROR(__xludf.DUMMYFUNCTION("""COMPUTED_VALUE"""),"Burg Feuerstein") -> Burg Feuerstein | AM47: =IFERROR(__xludf.DUMMYFUNCTION("""COMPUTED_VALUE"""),"URD") -> URD | AN47: =IFERROR(__xludf.DUMMYFUNCTION("""COMPUTED_VALUE"""),"Burg Feuerstein") -> Burg Feuerstein | AO47: =IFERROR(__xludf.DUMMYFUNCTION("""COMPUTED_VALUE"""),"Germany") -> Germany
AC48: =IFERROR(__xludf.DUMMYFUNCTION("""COMPUTED_VALUE"""),"Brighton") -> Brighton | AD48: =IFERROR(__xludf.DUMMYFUNCTION("""COMPUTED_VALUE"""),"BSH") -> BSH | AE48: =IFERROR(__xludf.DUMMYFUNCTION("""COMPUTED_VALUE"""),"Brighton") -> Brighton | AF48: =IFERROR(__xludf.DUMMYFUNCTION("""COMPUTED_VALUE"""),"United Kingdom") -> United Kingdom | AL48: =IFERROR(__xludf.DUMMYFUNCTION("""COMPUTED_VALUE"""),"Chemnitz") -> Chemnitz | AM48: =IFERROR(__xludf.DUMMYFUNCTION("""COMPUTED_VALUE"""),"ZTZ") -> ZTZ | AN48: =IFERROR(__xludf.DUMMYFUNCTION("""COMPUTED_VALUE"""),"Chemnitz Railway Stn.") -> Chemnitz Railway Stn. | AO48: =IFERROR(__xludf.DUMMYFUNCTION("""COMPUTED_VALUE"""),"Germany") -> Germany
AC49: =IFERROR(__xludf.DUMMYFUNCTION("""COMPUTED_VALUE"""),"Bristol") -> Bristol | AD49: =IFERROR(__xludf.DUMMYFUNCTION("""COMPUTED_VALUE"""),"BRS") -> BRS | AE49: =IFERROR(__xludf.DUMMYFUNCTION("""COMPUTED_VALUE"""),"Bristol") -> Bristol | AF49: =IFERROR(__xludf.DUMMYFUNCTION("""COMPUTED_VALUE"""),"United Kingdom") -> United Kingdom | AL49: =IFERROR(__xludf.DUMMYFUNCTION("""COMPUTED_VALUE"""),"Cochstedt") -> Cochstedt | AM49: =IFERROR(__xludf.DUMMYFUNCTION("""COMPUTED_VALUE"""),"CSO") -> CSO | AN49: =IFERROR(__xludf.DUMMYFUNCTION("""COMPUTED_VALUE"""),"Cochstedt") -> Cochstedt | AO49: =IFERROR(__xludf.DUMMYFUNCTION("""COMPUTED_VALUE"""),"Germany") -> Germany
AC50: =IFERROR(__xludf.DUMMYFUNCTION("""COMPUTED_VALUE"""),"Britrail Rail Zone S") -> Britrail Rail Zone S | AD50: =IFERROR(__xludf.DUMMYFUNCTION("""COMPUTED_VALUE"""),"QQS") -> QQS | AE50: =IFERROR(__xludf.DUMMYFUNCTION("""COMPUTED_VALUE"""),"London St. Pancras") -> London St. Pancras | AF50: =IFERROR(__xludf.DUMMYFUNCTION("""COMPUTED_VALUE"""),"United Kingdom") -> United Kingdom | AL50: =IFERROR(__xludf.DUMMYFUNCTION("""COMPUTED_VALUE"""),"Cologne") -> Cologne | AM50: =IFERROR(__xludf.DUMMYFUNCTION("""COMPUTED_VALUE"""),"CGN") -> CGN | AN50: =IFERROR(__xludf.DUMMYFUNCTION("""COMPUTED_VALUE"""),"Cologne/bonn") -> Cologne/bonn | AO50: =IFERROR(__xludf.DUMMYFUNCTION("""COMPUTED_VALUE"""),"Germany") -> Germany
AC51: =IFERROR(__xludf.DUMMYFUNCTION("""COMPUTED_VALUE"""),"Brize Norton") -> Brize Norton | AD51: =IFERROR(__xludf.DUMMYFUNCTION("""COMPUTED_VALUE"""),"BZZ") -> BZZ | AE51: =IFERROR(__xludf.DUMMYFUNCTION("""COMPUTED_VALUE"""),"Raf Station") -> Raf Station | AF51: =IFERROR(__xludf.DUMMYFUNCTION("""COMPUTED_VALUE"""),"United Kingdom") -> United Kingdom | AL51: =IFERROR(__xludf.DUMMYFUNCTION("""COMPUTED_VALUE"""),"Cottbus") -> Cottbus | AM51: =IFERROR(__xludf.DUMMYFUNCTION("""COMPUTED_VALUE"""),"CBU") -> CBU | AN51: =IFERROR(__xludf.DUMMYFUNCTION("""COMPUTED_VALUE"""),"Cottbus") -> Cottbus | AO51: =IFERROR(__xludf.DUMMYFUNCTION("""COMPUTED_VALUE"""),"Germany") -> Germany
AC52: =IFERROR(__xludf.DUMMYFUNCTION("""COMPUTED_VALUE"""),"Burtonwood") -> Burtonwood | AD52: =IFERROR(__xludf.DUMMYFUNCTION("""COMPUTED_VALUE"""),"BUT") -> BUT | AE52: =IFERROR(__xludf.DUMMYFUNCTION("""COMPUTED_VALUE"""),"Burtonwood") -> Burtonwood | AF52: =IFERROR(__xludf.DUMMYFUNCTION("""COMPUTED_VALUE"""),"United Kingdom") -> United Kingdom | AL52: =IFERROR(__xludf.DUMMYFUNCTION("""COMPUTED_VALUE"""),"Cottbus") -> Cottbus | AM52: =IFERROR(__xludf.DUMMYFUNCTION("""COMPUTED_VALUE"""),"ZTT") -> ZTT | AN52: =IFERROR(__xludf.DUMMYFUNCTION("""COMPUTED_VALUE"""),"Cottbus Railway Stn.") -> Cottbus Railway Stn. | AO52: =IFERROR(__xludf.DUMMYFUNCTION("""COMPUTED_VALUE"""),"Germany") -> Germany
AC53: =IFERROR(__xludf.DUMMYFUNCTION("""COMPUTED_VALUE"""),"Bury St Edmunds") -> Bury St Edmunds | AD53: =IFERROR(__xludf.DUMMYFUNCTION("""COMPUTED_VALUE"""),"BEQ") -> BEQ | AE53: =IFERROR(__xludf.DUMMYFUNCTION("""COMPUTED_VALUE"""),"Honington") -> Honington | AF53: =IFERROR(__xludf.DUMMYFUNCTION("""COMPUTED_VALUE"""),"United Kingdom") -> United Kingdom | AL53: =IFERROR(__xludf.DUMMYFUNCTION("""COMPUTED_VALUE"""),"Cuxhaven") -> Cuxhaven | AM53: =IFERROR(__xludf.DUMMYFUNCTION("""COMPUTED_VALUE"""),"FCN") -> FCN | AN53: =IFERROR(__xludf.DUMMYFUNCTION("""COMPUTED_VALUE"""),"Cuxhaven/Nordholz") -> Cuxhaven/Nordholz | AO53: =IFERROR(__xludf.DUMMYFUNCTION("""COMPUTED_VALUE"""),"Germany") -> Germany
AC54: =IFERROR(__xludf.DUMMYFUNCTION("""COMPUTED_VALUE"""),"Cambridge") -> Cambridge | AD54: =IFERROR(__xludf.DUMMYFUNCTION("""COMPUTED_VALUE"""),"CBG") -> CBG | AE54: =IFERROR(__xludf.DUMMYFUNCTION("""COMPUTED_VALUE"""),"Cambridge") -> Cambridge | AF54: =IFERROR(__xludf.DUMMYFUNCTION("""COMPUTED_VALUE"""),"United Kingdom") -> United Kingdom | AL54: =IFERROR(__xludf.DUMMYFUNCTION("""COMPUTED_VALUE"""),"Dessau") -> Dessau | AM54: =IFERROR(__xludf.DUMMYFUNCTION("""COMPUTED_VALUE"""),"ZSU") -> ZSU | AN54: =IFERROR(__xludf.DUMMYFUNCTION("""COMPUTED_VALUE"""),"Dessau Railway Stn.") -> Dessau Railway Stn. | AO54: =IFERROR(__xludf.DUMMYFUNCTION("""COMPUTED_VALUE"""),"Germany") -> Germany
AC55: =IFERROR(__xludf.DUMMYFUNCTION("""COMPUTED_VALUE"""),"Campbeltown") -> Campbeltown | AD55: =IFERROR(__xludf.DUMMYFUNCTION("""COMPUTED_VALUE"""),"CAL") -> CAL | AE55: =IFERROR(__xludf.DUMMYFUNCTION("""COMPUTED_VALUE"""),"Machrihanish") -> Machrihanish | AF55: =IFERROR(__xludf.DUMMYFUNCTION("""COMPUTED_VALUE"""),"United Kingdom") -> United Kingdom | AL55: =IFERROR(__xludf.DUMMYFUNCTION("""COMPUTED_VALUE"""),"Dortmund") -> Dortmund | AM55: =IFERROR(__xludf.DUMMYFUNCTION("""COMPUTED_VALUE"""),"DTM") -> DTM | AN55: =IFERROR(__xludf.DUMMYFUNCTION("""COMPUTED_VALUE"""),"Dortmund") -> Dortmund | AO55: =IFERROR(__xludf.DUMMYFUNCTION("""COMPUTED_VALUE"""),"Germany") -> Germany
AC56: =IFERROR(__xludf.DUMMYFUNCTION("""COMPUTED_VALUE"""),"Cardiff") -> Cardiff | AD56: =IFERROR(__xludf.DUMMYFUNCTION("""COMPUTED_VALUE"""),"CWL") -> CWL | AE56: =IFERROR(__xludf.DUMMYFUNCTION("""COMPUTED_VALUE"""),"Cardiff-wales Arpt") -> Cardiff-wales Arpt | AF56: =IFERROR(__xludf.DUMMYFUNCTION("""COMPUTED_VALUE"""),"United Kingdom") -> United Kingdom | AL56: =IFERROR(__xludf.DUMMYFUNCTION("""COMPUTED_VALUE"""),"Dresden") -> Dresden | AM56: =IFERROR(__xludf.DUMMYFUNCTION("""COMPUTED_VALUE"""),"DRS") -> DRS | AN56: =IFERROR(__xludf.DUMMYFUNCTION("""COMPUTED_VALUE"""),"Dresden Arpt") -> Dresden Arpt | AO56: =IFERROR(__xludf.DUMMYFUNCTION("""COMPUTED_VALUE"""),"Germany") -> Germany
AC57: =IFERROR(__xludf.DUMMYFUNCTION("""COMPUTED_VALUE"""),"Carlisle") -> Carlisle | AD57: =IFERROR(__xludf.DUMMYFUNCTION("""COMPUTED_VALUE"""),"CAX") -> CAX | AE57: =IFERROR(__xludf.DUMMYFUNCTION("""COMPUTED_VALUE"""),"Carlisle") -> Carlisle | AF57: =IFERROR(__xludf.DUMMYFUNCTION("""COMPUTED_VALUE"""),"United Kingdom") -> United Kingdom | AL57: =IFERROR(__xludf.DUMMYFUNCTION("""COMPUTED_VALUE"""),"Dusseldorf") -> Dusseldorf | AM57: =IFERROR(__xludf.DUMMYFUNCTION("""COMPUTED_VALUE"""),"DUS") -> DUS | AN57: =IFERROR(__xludf.DUMMYFUNCTION("""COMPUTED_VALUE"""),"Düsseldorf International Airport (Rhein-Ruhr)") -> Düsseldorf International Airport (Rhein-Ruhr) | AO57: =IFERROR(__xludf.DUMMYFUNCTION("""COMPUTED_VALUE"""),"Germany") -> Germany
AC58: =IFERROR(__xludf.DUMMYFUNCTION("""COMPUTED_VALUE"""),"Chester") -> Chester | AD58: =IFERROR(__xludf.DUMMYFUNCTION("""COMPUTED_VALUE"""),"CEG") -> CEG | AE58: =IFERROR(__xludf.DUMMYFUNCTION("""COMPUTED_VALUE"""),"Chester") -> Chester | AF58: =IFERROR(__xludf.DUMMYFUNCTION("""COMPUTED_VALUE"""),"United Kingdom") -> United Kingdom | AL58: =IFERROR(__xludf.DUMMYFUNCTION("""COMPUTED_VALUE"""),"Dusseldorf") -> Dusseldorf | AM58: =IFERROR(__xludf.DUMMYFUNCTION("""COMPUTED_VALUE"""),"MGL") -> MGL | AN58: =IFERROR(__xludf.DUMMYFUNCTION("""COMPUTED_VALUE"""),"Moenchen-Gl. - DUS Exp") -> Moenchen-Gl. - DUS Exp | AO58: =IFERROR(__xludf.DUMMYFUNCTION("""COMPUTED_VALUE"""),"Germany") -> Germany
AC59: =IFERROR(__xludf.DUMMYFUNCTION("""COMPUTED_VALUE"""),"Isle Of Coll") -> Isle Of Coll | AD59: =IFERROR(__xludf.DUMMYFUNCTION("""COMPUTED_VALUE"""),"COL") -> COL | AE59: =IFERROR(__xludf.DUMMYFUNCTION("""COMPUTED_VALUE"""),"Isle Of Coll") -> Isle Of Coll | AF59: =IFERROR(__xludf.DUMMYFUNCTION("""COMPUTED_VALUE"""),"United Kingdom") -> United Kingdom | AL59: =IFERROR(__xludf.DUMMYFUNCTION("""COMPUTED_VALUE"""),"Dusseldorf") -> Dusseldorf | AM59: =IFERROR(__xludf.DUMMYFUNCTION("""COMPUTED_VALUE"""),"NRN") -> NRN | AN59: =IFERROR(__xludf.DUMMYFUNCTION("""COMPUTED_VALUE"""),"Weeze") -> Weeze | AO59: =IFERROR(__xludf.DUMMYFUNCTION("""COMPUTED_VALUE"""),"Germany") -> Germany
AC60: =IFERROR(__xludf.DUMMYFUNCTION("""COMPUTED_VALUE"""),"Isle Of Colonsay") -> Isle Of Colonsay | AD60: =IFERROR(__xludf.DUMMYFUNCTION("""COMPUTED_VALUE"""),"CSA") -> CSA | AE60: =IFERROR(__xludf.DUMMYFUNCTION("""COMPUTED_VALUE"""),"Isle Of Colonsay") -> Isle Of Colonsay | AF60: =IFERROR(__xludf.DUMMYFUNCTION("""COMPUTED_VALUE"""),"United Kingdom") -> United Kingdom | AL60: =IFERROR(__xludf.DUMMYFUNCTION("""COMPUTED_VALUE"""),"Dusseldorf") -> Dusseldorf | AM60: =IFERROR(__xludf.DUMMYFUNCTION("""COMPUTED_VALUE"""),"QDU") -> QDU | AN60: =IFERROR(__xludf.DUMMYFUNCTION("""COMPUTED_VALUE"""),"Station") -> Station | AO60: =IFERROR(__xludf.DUMMYFUNCTION("""COMPUTED_VALUE"""),"Germany") -> Germany
AC61: =IFERROR(__xludf.DUMMYFUNCTION("""COMPUTED_VALUE"""),"Coventry") -> Coventry | AD61: =IFERROR(__xludf.DUMMYFUNCTION("""COMPUTED_VALUE"""),"CVT") -> CVT | AE61: =IFERROR(__xludf.DUMMYFUNCTION("""COMPUTED_VALUE"""),"Coventry - West Midlands International Airport") -> Coventry - West Midlands International Airport | AF61: =IFERROR(__xludf.DUMMYFUNCTION("""COMPUTED_VALUE"""),"United Kingdom") -> United Kingdom | AL61: =IFERROR(__xludf.DUMMYFUNCTION("""COMPUTED_VALUE"""),"Eisenach") -> Eisenach | AM61: =IFERROR(__xludf.DUMMYFUNCTION("""COMPUTED_VALUE"""),"EIB") -> EIB | AN61: =IFERROR(__xludf.DUMMYFUNCTION("""COMPUTED_VALUE"""),"Eisenach") -> Eisenach | AO61: =IFERROR(__xludf.DUMMYFUNCTION("""COMPUTED_VALUE"""),"Germany") -> Germany
AC62: =IFERROR(__xludf.DUMMYFUNCTION("""COMPUTED_VALUE"""),"Cromarty") -> Cromarty | AD62: =IFERROR(__xludf.DUMMYFUNCTION("""COMPUTED_VALUE"""),"CRN") -> CRN | AE62: =IFERROR(__xludf.DUMMYFUNCTION("""COMPUTED_VALUE"""),"Cromarty") -> Cromarty | AF62: =IFERROR(__xludf.DUMMYFUNCTION("""COMPUTED_VALUE"""),"United Kingdom") -> United Kingdom | AL62: =IFERROR(__xludf.DUMMYFUNCTION("""COMPUTED_VALUE"""),"Emden") -> Emden | AM62: =IFERROR(__xludf.DUMMYFUNCTION("""COMPUTED_VALUE"""),"EME") -> EME | AN62: =IFERROR(__xludf.DUMMYFUNCTION("""COMPUTED_VALUE"""),"Emden") -> Emden | AO62: =IFERROR(__xludf.DUMMYFUNCTION("""COMPUTED_VALUE"""),"Germany") -> Germany
AC63: =IFERROR(__xludf.DUMMYFUNCTION("""COMPUTED_VALUE"""),"Dewsbury") -> Dewsbury | AD63: =IFERROR(__xludf.DUMMYFUNCTION("""COMPUTED_VALUE"""),"ZEQ") -> ZEQ | AE63: =IFERROR(__xludf.DUMMYFUNCTION("""COMPUTED_VALUE"""),"Bus Station") -> Bus Station | AF63: =IFERROR(__xludf.DUMMYFUNCTION("""COMPUTED_VALUE"""),"United Kingdom") -> United Kingdom | AL63: =IFERROR(__xludf.DUMMYFUNCTION("""COMPUTED_VALUE"""),"Erfurt") -> Erfurt | AM63: =IFERROR(__xludf.DUMMYFUNCTION("""COMPUTED_VALUE"""),"ERF") -> ERF | AN63: =IFERROR(__xludf.DUMMYFUNCTION("""COMPUTED_VALUE"""),"Erfurt") -> Erfurt | AO63: =IFERROR(__xludf.DUMMYFUNCTION("""COMPUTED_VALUE"""),"Germany") -> Germany
AC64: =IFERROR(__xludf.DUMMYFUNCTION("""COMPUTED_VALUE"""),"Doncaster") -> Doncaster | AD64: =IFERROR(__xludf.DUMMYFUNCTION("""COMPUTED_VALUE"""),"DSA") -> DSA | AE64: =IFERROR(__xludf.DUMMYFUNCTION("""COMPUTED_VALUE"""),"Robin Hood International") -> Robin Hood International | AF64: =IFERROR(__xludf.DUMMYFUNCTION("""COMPUTED_VALUE"""),"United Kingdom") -> United Kingdom | AL64: =IFERROR(__xludf.DUMMYFUNCTION("""COMPUTED_VALUE"""),"Essen") -> Essen | AM64: =IFERROR(__xludf.DUMMYFUNCTION("""COMPUTED_VALUE"""),"ESS") -> ESS | AN64: =IFERROR(__xludf.DUMMYFUNCTION("""COMPUTED_VALUE"""),"Essen") -> Essen | AO64: =IFERROR(__xludf.DUMMYFUNCTION("""COMPUTED_VALUE"""),"Germany") -> Germany
AC65: =IFERROR(__xludf.DUMMYFUNCTION("""COMPUTED_VALUE"""),"Dornoch") -> Dornoch | AD65: =IFERROR(__xludf.DUMMYFUNCTION("""COMPUTED_VALUE"""),"DOC") -> DOC | AE65: =IFERROR(__xludf.DUMMYFUNCTION("""COMPUTED_VALUE"""),"Dornoch") -> Dornoch | AF65: =IFERROR(__xludf.DUMMYFUNCTION("""COMPUTED_VALUE"""),"United Kingdom") -> United Kingdom | AL65: =IFERROR(__xludf.DUMMYFUNCTION("""COMPUTED_VALUE"""),"Fictitious Point/AA2") -> Fictitious Point/AA2 | AM65: =IFERROR(__xludf.DUMMYFUNCTION("""COMPUTED_VALUE"""),"ZGZ") -> ZGZ | AN65: =IFERROR(__xludf.DUMMYFUNCTION("""COMPUTED_VALUE"""),"GermanRail Pass") -> GermanRail Pass | AO65: =IFERROR(__xludf.DUMMYFUNCTION("""COMPUTED_VALUE"""),"Germany") -> Germany
AC66: =IFERROR(__xludf.DUMMYFUNCTION("""COMPUTED_VALUE"""),"Dundee") -> Dundee | AD66: =IFERROR(__xludf.DUMMYFUNCTION("""COMPUTED_VALUE"""),"DND") -> DND | AE66: =IFERROR(__xludf.DUMMYFUNCTION("""COMPUTED_VALUE"""),"Dundee") -> Dundee | AF66: =IFERROR(__xludf.DUMMYFUNCTION("""COMPUTED_VALUE"""),"United Kingdom") -> United Kingdom | AL66: =IFERROR(__xludf.DUMMYFUNCTION("""COMPUTED_VALUE"""),"Fictitious Point/LH") -> Fictitious Point/LH | AM66: =IFERROR(__xludf.DUMMYFUNCTION("""COMPUTED_VALUE"""),"QFP") -> QFP | AN66: =IFERROR(__xludf.DUMMYFUNCTION("""COMPUTED_VALUE"""),"Fictitious Point/LH") -> Fictitious Point/LH | AO66: =IFERROR(__xludf.DUMMYFUNCTION("""COMPUTED_VALUE"""),"Germany") -> Germany
AC67: =IFERROR(__xludf.DUMMYFUNCTION("""COMPUTED_VALUE"""),"Dundee") -> Dundee | AD67: =IFERROR(__xludf.DUMMYFUNCTION("""COMPUTED_VALUE"""),"ZDU") -> ZDU | AE67: =IFERROR(__xludf.DUMMYFUNCTION("""COMPUTED_VALUE"""),"ScotRail") -> ScotRail | AF67: =IFERROR(__xludf.DUMMYFUNCTION("""COMPUTED_VALUE"""),"United Kingdom") -> United Kingdom | AL67: =IFERROR(__xludf.DUMMYFUNCTION("""COMPUTED_VALUE"""),"Hamburg") -> Hamburg | AM67: =IFERROR(__xludf.DUMMYFUNCTION("""COMPUTED_VALUE"""),"XFW") -> XFW | AN67: =IFERROR(__xludf.DUMMYFUNCTION("""COMPUTED_VALUE"""),"Finkenwerder") -> Finkenwerder | AO67: =IFERROR(__xludf.DUMMYFUNCTION("""COMPUTED_VALUE"""),"Germany") -> Germany
AC68: =IFERROR(__xludf.DUMMYFUNCTION("""COMPUTED_VALUE"""),"Durham Tees Valley") -> Durham Tees Valley | AD68: =IFERROR(__xludf.DUMMYFUNCTION("""COMPUTED_VALUE"""),"MME") -> MME | AE68: =IFERROR(__xludf.DUMMYFUNCTION("""COMPUTED_VALUE"""),"Durham Tees Valley") -> Durham Tees Valley | AF68: =IFERROR(__xludf.DUMMYFUNCTION("""COMPUTED_VALUE"""),"United Kingdom") -> United Kingdom | AL68: =IFERROR(__xludf.DUMMYFUNCTION("""COMPUTED_VALUE"""),"Flensburg") -> Flensburg | AM68: =IFERROR(__xludf.DUMMYFUNCTION("""COMPUTED_VALUE"""),"FLF") -> FLF | AN68: =IFERROR(__xludf.DUMMYFUNCTION("""COMPUTED_VALUE"""),"Schaferhaus") -> Schaferhaus | AO68: =IFERROR(__xludf.DUMMYFUNCTION("""COMPUTED_VALUE"""),"Germany") -> Germany
AC69: =IFERROR(__xludf.DUMMYFUNCTION("""COMPUTED_VALUE"""),"Eday") -> Eday | AD69: =IFERROR(__xludf.DUMMYFUNCTION("""COMPUTED_VALUE"""),"EOI") -> EOI | AE69: =IFERROR(__xludf.DUMMYFUNCTION("""COMPUTED_VALUE"""),"Eday") -> Eday | AF69: =IFERROR(__xludf.DUMMYFUNCTION("""COMPUTED_VALUE"""),"United Kingdom") -> United Kingdom | AL69: =IFERROR(__xludf.DUMMYFUNCTION("""COMPUTED_VALUE"""),"Hahn") -> Hahn | AM69: =IFERROR(__xludf.DUMMYFUNCTION("""COMPUTED_VALUE"""),"HHN") -> HHN | AN69: =IFERROR(__xludf.DUMMYFUNCTION("""COMPUTED_VALUE"""),"Hahn") -> Hahn | AO69: =IFERROR(__xludf.DUMMYFUNCTION("""COMPUTED_VALUE"""),"Germany") -> Germany
AC70: =IFERROR(__xludf.DUMMYFUNCTION("""COMPUTED_VALUE"""),"Edinburgh") -> Edinburgh | AD70: =IFERROR(__xludf.DUMMYFUNCTION("""COMPUTED_VALUE"""),"EDI") -> EDI | AE70: =IFERROR(__xludf.DUMMYFUNCTION("""COMPUTED_VALUE"""),"Turnhouse") -> Turnhouse | AF70: =IFERROR(__xludf.DUMMYFUNCTION("""COMPUTED_VALUE"""),"United Kingdom") -> United Kingdom | AL70: =IFERROR(__xludf.DUMMYFUNCTION("""COMPUTED_VALUE"""),"Frankfurt") -> Frankfurt | AM70: =IFERROR(__xludf.DUMMYFUNCTION("""COMPUTED_VALUE"""),"FRA") -> FRA | AN70: =IFERROR(__xludf.DUMMYFUNCTION("""COMPUTED_VALUE"""),"Frankfurt International Airport (Rhein-Main)") -> Frankfurt International Airport (Rhein-Main) | AO70: =IFERROR(__xludf.DUMMYFUNCTION("""COMPUTED_VALUE"""),"Germany") -> Germany
AC71: =IFERROR(__xludf.DUMMYFUNCTION("""COMPUTED_VALUE"""),"Edinburgh") -> Edinburgh | AD71: =IFERROR(__xludf.DUMMYFUNCTION("""COMPUTED_VALUE"""),"ZXE") -> ZXE | AE71: =IFERROR(__xludf.DUMMYFUNCTION("""COMPUTED_VALUE"""),"ScotRail") -> ScotRail | AF71: =IFERROR(__xludf.DUMMYFUNCTION("""COMPUTED_VALUE"""),"United Kingdom") -> United Kingdom | AL71: =IFERROR(__xludf.DUMMYFUNCTION("""COMPUTED_VALUE"""),"Frankfurt") -> Frankfurt | AM71: =IFERROR(__xludf.DUMMYFUNCTION("""COMPUTED_VALUE"""),"QGV") -> QGV | AN71: =IFERROR(__xludf.DUMMYFUNCTION("""COMPUTED_VALUE"""),"Neu Isenburg") -> Neu Isenburg | AO71: =IFERROR(__xludf.DUMMYFUNCTION("""COMPUTED_VALUE"""),"Germany") -> Germany
AC72: =IFERROR(__xludf.DUMMYFUNCTION("""COMPUTED_VALUE"""),"Enniskillen") -> Enniskillen | AD72: =IFERROR(__xludf.DUMMYFUNCTION("""COMPUTED_VALUE"""),"ENK") -> ENK | AE72: =IFERROR(__xludf.DUMMYFUNCTION("""COMPUTED_VALUE"""),"Enniskillen") -> Enniskillen | AF72: =IFERROR(__xludf.DUMMYFUNCTION("""COMPUTED_VALUE"""),"United Kingdom") -> United Kingdom | AL72: =IFERROR(__xludf.DUMMYFUNCTION("""COMPUTED_VALUE"""),"Frankfurt") -> Frankfurt | AM72: =IFERROR(__xludf.DUMMYFUNCTION("""COMPUTED_VALUE"""),"FRF") -> FRF | AN72: =IFERROR(__xludf.DUMMYFUNCTION("""COMPUTED_VALUE"""),"Rhein-Main AFB") -> Rhein-Main AFB | AO72: =IFERROR(__xludf.DUMMYFUNCTION("""COMPUTED_VALUE"""),"Germany") -> Germany
AC73: =IFERROR(__xludf.DUMMYFUNCTION("""COMPUTED_VALUE"""),"Exeter") -> Exeter | AD73: =IFERROR(__xludf.DUMMYFUNCTION("""COMPUTED_VALUE"""),"EXT") -> EXT | AE73: =IFERROR(__xludf.DUMMYFUNCTION("""COMPUTED_VALUE"""),"Exeter") -> Exeter | AF73: =IFERROR(__xludf.DUMMYFUNCTION("""COMPUTED_VALUE"""),"United Kingdom") -> United Kingdom | AL73: =IFERROR(__xludf.DUMMYFUNCTION("""COMPUTED_VALUE"""),"Frankfurt/Oder") -> Frankfurt/Oder | AM73: =IFERROR(__xludf.DUMMYFUNCTION("""COMPUTED_VALUE"""),"ZFR") -> ZFR | AN73: =IFERROR(__xludf.DUMMYFUNCTION("""COMPUTED_VALUE"""),"Frankfurt/Oder Railway") -> Frankfurt/Oder Railway | AO73: =IFERROR(__xludf.DUMMYFUNCTION("""COMPUTED_VALUE"""),"Germany") -> Germany
AC74: =IFERROR(__xludf.DUMMYFUNCTION("""COMPUTED_VALUE"""),"Fair Isle") -> Fair Isle | AD74: =IFERROR(__xludf.DUMMYFUNCTION("""COMPUTED_VALUE"""),"FIE") -> FIE | AE74: =IFERROR(__xludf.DUMMYFUNCTION("""COMPUTED_VALUE"""),"Fair Isle") -> Fair Isle | AF74: =IFERROR(__xludf.DUMMYFUNCTION("""COMPUTED_VALUE"""),"United Kingdom") -> United Kingdom | AL74: =IFERROR(__xludf.DUMMYFUNCTION("""COMPUTED_VALUE"""),"Friedrichshafen") -> Friedrichshafen | AM74: =IFERROR(__xludf.DUMMYFUNCTION("""COMPUTED_VALUE"""),"FDH") -> FDH | AN74: =IFERROR(__xludf.DUMMYFUNCTION("""COMPUTED_VALUE"""),"Friedrichshafen") -> Friedrichshafen | AO74: =IFERROR(__xludf.DUMMYFUNCTION("""COMPUTED_VALUE"""),"Germany") -> Germany
AC75: =IFERROR(__xludf.DUMMYFUNCTION("""COMPUTED_VALUE"""),"Fairford") -> Fairford | AD75: =IFERROR(__xludf.DUMMYFUNCTION("""COMPUTED_VALUE"""),"FFD") -> FFD | AE75: =IFERROR(__xludf.DUMMYFUNCTION("""COMPUTED_VALUE"""),"RAF Station") -> RAF Station | AF75: =IFERROR(__xludf.DUMMYFUNCTION("""COMPUTED_VALUE"""),"United Kingdom") -> United Kingdom | AL75: =IFERROR(__xludf.DUMMYFUNCTION("""COMPUTED_VALUE"""),"Fritzlar") -> Fritzlar | AM75: =IFERROR(__xludf.DUMMYFUNCTION("""COMPUTED_VALUE"""),"FRZ") -> FRZ | AN75: =IFERROR(__xludf.DUMMYFUNCTION("""COMPUTED_VALUE"""),"Fritzlar Airbase") -> Fritzlar Airbase | AO75: =IFERROR(__xludf.DUMMYFUNCTION("""COMPUTED_VALUE"""),"Germany") -> Germany
AC76: =IFERROR(__xludf.DUMMYFUNCTION("""COMPUTED_VALUE"""),"Fakenham") -> Fakenham | AD76: =IFERROR(__xludf.DUMMYFUNCTION("""COMPUTED_VALUE"""),"FKH") -> FKH | AE76: =IFERROR(__xludf.DUMMYFUNCTION("""COMPUTED_VALUE"""),"Sculthorp RAF") -> Sculthorp RAF | AF76: =IFERROR(__xludf.DUMMYFUNCTION("""COMPUTED_VALUE"""),"United Kingdom") -> United Kingdom | AL76: =IFERROR(__xludf.DUMMYFUNCTION("""COMPUTED_VALUE"""),"Fuerstenfeldbruck") -> Fuerstenfeldbruck | AM76: =IFERROR(__xludf.DUMMYFUNCTION("""COMPUTED_VALUE"""),"FEL") -> FEL | AN76: =IFERROR(__xludf.DUMMYFUNCTION("""COMPUTED_VALUE"""),"Fuerstenfeldbruck") -> Fuerstenfeldbruck | AO76: =IFERROR(__xludf.DUMMYFUNCTION("""COMPUTED_VALUE"""),"Germany") -> Germany
AC77: =IFERROR(__xludf.DUMMYFUNCTION("""COMPUTED_VALUE"""),"Farnborough") -> Farnborough | AD77: =IFERROR(__xludf.DUMMYFUNCTION("""COMPUTED_VALUE"""),"FAB") -> FAB | AE77: =IFERROR(__xludf.DUMMYFUNCTION("""COMPUTED_VALUE"""),"Farnborough") -> Farnborough | AF77: =IFERROR(__xludf.DUMMYFUNCTION("""COMPUTED_VALUE"""),"United Kingdom") -> United Kingdom | AL77: =IFERROR(__xludf.DUMMYFUNCTION("""COMPUTED_VALUE"""),"Geilenkirchen") -> Geilenkirchen | AM77: =IFERROR(__xludf.DUMMYFUNCTION("""COMPUTED_VALUE"""),"GKE") -> GKE | AN77: =IFERROR(__xludf.DUMMYFUNCTION("""COMPUTED_VALUE"""),"Geilenkirchen") -> Geilenkirchen | AO77: =IFERROR(__xludf.DUMMYFUNCTION("""COMPUTED_VALUE"""),"Germany") -> Germany
AC78: =IFERROR(__xludf.DUMMYFUNCTION("""COMPUTED_VALUE"""),"Fetlar") -> Fetlar | AD78: =IFERROR(__xludf.DUMMYFUNCTION("""COMPUTED_VALUE"""),"FEA") -> FEA | AE78: =IFERROR(__xludf.DUMMYFUNCTION("""COMPUTED_VALUE"""),"Fetlar") -> Fetlar | AF78: =IFERROR(__xludf.DUMMYFUNCTION("""COMPUTED_VALUE"""),"United Kingdom") -> United Kingdom | AL78: =IFERROR(__xludf.DUMMYFUNCTION("""COMPUTED_VALUE"""),"Gera") -> Gera | AM78: =IFERROR(__xludf.DUMMYFUNCTION("""COMPUTED_VALUE"""),"ZGA") -> ZGA | AN78: =IFERROR(__xludf.DUMMYFUNCTION("""COMPUTED_VALUE"""),"Gera Railway") -> Gera Railway | AO78: =IFERROR(__xludf.DUMMYFUNCTION("""COMPUTED_VALUE"""),"Germany") -> Germany
AC79: =IFERROR(__xludf.DUMMYFUNCTION("""COMPUTED_VALUE"""),"Filton") -> Filton | AD79: =IFERROR(__xludf.DUMMYFUNCTION("""COMPUTED_VALUE"""),"FZO") -> FZO | AE79: =IFERROR(__xludf.DUMMYFUNCTION("""COMPUTED_VALUE"""),"Filton") -> Filton | AF79: =IFERROR(__xludf.DUMMYFUNCTION("""COMPUTED_VALUE"""),"United Kingdom") -> United Kingdom | AL79: =IFERROR(__xludf.DUMMYFUNCTION("""COMPUTED_VALUE"""),"Giebelstadt") -> Giebelstadt | AM79: =IFERROR(__xludf.DUMMYFUNCTION("""COMPUTED_VALUE"""),"GHF") -> GHF | AN79: =IFERROR(__xludf.DUMMYFUNCTION("""COMPUTED_VALUE"""),"Giebelstadt") -> Giebelstadt | AO79: =IFERROR(__xludf.DUMMYFUNCTION("""COMPUTED_VALUE"""),"Germany") -> Germany
AC80: =IFERROR(__xludf.DUMMYFUNCTION("""COMPUTED_VALUE"""),"Flotta") -> Flotta | AD80: =IFERROR(__xludf.DUMMYFUNCTION("""COMPUTED_VALUE"""),"FLH") -> FLH | AE80: =IFERROR(__xludf.DUMMYFUNCTION("""COMPUTED_VALUE"""),"Flotta") -> Flotta | AF80: =IFERROR(__xludf.DUMMYFUNCTION("""COMPUTED_VALUE"""),"United Kingdom") -> United Kingdom | AL80: =IFERROR(__xludf.DUMMYFUNCTION("""COMPUTED_VALUE"""),"Goerlitz") -> Goerlitz | AM80: =IFERROR(__xludf.DUMMYFUNCTION("""COMPUTED_VALUE"""),"ZGE") -> ZGE | AN80: =IFERROR(__xludf.DUMMYFUNCTION("""COMPUTED_VALUE"""),"Goerlitz Railway") -> Goerlitz Railway | AO80: =IFERROR(__xludf.DUMMYFUNCTION("""COMPUTED_VALUE"""),"Germany") -> Germany
AC81: =IFERROR(__xludf.DUMMYFUNCTION("""COMPUTED_VALUE"""),"Forres") -> Forres | AD81: =IFERROR(__xludf.DUMMYFUNCTION("""COMPUTED_VALUE"""),"FSS") -> FSS | AE81: =IFERROR(__xludf.DUMMYFUNCTION("""COMPUTED_VALUE"""),"Kinloss") -> Kinloss | AF81: =IFERROR(__xludf.DUMMYFUNCTION("""COMPUTED_VALUE"""),"United Kingdom") -> United Kingdom | AL81: =IFERROR(__xludf.DUMMYFUNCTION("""COMPUTED_VALUE"""),"Gotha") -> Gotha | AM81: =IFERROR(__xludf.DUMMYFUNCTION("""COMPUTED_VALUE"""),"ZGO") -> ZGO | AN81: =IFERROR(__xludf.DUMMYFUNCTION("""COMPUTED_VALUE"""),"Gotha Railway") -> Gotha Railway | AO81: =IFERROR(__xludf.DUMMYFUNCTION("""COMPUTED_VALUE"""),"Germany") -> Germany
AC82: =IFERROR(__xludf.DUMMYFUNCTION("""COMPUTED_VALUE"""),"Fort William") -> Fort William | AD82: =IFERROR(__xludf.DUMMYFUNCTION("""COMPUTED_VALUE"""),"FWM") -> FWM | AE82: =IFERROR(__xludf.DUMMYFUNCTION("""COMPUTED_VALUE"""),"Heliport") -> Heliport | AF82: =IFERROR(__xludf.DUMMYFUNCTION("""COMPUTED_VALUE"""),"United Kingdom") -> United Kingdom | AL82: =IFERROR(__xludf.DUMMYFUNCTION("""COMPUTED_VALUE"""),"Greifswald") -> Greifswald | AM82: =IFERROR(__xludf.DUMMYFUNCTION("""COMPUTED_VALUE"""),"ZGW") -> ZGW | AN82: =IFERROR(__xludf.DUMMYFUNCTION("""COMPUTED_VALUE"""),"Greifswald Railway") -> Greifswald Railway | AO82: =IFERROR(__xludf.DUMMYFUNCTION("""COMPUTED_VALUE"""),"Germany") -> Germany
AC83: =IFERROR(__xludf.DUMMYFUNCTION("""COMPUTED_VALUE"""),"Foula") -> Foula | AD83: =IFERROR(__xludf.DUMMYFUNCTION("""COMPUTED_VALUE"""),"FOA") -> FOA | AE83: =IFERROR(__xludf.DUMMYFUNCTION("""COMPUTED_VALUE"""),"Foula") -> Foula | AF83: =IFERROR(__xludf.DUMMYFUNCTION("""COMPUTED_VALUE"""),"United Kingdom") -> United Kingdom | AL83: =IFERROR(__xludf.DUMMYFUNCTION("""COMPUTED_VALUE"""),"Guetersloh") -> Guetersloh | AM83: =IFERROR(__xludf.DUMMYFUNCTION("""COMPUTED_VALUE"""),"GUT") -> GUT | AN83: =IFERROR(__xludf.DUMMYFUNCTION("""COMPUTED_VALUE"""),"Guetersloh") -> Guetersloh | AO83: =IFERROR(__xludf.DUMMYFUNCTION("""COMPUTED_VALUE"""),"Germany") -> Germany
AC84: =IFERROR(__xludf.DUMMYFUNCTION("""COMPUTED_VALUE"""),"Glasgow") -> Glasgow | AD84: =IFERROR(__xludf.DUMMYFUNCTION("""COMPUTED_VALUE"""),"GLA") -> GLA | AE84: =IFERROR(__xludf.DUMMYFUNCTION("""COMPUTED_VALUE"""),"Glasgow International") -> Glasgow International | AF84: =IFERROR(__xludf.DUMMYFUNCTION("""COMPUTED_VALUE"""),"United Kingdom") -> United Kingdom | AL84: =IFERROR(__xludf.DUMMYFUNCTION("""COMPUTED_VALUE"""),"Guettin") -> Guettin | AM84: =IFERROR(__xludf.DUMMYFUNCTION("""COMPUTED_VALUE"""),"GTI") -> GTI | AN84: =IFERROR(__xludf.DUMMYFUNCTION("""COMPUTED_VALUE"""),"Guettin") -> Guettin | AO84: =IFERROR(__xludf.DUMMYFUNCTION("""COMPUTED_VALUE"""),"Germany") -> Germany
AC85: =IFERROR(__xludf.DUMMYFUNCTION("""COMPUTED_VALUE"""),"Glasgow") -> Glasgow | AD85: =IFERROR(__xludf.DUMMYFUNCTION("""COMPUTED_VALUE"""),"PIK") -> PIK | AE85: =IFERROR(__xludf.DUMMYFUNCTION("""COMPUTED_VALUE"""),"Prestwick") -> Prestwick | AF85: =IFERROR(__xludf.DUMMYFUNCTION("""COMPUTED_VALUE"""),"United Kingdom") -> United Kingdom | AL85: =IFERROR(__xludf.DUMMYFUNCTION("""COMPUTED_VALUE"""),"Halle") -> Halle | AM85: =IFERROR(__xludf.DUMMYFUNCTION("""COMPUTED_VALUE"""),"ZHZ") -> ZHZ | AN85: =IFERROR(__xludf.DUMMYFUNCTION("""COMPUTED_VALUE"""),"Halle Railway") -> Halle Railway | AO85: =IFERROR(__xludf.DUMMYFUNCTION("""COMPUTED_VALUE"""),"Germany") -> Germany
AC86: =IFERROR(__xludf.DUMMYFUNCTION("""COMPUTED_VALUE"""),"Glasgow") -> Glasgow | AD86: =IFERROR(__xludf.DUMMYFUNCTION("""COMPUTED_VALUE"""),"ZGG") -> ZGG | AE86: =IFERROR(__xludf.DUMMYFUNCTION("""COMPUTED_VALUE"""),"ScotRail") -> ScotRail | AF86: =IFERROR(__xludf.DUMMYFUNCTION("""COMPUTED_VALUE"""),"United Kingdom") -> United Kingdom | AL86: =IFERROR(__xludf.DUMMYFUNCTION("""COMPUTED_VALUE"""),"Hamburg") -> Hamburg | AM86: =IFERROR(__xludf.DUMMYFUNCTION("""COMPUTED_VALUE"""),"HAM") -> HAM | AN86: =IFERROR(__xludf.DUMMYFUNCTION("""COMPUTED_VALUE"""),"Hamburg") -> Hamburg | AO86: =IFERROR(__xludf.DUMMYFUNCTION("""COMPUTED_VALUE"""),"Germany") -> Germany
AC87: =IFERROR(__xludf.DUMMYFUNCTION("""COMPUTED_VALUE"""),"Gloucester") -> Gloucester | AD87: =IFERROR(__xludf.DUMMYFUNCTION("""COMPUTED_VALUE"""),"GLO") -> GLO | AE87: =IFERROR(__xludf.DUMMYFUNCTION("""COMPUTED_VALUE"""),"Gloucestershire") -> Gloucestershire | AF87: =IFERROR(__xludf.DUMMYFUNCTION("""COMPUTED_VALUE"""),"United Kingdom") -> United Kingdom | AL87: =IFERROR(__xludf.DUMMYFUNCTION("""COMPUTED_VALUE"""),"Lübeck") -> Lübeck | AM87: =IFERROR(__xludf.DUMMYFUNCTION("""COMPUTED_VALUE"""),"LBC") -> LBC | AN87: =IFERROR(__xludf.DUMMYFUNCTION("""COMPUTED_VALUE"""),"Lübeck Blankensee") -> Lübeck Blankensee | AO87: =IFERROR(__xludf.DUMMYFUNCTION("""COMPUTED_VALUE"""),"Germany") -> Germany
AC88: =IFERROR(__xludf.DUMMYFUNCTION("""COMPUTED_VALUE"""),"Grimsby") -> Grimsby | AD88: =IFERROR(__xludf.DUMMYFUNCTION("""COMPUTED_VALUE"""),"GSY") -> GSY | AE88: =IFERROR(__xludf.DUMMYFUNCTION("""COMPUTED_VALUE"""),"Binbrook") -> Binbrook | AF88: =IFERROR(__xludf.DUMMYFUNCTION("""COMPUTED_VALUE"""),"United Kingdom") -> United Kingdom | AL88: =IFERROR(__xludf.DUMMYFUNCTION("""COMPUTED_VALUE"""),"Hanover") -> Hanover | AM88: =IFERROR(__xludf.DUMMYFUNCTION("""COMPUTED_VALUE"""),"HAJ") -> HAJ | AN88: =IFERROR(__xludf.DUMMYFUNCTION("""COMPUTED_VALUE"""),"Hanover Arpt") -> Hanover Arpt | AO88: =IFERROR(__xludf.DUMMYFUNCTION("""COMPUTED_VALUE"""),"Germany") -> Germany
AC89: =IFERROR(__xludf.DUMMYFUNCTION("""COMPUTED_VALUE"""),"Guernsey") -> Guernsey | AD89: =IFERROR(__xludf.DUMMYFUNCTION("""COMPUTED_VALUE"""),"GCI") -> GCI | AE89: =IFERROR(__xludf.DUMMYFUNCTION("""COMPUTED_VALUE"""),"Guernsey") -> Guernsey | AF89: =IFERROR(__xludf.DUMMYFUNCTION("""COMPUTED_VALUE"""),"United Kingdom") -> United Kingdom | AL89: =IFERROR(__xludf.DUMMYFUNCTION("""COMPUTED_VALUE"""),"Hanover") -> Hanover | AM89: =IFERROR(__xludf.DUMMYFUNCTION("""COMPUTED_VALUE"""),"ZVR") -> ZVR | AN89: =IFERROR(__xludf.DUMMYFUNCTION("""COMPUTED_VALUE"""),"Hanover Railway") -> Hanover Railway | AO89: =IFERROR(__xludf.DUMMYFUNCTION("""COMPUTED_VALUE"""),"Germany") -> Germany
AC90: =IFERROR(__xludf.DUMMYFUNCTION("""COMPUTED_VALUE"""),"Hammersmith") -> Hammersmith | AD90: =IFERROR(__xludf.DUMMYFUNCTION("""COMPUTED_VALUE"""),"WUK") -> WUK | AE90: =IFERROR(__xludf.DUMMYFUNCTION("""COMPUTED_VALUE"""),"Off Line Point") -> Off Line Point | AF90: =IFERROR(__xludf.DUMMYFUNCTION("""COMPUTED_VALUE"""),"United Kingdom") -> United Kingdom | AL90: =IFERROR(__xludf.DUMMYFUNCTION("""COMPUTED_VALUE"""),"Hanover") -> Hanover | AM90: =IFERROR(__xludf.DUMMYFUNCTION("""COMPUTED_VALUE"""),"ZVM") -> ZVM | AN90: =IFERROR(__xludf.DUMMYFUNCTION("""COMPUTED_VALUE"""),"Messe-BF Railway Servi") -> Messe-BF Railway Servi | AO90: =IFERROR(__xludf.DUMMYFUNCTION("""COMPUTED_VALUE"""),"Germany") -> Germany
AC91: =IFERROR(__xludf.DUMMYFUNCTION("""COMPUTED_VALUE"""),"Harrogate") -> Harrogate | AD91: =IFERROR(__xludf.DUMMYFUNCTION("""COMPUTED_VALUE"""),"HRT") -> HRT | AE91: =IFERROR(__xludf.DUMMYFUNCTION("""COMPUTED_VALUE"""),"Linton-On-Ouse") -> Linton-On-Ouse | AF91: =IFERROR(__xludf.DUMMYFUNCTION("""COMPUTED_VALUE"""),"United Kingdom") -> United Kingdom | AL91: =IFERROR(__xludf.DUMMYFUNCTION("""COMPUTED_VALUE"""),"Heide-Buesum") -> Heide-Buesum | AM91: =IFERROR(__xludf.DUMMYFUNCTION("""COMPUTED_VALUE"""),"HEI") -> HEI | AN91: =IFERROR(__xludf.DUMMYFUNCTION("""COMPUTED_VALUE"""),"Heide-Buesum") -> Heide-Buesum | AO91: =IFERROR(__xludf.DUMMYFUNCTION("""COMPUTED_VALUE"""),"Germany") -> Germany
AC92: =IFERROR(__xludf.DUMMYFUNCTION("""COMPUTED_VALUE"""),"Hatfield") -> Hatfield | AD92: =IFERROR(__xludf.DUMMYFUNCTION("""COMPUTED_VALUE"""),"HTF") -> HTF | AE92: =IFERROR(__xludf.DUMMYFUNCTION("""COMPUTED_VALUE"""),"Hatfield") -> Hatfield | AF92: =IFERROR(__xludf.DUMMYFUNCTION("""COMPUTED_VALUE"""),"United Kingdom") -> United Kingdom | AL92: =IFERROR(__xludf.DUMMYFUNCTION("""COMPUTED_VALUE"""),"Heidelberg") -> Heidelberg | AM92: =IFERROR(__xludf.DUMMYFUNCTION("""COMPUTED_VALUE"""),"HDB") -> HDB | AN92: =IFERROR(__xludf.DUMMYFUNCTION("""COMPUTED_VALUE"""),"Heidelberg") -> Heidelberg | AO92: =IFERROR(__xludf.DUMMYFUNCTION("""COMPUTED_VALUE"""),"Germany") -> Germany
AC93: =IFERROR(__xludf.DUMMYFUNCTION("""COMPUTED_VALUE"""),"Haverfordwest") -> Haverfordwest | AD93: =IFERROR(__xludf.DUMMYFUNCTION("""COMPUTED_VALUE"""),"HAW") -> HAW | AE93: =IFERROR(__xludf.DUMMYFUNCTION("""COMPUTED_VALUE"""),"Haverfordwest") -> Haverfordwest | AF93: =IFERROR(__xludf.DUMMYFUNCTION("""COMPUTED_VALUE"""),"United Kingdom") -> United Kingdom | AL93: =IFERROR(__xludf.DUMMYFUNCTION("""COMPUTED_VALUE"""),"Helgoland") -> Helgoland | AM93: =IFERROR(__xludf.DUMMYFUNCTION("""COMPUTED_VALUE"""),"HGL") -> HGL | AN93: =IFERROR(__xludf.DUMMYFUNCTION("""COMPUTED_VALUE"""),"Helgoland") -> Helgoland | AO93: =IFERROR(__xludf.DUMMYFUNCTION("""COMPUTED_VALUE"""),"Germany") -> Germany
AC94: =IFERROR(__xludf.DUMMYFUNCTION("""COMPUTED_VALUE"""),"High Wycombe") -> High Wycombe | AD94: =IFERROR(__xludf.DUMMYFUNCTION("""COMPUTED_VALUE"""),"HYC") -> HYC | AE94: =IFERROR(__xludf.DUMMYFUNCTION("""COMPUTED_VALUE"""),"High Wycombe") -> High Wycombe | AF94: =IFERROR(__xludf.DUMMYFUNCTION("""COMPUTED_VALUE"""),"United Kingdom") -> United Kingdom | AL94: =IFERROR(__xludf.DUMMYFUNCTION("""COMPUTED_VALUE"""),"Heringsdorf") -> Heringsdorf | AM94: =IFERROR(__xludf.DUMMYFUNCTION("""COMPUTED_VALUE"""),"HDF") -> HDF | AN94: =IFERROR(__xludf.DUMMYFUNCTION("""COMPUTED_VALUE"""),"Heringsdorf") -> Heringsdorf | AO94: =IFERROR(__xludf.DUMMYFUNCTION("""COMPUTED_VALUE"""),"Germany") -> Germany
AC95: =IFERROR(__xludf.DUMMYFUNCTION("""COMPUTED_VALUE"""),"Holyhead") -> Holyhead | AD95: =IFERROR(__xludf.DUMMYFUNCTION("""COMPUTED_VALUE"""),"HLY") -> HLY | AE95: =IFERROR(__xludf.DUMMYFUNCTION("""COMPUTED_VALUE"""),"Holyhead") -> Holyhead | AF95: =IFERROR(__xludf.DUMMYFUNCTION("""COMPUTED_VALUE"""),"United Kingdom") -> United Kingdom | AL95: =IFERROR(__xludf.DUMMYFUNCTION("""COMPUTED_VALUE"""),"Hof") -> Hof | AM95: =IFERROR(__xludf.DUMMYFUNCTION("""COMPUTED_VALUE"""),"HOQ") -> HOQ | AN95: =IFERROR(__xludf.DUMMYFUNCTION("""COMPUTED_VALUE"""),"Hof") -> Hof | AO95: =IFERROR(__xludf.DUMMYFUNCTION("""COMPUTED_VALUE"""),"Germany") -> Germany
AC96: =IFERROR(__xludf.DUMMYFUNCTION("""COMPUTED_VALUE"""),"Hoy Island") -> Hoy Island | AD96: =IFERROR(__xludf.DUMMYFUNCTION("""COMPUTED_VALUE"""),"HOY") -> HOY | AE96: =IFERROR(__xludf.DUMMYFUNCTION("""COMPUTED_VALUE"""),"Hoy Island") -> Hoy Island | AF96: =IFERROR(__xludf.DUMMYFUNCTION("""COMPUTED_VALUE"""),"United Kingdom") -> United Kingdom | AL96: =IFERROR(__xludf.DUMMYFUNCTION("""COMPUTED_VALUE"""),"Husum") -> Husum | AM96: =IFERROR(__xludf.DUMMYFUNCTION("""COMPUTED_VALUE"""),"QHU") -> QHU | AN96: =IFERROR(__xludf.DUMMYFUNCTION("""COMPUTED_VALUE"""),"Husum") -> Husum | AO96: =IFERROR(__xludf.DUMMYFUNCTION("""COMPUTED_VALUE"""),"Germany") -> Germany
AC97: =IFERROR(__xludf.DUMMYFUNCTION("""COMPUTED_VALUE"""),"Humberside") -> Humberside | AD97: =IFERROR(__xludf.DUMMYFUNCTION("""COMPUTED_VALUE"""),"HUY") -> HUY | AE97: =IFERROR(__xludf.DUMMYFUNCTION("""COMPUTED_VALUE"""),"Humberside Arpt") -> Humberside Arpt | AF97: =IFERROR(__xludf.DUMMYFUNCTION("""COMPUTED_VALUE"""),"United Kingdom") -> United Kingdom | AL97: =IFERROR(__xludf.DUMMYFUNCTION("""COMPUTED_VALUE"""),"Illisheim") -> Illisheim | AM97: =IFERROR(__xludf.DUMMYFUNCTION("""COMPUTED_VALUE"""),"ILH") -> ILH | AN97: =IFERROR(__xludf.DUMMYFUNCTION("""COMPUTED_VALUE"""),"Illis Airbase") -> Illis Airbase | AO97: =IFERROR(__xludf.DUMMYFUNCTION("""COMPUTED_VALUE"""),"Germany") -> Germany
AC98: =IFERROR(__xludf.DUMMYFUNCTION("""COMPUTED_VALUE"""),"Inverness") -> Inverness | AD98: =IFERROR(__xludf.DUMMYFUNCTION("""COMPUTED_VALUE"""),"INV") -> INV | AE98: =IFERROR(__xludf.DUMMYFUNCTION("""COMPUTED_VALUE"""),"Inverness") -> Inverness | AF98: =IFERROR(__xludf.DUMMYFUNCTION("""COMPUTED_VALUE"""),"United Kingdom") -> United Kingdom | AL98: =IFERROR(__xludf.DUMMYFUNCTION("""COMPUTED_VALUE"""),"Ingolstadt-Manching") -> Ingolstadt-Manching | AM98: =IFERROR(__xludf.DUMMYFUNCTION("""COMPUTED_VALUE"""),"IGS") -> IGS | AN98: =IFERROR(__xludf.DUMMYFUNCTION("""COMPUTED_VALUE"""),"Ingolstadt-Manching") -> Ingolstadt-Manching | AO98: =IFERROR(__xludf.DUMMYFUNCTION("""COMPUTED_VALUE"""),"Germany") -> Germany
AC99: =IFERROR(__xludf.DUMMYFUNCTION("""COMPUTED_VALUE"""),"Inverness") -> Inverness | AD99: =IFERROR(__xludf.DUMMYFUNCTION("""COMPUTED_VALUE"""),"ZIV") -> ZIV | AE99: =IFERROR(__xludf.DUMMYFUNCTION("""COMPUTED_VALUE"""),"ScotRail") -> ScotRail | AF99: =IFERROR(__xludf.DUMMYFUNCTION("""COMPUTED_VALUE"""),"United Kingdom") -> United Kingdom | AL99: =IFERROR(__xludf.DUMMYFUNCTION("""COMPUTED_VALUE"""),"Jena") -> Jena | AM99: =IFERROR(__xludf.DUMMYFUNCTION("""COMPUTED_VALUE"""),"ZJS") -> ZJS | AN99: =IFERROR(__xludf.DUMMYFUNCTION("""COMPUTED_VALUE"""),"Jena Railway") -> Jena Railway | AO99: =IFERROR(__xludf.DUMMYFUNCTION("""COMPUTED_VALUE"""),"Germany") -> Germany
AC100: =IFERROR(__xludf.DUMMYFUNCTION("""COMPUTED_VALUE"""),"Ipswich") -> Ipswich | AD100: =IFERROR(__xludf.DUMMYFUNCTION("""COMPUTED_VALUE"""),"IPW") -> IPW | AE100: =IFERROR(__xludf.DUMMYFUNCTION("""COMPUTED_VALUE"""),"Ipswich (Closed)") -> Ipswich (Closed) | AF100: =IFERROR(__xludf.DUMMYFUNCTION("""COMPUTED_VALUE"""),"United Kingdom") -> United Kingdom | AL100: =IFERROR(__xludf.DUMMYFUNCTION("""COMPUTED_VALUE"""),"Juist") -> Juist | AM100: =IFERROR(__xludf.DUMMYFUNCTION("""COMPUTED_VALUE"""),"JUI") -> JUI | AN100: =IFERROR(__xludf.DUMMYFUNCTION("""COMPUTED_VALUE"""),"Juist") -> Juist | AO100: =IFERROR(__xludf.DUMMYFUNCTION("""COMPUTED_VALUE"""),"Germany") -> Germany
AC101: =IFERROR(__xludf.DUMMYFUNCTION("""COMPUTED_VALUE"""),"Islay") -> Islay | AD101: =IFERROR(__xludf.DUMMYFUNCTION("""COMPUTED_VALUE"""),"ILY") -> ILY | AE101: =IFERROR(__xludf.DUMMYFUNCTION("""COMPUTED_VALUE"""),"Glenegedale") -> Glenegedale | AF101: =IFERROR(__xludf.DUMMYFUNCTION("""COMPUTED_VALUE"""),"United Kingdom") -> United Kingdom | AL101: =IFERROR(__xludf.DUMMYFUNCTION("""COMPUTED_VALUE"""),"Kaiserslautern") -> Kaiserslautern | AM101: =IFERROR(__xludf.DUMMYFUNCTION("""COMPUTED_VALUE"""),"KLT") -> KLT | AN101: =IFERROR(__xludf.DUMMYFUNCTION("""COMPUTED_VALUE"""),"Kaiserslautern") -> Kaiserslautern | AO101: =IFERROR(__xludf.DUMMYFUNCTION("""COMPUTED_VALUE"""),"Germany") -> Germany
AC102: =IFERROR(__xludf.DUMMYFUNCTION("""COMPUTED_VALUE"""),"Isle Of Man") -> Isle Of Man | AD102: =IFERROR(__xludf.DUMMYFUNCTION("""COMPUTED_VALUE"""),"IOM") -> IOM | AE102: =IFERROR(__xludf.DUMMYFUNCTION("""COMPUTED_VALUE"""),"Ronaldsway") -> Ronaldsway | AF102: =IFERROR(__xludf.DUMMYFUNCTION("""COMPUTED_VALUE"""),"United Kingdom") -> United Kingdom | AL102: =IFERROR(__xludf.DUMMYFUNCTION("""COMPUTED_VALUE"""),"Karlsruhe/Baden Baden") -> Karlsruhe/Baden Baden | AM102: =IFERROR(__xludf.DUMMYFUNCTION("""COMPUTED_VALUE"""),"FKB") -> FKB | AN102: =IFERROR(__xludf.DUMMYFUNCTION("""COMPUTED_VALUE"""),"Soellingen") -> Soellingen | AO102: =IFERROR(__xludf.DUMMYFUNCTION("""COMPUTED_VALUE"""),"Germany") -> Germany
AC103: =IFERROR(__xludf.DUMMYFUNCTION("""COMPUTED_VALUE"""),"Isle Of Skye") -> Isle Of Skye | AD103: =IFERROR(__xludf.DUMMYFUNCTION("""COMPUTED_VALUE"""),"SKL") -> SKL | AE103: =IFERROR(__xludf.DUMMYFUNCTION("""COMPUTED_VALUE"""),"Broadford") -> Broadford | AF103: =IFERROR(__xludf.DUMMYFUNCTION("""COMPUTED_VALUE"""),"United Kingdom") -> United Kingdom | AL103: =IFERROR(__xludf.DUMMYFUNCTION("""COMPUTED_VALUE"""),"Kassel") -> Kassel | AM103: =IFERROR(__xludf.DUMMYFUNCTION("""COMPUTED_VALUE"""),"KSF") -> KSF | AN103: =IFERROR(__xludf.DUMMYFUNCTION("""COMPUTED_VALUE"""),"Kassel-Calden") -> Kassel-Calden | AO103: =IFERROR(__xludf.DUMMYFUNCTION("""COMPUTED_VALUE"""),"Germany") -> Germany
AC104: =IFERROR(__xludf.DUMMYFUNCTION("""COMPUTED_VALUE"""),"Isles Of Scilly") -> Isles Of Scilly | AD104: =IFERROR(__xludf.DUMMYFUNCTION("""COMPUTED_VALUE"""),"ISC") -> ISC | AE104: =IFERROR(__xludf.DUMMYFUNCTION("""COMPUTED_VALUE"""),"St Marys") -> St Marys | AF104: =IFERROR(__xludf.DUMMYFUNCTION("""COMPUTED_VALUE"""),"United Kingdom") -> United Kingdom | AL104: =IFERROR(__xludf.DUMMYFUNCTION("""COMPUTED_VALUE"""),"Kiel") -> Kiel | AM104: =IFERROR(__xludf.DUMMYFUNCTION("""COMPUTED_VALUE"""),"KEL") -> KEL | AN104: =IFERROR(__xludf.DUMMYFUNCTION("""COMPUTED_VALUE"""),"Holtenau") -> Holtenau | AO104: =IFERROR(__xludf.DUMMYFUNCTION("""COMPUTED_VALUE"""),"Germany") -> Germany
AC105: =IFERROR(__xludf.DUMMYFUNCTION("""COMPUTED_VALUE"""),"Isles Of Scilly") -> Isles Of Scilly | AD105: =IFERROR(__xludf.DUMMYFUNCTION("""COMPUTED_VALUE"""),"TSO") -> TSO | AE105: =IFERROR(__xludf.DUMMYFUNCTION("""COMPUTED_VALUE"""),"Tresco") -> Tresco | AF105: =IFERROR(__xludf.DUMMYFUNCTION("""COMPUTED_VALUE"""),"United Kingdom") -> United Kingdom | AL105: =IFERROR(__xludf.DUMMYFUNCTION("""COMPUTED_VALUE"""),"Kitzingen") -> Kitzingen | AM105: =IFERROR(__xludf.DUMMYFUNCTION("""COMPUTED_VALUE"""),"KZG") -> KZG | AN105: =IFERROR(__xludf.DUMMYFUNCTION("""COMPUTED_VALUE"""),"Kitzingen") -> Kitzingen | AO105: =IFERROR(__xludf.DUMMYFUNCTION("""COMPUTED_VALUE"""),"Germany") -> Germany
AC106: =IFERROR(__xludf.DUMMYFUNCTION("""COMPUTED_VALUE"""),"Jersey") -> Jersey | AD106: =IFERROR(__xludf.DUMMYFUNCTION("""COMPUTED_VALUE"""),"JER") -> JER | AE106: =IFERROR(__xludf.DUMMYFUNCTION("""COMPUTED_VALUE"""),"States") -> States | AF106: =IFERROR(__xludf.DUMMYFUNCTION("""COMPUTED_VALUE"""),"United Kingdom") -> United Kingdom | AL106: =IFERROR(__xludf.DUMMYFUNCTION("""COMPUTED_VALUE"""),"Koethen") -> Koethen | AM106: =IFERROR(__xludf.DUMMYFUNCTION("""COMPUTED_VALUE"""),"KOQ") -> KOQ | AN106: =IFERROR(__xludf.DUMMYFUNCTION("""COMPUTED_VALUE"""),"Koethen") -> Koethen | AO106: =IFERROR(__xludf.DUMMYFUNCTION("""COMPUTED_VALUE"""),"Germany") -> Germany
...

Sheet JR
A1: =IFERROR(__xludf.DUMMYFUNCTION("IMPORTRANGE(""https://docs.google.com/spreadsheets/d/1vRztkEdMwazrjryEuxNBqxbQcg_cKEBuU59fnl4i3lI/edit?gid=1482188771#gid=1482188771"",""JURISDICTIONS!A:W"")"),"rff") -> rff | B1: =IFERROR(__xludf.DUMMYFUNCTION("""COMPUTED_VALUE"""),"Status") -> Status | C1: =IFERROR(__xludf.DUMMYFUNCTION("""COMPUTED_VALUE"""),"PROCESSING TIME") -> PROCESSING TIME | D1: =IFERROR(__xludf.DUMMYFUNCTION("""COMPUTED_VALUE"""),"JURISDICTION COSTS") -> JURISDICTION COSTS | E1: =IFERROR(__xludf.DUMMYFUNCTION("""COMPUTED_VALUE"""),"COURT FEES") -> COURT FEES | F1: =IFERROR(__xludf.DUMMYFUNCTION("""COMPUTED_VALUE"""),"LAWYER FEES") -> LAWYER FEES | G1: =IFERROR(__xludf.DUMMYFUNCTION("""COMPUTED_VALUE"""),"Lawyer 1") -> Lawyer 1 | H1: =IFERROR(__xludf.DUMMYFUNCTION("""COMPUTED_VALUE"""),"Lawyer 1 Contact") -> Lawyer 1 Contact | I1: =IFERROR(__xludf.DUMMYFUNCTION("""COMPUTED_VALUE"""),"Note") -> Note | J1: =IFERROR(__xludf.DUMMYFUNCTION("""COMPUTED_VALUE"""),"Lawyer 1 Sheet") -> Lawyer 1 Sheet | K1: =IFERROR(__xludf.DUMMYFUNCTION("""COMPUTED_VALUE"""),"Lawyer 2") -> Lawyer 2 | L1: =IFERROR(__xludf.DUMMYFUNCTION("""COMPUTED_VALUE"""),"Lawyer 2 Contact") -> Lawyer 2 Contact | M1: =IFERROR(__xludf.DUMMYFUNCTION("""COMPUTED_VALUE"""),"Lawyer 2 Claims") -> Lawyer 2 Claims | N1: =IFERROR(__xludf.DUMMYFUNCTION("""COMPUTED_VALUE"""),"Lawyer 2 Sheet") -> Lawyer 2 Sheet | O1: =IFERROR(__xludf.DUMMYFUNCTION("""COMPUTED_VALUE"""),"RANK") -> RANK | P1: =IFERROR(__xludf.DUMMYFUNCTION("""COMPUTED_VALUE"""),"EXPIRATION PERIOD") -> EXPIRATION PERIOD | Q1: =IFERROR(__xludf.DUMMYFUNCTION("""COMPUTED_VALUE"""),"Assignment Form / POA") -> Assignment Form / POA | R1: =IFERROR(__xludf.DUMMYFUNCTION("""COMPUTED_VALUE"""),"TKT/ BP") -> TKT/ BP | S1: =IFERROR(__xludf.DUMMYFUNCTION("""COMPUTED_VALUE"""),"ID") -> ID | T1: =IFERROR(__xludf.DUMMYFUNCTION("""COMPUTED_VALUE"""),"Claim Email") -> Claim Email | U1: =IFERROR(__xludf.DUMMYFUNCTION("""COMPUTED_VALUE"""),"Rerouted Tkt") -> Rerouted Tkt | V1: =IFERROR(__xludf.DUMMYFUNCTION("""COMPUTED_VALUE"""),"Disruption Proof") -> Disruption Proof | W1: =IFERROR(__xludf.DUMMYFUNCTION("""COMPUTED_VALUE"""),"Note") -> Note
A2: =IFERROR(__xludf.DUMMYFUNCTION("""COMPUTED_VALUE"""),"Sweden") -> Sweden | B2: =IFERROR(__xludf.DUMMYFUNCTION("""COMPUTED_VALUE"""),"CONTRACTED") -> CONTRACTED | C2: =IFERROR(__xludf.DUMMYFUNCTION("""COMPUTED_VALUE"""),"2–6 months") -> 2–6 months | G2: =IFERROR(__xludf.DUMMYFUNCTION("""COMPUTED_VALUE"""),"Michael Forvass") -> Michael Forvass | H2: =IFERROR(__xludf.DUMMYFUNCTION("""COMPUTED_VALUE"""),"michael@juristavdelningen.se") -> michael@juristavdelningen.se | J2: =IFERROR(__xludf.DUMMYFUNCTION("""COMPUTED_VALUE"""),"Sweden") -> Sweden | O2: =IFERROR(__xludf.DUMMYFUNCTION("""COMPUTED_VALUE"""),1.0) -> 1 | P2: =IFERROR(__xludf.DUMMYFUNCTION("""COMPUTED_VALUE"""),"2 months - 10 years") -> 2 months - 10 years | Q2: =IFERROR(__xludf.DUMMYFUNCTION("""COMPUTED_VALUE"""),"Yes") -> Yes | R2: =IFERROR(__xludf.DUMMYFUNCTION("""COMPUTED_VALUE"""),"Yes") -> Yes | S2: =IFERROR(__xludf.DUMMYFUNCTION("""COMPUTED_VALUE"""),"No") -> No | T2: =IFERROR(__xludf.DUMMYFUNCTION("""COMPUTED_VALUE"""),"Yes") -> Yes | U2: =IFERROR(__xludf.DUMMYFUNCTION("""COMPUTED_VALUE"""),"No") -> No | V2: =IFERROR(__xludf.DUMMYFUNCTION("""COMPUTED_VALUE"""),"No") -> No | W2: =IFERROR(__xludf.DUMMYFUNCTION("""COMPUTED_VALUE"""),"If a passenger notifies an airline within the first 2 months after a flight disruption, the claim should be eligible for 10 years.") -> If a passenger notifies an airline within the first 2 months after a flight disruption, the claim should be eligible for 10 years.
A3: =IFERROR(__xludf.DUMMYFUNCTION("""COMPUTED_VALUE"""),"Romania") -> Romania | B3: =IFERROR(__xludf.DUMMYFUNCTION("""COMPUTED_VALUE"""),"CONTRACTED") -> CONTRACTED | C3: =IFERROR(__xludf.DUMMYFUNCTION("""COMPUTED_VALUE"""),"Long") -> Long | G3: =IFERROR(__xludf.DUMMYFUNCTION("""COMPUTED_VALUE"""),"BOGDAN BLAJ") -> BOGDAN BLAJ | H3: =IFERROR(__xludf.DUMMYFUNCTION("""COMPUTED_VALUE"""),"bogdan@blaj-law.ro") -> bogdan@blaj-law.ro | J3: =IFERROR(__xludf.DUMMYFUNCTION("""COMPUTED_VALUE"""),"Romania") -> Romania | O3: =IFERROR(__xludf.DUMMYFUNCTION("""COMPUTED_VALUE"""),2.0) -> 2 | P3: =IFERROR(__xludf.DUMMYFUNCTION("""COMPUTED_VALUE"""),"3 years") -> 3 years | Q3: =IFERROR(__xludf.DUMMYFUNCTION("""COMPUTED_VALUE"""),"Yes") -> Yes | R3: =IFERROR(__xludf.DUMMYFUNCTION("""COMPUTED_VALUE"""),"Yes") -> Yes | S3: =IFERROR(__xludf.DUMMYFUNCTION("""COMPUTED_VALUE"""),"No") -> No | T3: =IFERROR(__xludf.DUMMYFUNCTION("""COMPUTED_VALUE"""),"Yes") -> Yes | U3: =IFERROR(__xludf.DUMMYFUNCTION("""COMPUTED_VALUE"""),"Yes") -> Yes | V3: =IFERROR(__xludf.DUMMYFUNCTION("""COMPUTED_VALUE"""),"No") -> No | W3: =IFERROR(__xludf.DUMMYFUNCTION("""COMPUTED_VALUE"""),"Goal: 100 claims a week No legal assessment necessary: we should only check the disruption and EOC Documents required: AF, BP/eticket, claim, proof of sending the claim to airline") -> Goal: 100 claims a week No legal assessment necessary: we should only check the disruption and EOC Documents required: AF, BP/eticket, claim, proof of sending the claim to airline
A4: =IFERROR(__xludf.DUMMYFUNCTION("""COMPUTED_VALUE"""),"Austria") -> Austria | B4: =IFERROR(__xludf.DUMMYFUNCTION("""COMPUTED_VALUE"""),"CONTRACTED") -> CONTRACTED | C4: =IFERROR(__xludf.DUMMYFUNCTION("""COMPUTED_VALUE"""),"2-6 months") -> 2-6 months | D4: =IFERROR(__xludf.DUMMYFUNCTION("""COMPUTED_VALUE"""),"attorney fees prescribed by the law") -> attorney fees prescribed by the law | E4: =IFERROR(__xludf.DUMMYFUNCTION("""COMPUTED_VALUE"""),"200 Euros: 70,00 EUR 400 Euro: 90,00 EUR 600 Euros: 90,00 EUR") -> 200 Euros: 70,00 EUR 400 Euro: 90,00 EUR 600 Euros: 90,00 EUR | F4: =IFERROR(__xludf.DUMMYFUNCTION("""COMPUTED_VALUE"""),"Between 2000-3000 EUR depending on the lawyer's workload") -> Between 2000-3000 EUR depending on the lawyer's workload | G4: =IFERROR(__xludf.DUMMYFUNCTION("""COMPUTED_VALUE"""),"ALEXANDER SKRIBE") -> ALEXANDER SKRIBE | H4: =IFERROR(__xludf.DUMMYFUNCTION("""COMPUTED_VALUE"""),"skribe@skribe.law - mader@skribe.law") -> skribe@skribe.law - mader@skribe.law | J4: =IFERROR(__xludf.DUMMYFUNCTION("""COMPUTED_VALUE"""),"Austria") -> Austria | O4: =IFERROR(__xludf.DUMMYFUNCTION("""COMPUTED_VALUE"""),3.0) -> 3 | P4: =IFERROR(__xludf.DUMMYFUNCTION("""COMPUTED_VALUE"""),"3 years") -> 3 years | Q4: =IFERROR(__xludf.DUMMYFUNCTION("""COMPUTED_VALUE"""),"Yes") -> Yes | R4: =IFERROR(__xludf.DUMMYFUNCTION("""COMPUTED_VALUE"""),"Yes") -> Yes | S4: =IFERROR(__xludf.DUMMYFUNCTION("""COMPUTED_VALUE"""),"Yes") -> Yes | T4: =IFERROR(__xludf.DUMMYFUNCTION("""COMPUTED_VALUE"""),"No") -> No | U4: =IFERROR(__xludf.DUMMYFUNCTION("""COMPUTED_VALUE"""),"Yes") -> Yes | V4: =IFERROR(__xludf.DUMMYFUNCTION("""COMPUTED_VALUE"""),"No") -> No
A5: =IFERROR(__xludf.DUMMYFUNCTION("""COMPUTED_VALUE"""),"France") -> France | B5: =IFERROR(__xludf.DUMMYFUNCTION("""COMPUTED_VALUE"""),"CONTRACTED") -> CONTRACTED | C5: =IFERROR(__xludf.DUMMYFUNCTION("""COMPUTED_VALUE"""),"~1 year") -> ~1 year | E5: =IFERROR(__xludf.DUMMYFUNCTION("""COMPUTED_VALUE"""),"If representing the consumer no fees.If representing the company fee in amount of _____") -> If representing the consumer no fees.If representing the company fee in amount of _____ | F5: =IFERROR(__xludf.DUMMYFUNCTION("""COMPUTED_VALUE"""),"50 EUR paid upfront, reimbursement of 10% of legal fees, average legal fees 200 EUR") -> 50 EUR paid upfront, reimbursement of 10% of legal fees, average legal fees 200 EUR | G5: =IFERROR(__xludf.DUMMYFUNCTION("""COMPUTED_VALUE"""),"JOYCE PITCHER") -> JOYCE PITCHER | H5: =IFERROR(__xludf.DUMMYFUNCTION("""COMPUTED_VALUE"""),"joyce@pitcher-avocat.fr claire@justice.cool") -> joyce@pitcher-avocat.fr claire@justice.cool | I5: =IFERROR(__xludf.DUMMYFUNCTION("""COMPUTED_VALUE"""),"www.justice.cool abdelrahman@refly.org @yo123321") -> www.justice.cool abdelrahman@refly.org @yo123321 | J5: =IFERROR(__xludf.DUMMYFUNCTION("""COMPUTED_VALUE"""),"France") -> France | O5: =IFERROR(__xludf.DUMMYFUNCTION("""COMPUTED_VALUE"""),4.0) -> 4 | P5: =IFERROR(__xludf.DUMMYFUNCTION("""COMPUTED_VALUE"""),"5 years") -> 5 years | Q5: =IFERROR(__xludf.DUMMYFUNCTION("""COMPUTED_VALUE"""),"Yes") -> Yes | R5: =IFERROR(__xludf.DUMMYFUNCTION("""COMPUTED_VALUE"""),"Yes") -> Yes | S5: =IFERROR(__xludf.DUMMYFUNCTION("""COMPUTED_VALUE"""),"Yes") -> Yes | T5: =IFERROR(__xludf.DUMMYFUNCTION("""COMPUTED_VALUE"""),"Yes") -> Yes | U5: =IFERROR(__xludf.DUMMYFUNCTION("""COMPUTED_VALUE"""),"Yes") -> Yes | V5: =IFERROR(__xludf.DUMMYFUNCTION("""COMPUTED_VALUE"""),"Yes") -> Yes | W5: =IFERROR(__xludf.DUMMYFUNCTION("""COMPUTED_VALUE"""),"Weather Check") -> Weather Check
A6: =IFERROR(__xludf.DUMMYFUNCTION("""COMPUTED_VALUE"""),"Italy") -> Italy | B6: =IFERROR(__xludf.DUMMYFUNCTION("""COMPUTED_VALUE"""),"CONTRACTED") -> CONTRACTED | C6: =IFERROR(__xludf.DUMMYFUNCTION("""COMPUTED_VALUE"""),"~1 year") -> ~1 year | E6: =IFERROR(__xludf.DUMMYFUNCTION("""COMPUTED_VALUE"""),"for claims below 2000 EUR - no court fees,, bailif costs - 30-40 EUR") -> for claims below 2000 EUR - no court fees,, bailif costs - 30-40 EUR | G6: =IFERROR(__xludf.DUMMYFUNCTION("""COMPUTED_VALUE"""),"MICHELE TARQUINIO") -> MICHELE TARQUINIO | H6: =IFERROR(__xludf.DUMMYFUNCTION("""COMPUTED_VALUE"""),"m.tarquinio77@gmail.com") -> m.tarquinio77@gmail.com | I6: =IFERROR(__xludf.DUMMYFUNCTION("""COMPUTED_VALUE"""),"https://login.aruba.it/auth/realms/pec/protocol/openid-connect/auth tarquinio.lawyer.refly@pec.it Coesius10+") -> https://login.aruba.it/auth/realms/pec/protocol/openid-connect/auth tarquinio.lawyer.refly@pec.it Coesius10+ | J6: =IFERROR(__xludf.DUMMYFUNCTION("""COMPUTED_VALUE"""),"Italy Michele") -> Italy Michele | K6: =IFERROR(__xludf.DUMMYFUNCTION("""COMPUTED_VALUE"""),"Alan Breda") -> Alan Breda | L6: =IFERROR(__xludf.DUMMYFUNCTION("""COMPUTED_VALUE"""),"info@studiolegalebreda.com") -> info@studiolegalebreda.com | M6: =IFERROR(__xludf.DUMMYFUNCTION("""COMPUTED_VALUE"""),268.0) -> 268 | N6: =IFERROR(__xludf.DUMMYFUNCTION("""COMPUTED_VALUE"""),"Italy Alan Breda") -> Italy Alan Breda | O6: =IFERROR(__xludf.DUMMYFUNCTION("""COMPUTED_VALUE"""),5.0) -> 5 | P6: =IFERROR(__xludf.DUMMYFUNCTION("""COMPUTED_VALUE"""),"2 years") -> 2 years | Q6: =IFERROR(__xludf.DUMMYFUNCTION("""COMPUTED_VALUE"""),"Yes") -> Yes | R6: =IFERROR(__xludf.DUMMYFUNCTION("""COMPUTED_VALUE"""),"Yes") -> Yes | S6: =IFERROR(__xludf.DUMMYFUNCTION("""COMPUTED_VALUE"""),"Yes") -> Yes | T6: =IFERROR(__xludf.DUMMYFUNCTION("""COMPUTED_VALUE"""),"yes") -> yes | U6: =IFERROR(__xludf.DUMMYFUNCTION("""COMPUTED_VALUE"""),"Yes") -> Yes | V6: =IFERROR(__xludf.DUMMYFUNCTION("""COMPUTED_VALUE"""),"Yes") -> Yes | W6: =IFERROR(__xludf.DUMMYFUNCTION("""COMPUTED_VALUE"""),"Michele: Goal: 100 claims a week our main lawyer claims should be uploaded to him only if we've send the claim to the airline using his email -> after 30 days we can share it with him- ID of the passenger needed in all claims Friendly airlines: Iberia"&", Vueling, Air Europe, WizzAir - only check the disruption, EOC and weather. No airpor stats Pietro (NEW) Goal: 40 claims usual + 10 with no dep/arr in IT Airlines: WizzAir Malta, WizzAir Hungary, Air Europa, TAP, Iberia, Air Dolomiti, Vueling ID requ"&"ired ") -> Michele: Goal: 100 claims a week our main lawyer claims should be uploaded to him only if we've send the claim to the airline using his email -> after 30 days we can share it with him- ID of the passenger needed in all claims Friendly airlines: Iberia, Vueling, Air Europe, WizzAir - only check the disruption, EOC and weather. No airpor stats Pietro (NEW) Goal: 40 claims usual + 10 with no dep/arr in IT Airlines: WizzAir Malta, WizzAir Hungary, Air Europa, TAP, Iberia, Air Dolomiti, Vueling ID required
A7: =IFERROR(__xludf.DUMMYFUNCTION("""COMPUTED_VALUE"""),"Spain") -> Spain | B7: =IFERROR(__xludf.DUMMYFUNCTION("""COMPUTED_VALUE"""),"CONTRACTED") -> CONTRACTED | C7: =IFERROR(__xludf.DUMMYFUNCTION("""COMPUTED_VALUE"""),"2–6 months") -> 2–6 months | G7: =IFERROR(__xludf.DUMMYFUNCTION("""COMPUTED_VALUE"""),"MMMM.ES") -> MMMM.ES | H7: =IFERROR(__xludf.DUMMYFUNCTION("""COMPUTED_VALUE"""),"rcedron@mmmm.es") -> rcedron@mmmm.es | J7: =IFERROR(__xludf.DUMMYFUNCTION("""COMPUTED_VALUE"""),"Spain — MMMM.ES") -> Spain — MMMM.ES | K7: =IFERROR(__xludf.DUMMYFUNCTION("""COMPUTED_VALUE"""),"LUPICINIO") -> LUPICINIO | L7: =IFERROR(__xludf.DUMMYFUNCTION("""COMPUTED_VALUE"""),"rga@lupicinio.com") -> rga@lupicinio.com | O7: =IFERROR(__xludf.DUMMYFUNCTION("""COMPUTED_VALUE"""),6.0) -> 6 | P7: =IFERROR(__xludf.DUMMYFUNCTION("""COMPUTED_VALUE"""),"5 years") -> 5 years | Q7: =IFERROR(__xludf.DUMMYFUNCTION("""COMPUTED_VALUE"""),"Yes") -> Yes | R7: =IFERROR(__xludf.DUMMYFUNCTION("""COMPUTED_VALUE"""),"Yes") -> Yes | S7: =IFERROR(__xludf.DUMMYFUNCTION("""COMPUTED_VALUE"""),"Yes") -> Yes | T7: =IFERROR(__xludf.DUMMYFUNCTION("""COMPUTED_VALUE"""),"No") -> No | U7: =IFERROR(__xludf.DUMMYFUNCTION("""COMPUTED_VALUE"""),"Yes") -> Yes | V7: =IFERROR(__xludf.DUMMYFUNCTION("""COMPUTED_VALUE"""),"Yes") -> Yes | W7: =IFERROR(__xludf.DUMMYFUNCTION("""COMPUTED_VALUE"""),"- Weather Check - Family book or minors certificate if someone is under 18 years old. - Request E-ticket if BP doesn't have Full route, PNR, Full Name, Date - Unknown is not acceptable as disruption proof - Booking Ref should visible on BP,if not, we ne"&"ed to include the flight number and date on AF") -> - Weather Check - Family book or minors certificate if someone is under 18 years old. - Request E-ticket if BP doesn't have Full route, PNR, Full Name, Date - Unknown is not acceptable as disruption proof - Booking Ref should visible on BP,if not, we need to include the flight number and date on AF
A8: =IFERROR(__xludf.DUMMYFUNCTION("""COMPUTED_VALUE"""),"Poland") -> Poland | B8: =IFERROR(__xludf.DUMMYFUNCTION("""COMPUTED_VALUE"""),"CONTRACTED") -> CONTRACTED | C8: =IFERROR(__xludf.DUMMYFUNCTION("""COMPUTED_VALUE"""),"Long") -> Long | D8: =IFERROR(__xludf.DUMMYFUNCTION("""COMPUTED_VALUE"""),"200 pln/case paid upfront plus attorney fess") -> 200 pln/case paid upfront plus attorney fess | E8: =IFERROR(__xludf.DUMMYFUNCTION("""COMPUTED_VALUE"""),"500 PLN - 1500 PLN - 100 PLN 1500 PLN - 4000 PLN - 200 PLN") -> 500 PLN - 1500 PLN - 100 PLN 1500 PLN - 4000 PLN - 200 PLN | F8: =IFERROR(__xludf.DUMMYFUNCTION("""COMPUTED_VALUE"""),"500 PLN -1500 PLN - 180PLN/270 PLN 1500 PLN-5000 PLN 600PLN/900 PLN") -> 500 PLN -1500 PLN - 180PLN/270 PLN 1500 PLN-5000 PLN 600PLN/900 PLN | G8: =IFERROR(__xludf.DUMMYFUNCTION("""COMPUTED_VALUE"""),"Sylwia Janiszewska") -> Sylwia Janiszewska | H8: =IFERROR(__xludf.DUMMYFUNCTION("""COMPUTED_VALUE"""),"radcaprawny@sylwia-janiszewska.pl") -> radcaprawny@sylwia-janiszewska.pl | J8: =IFERROR(__xludf.DUMMYFUNCTION("""COMPUTED_VALUE"""),"Poland") -> Poland | O8: =IFERROR(__xludf.DUMMYFUNCTION("""COMPUTED_VALUE"""),7.0) -> 7 | P8: =IFERROR(__xludf.DUMMYFUNCTION("""COMPUTED_VALUE"""),"1 year") -> 1 year | Q8: =IFERROR(__xludf.DUMMYFUNCTION("""COMPUTED_VALUE"""),"Yes") -> Yes | R8: =IFERROR(__xludf.DUMMYFUNCTION("""COMPUTED_VALUE"""),"Yes") -> Yes | S8: =IFERROR(__xludf.DUMMYFUNCTION("""COMPUTED_VALUE"""),"No") -> No | T8: =IFERROR(__xludf.DUMMYFUNCTION("""COMPUTED_VALUE"""),"Yes") -> Yes | U8: =IFERROR(__xludf.DUMMYFUNCTION("""COMPUTED_VALUE"""),"Yes") -> Yes | V8: =IFERROR(__xludf.DUMMYFUNCTION("""COMPUTED_VALUE"""),"Yes") -> Yes | W8: =IFERROR(__xludf.DUMMYFUNCTION("""COMPUTED_VALUE"""),"New AF for Wizzair. New AF handsigned for Ryanair and LOT or all cases moved to court birth certificate for minors, marriage cert if needed ") -> New AF for Wizzair. New AF handsigned for Ryanair and LOT or all cases moved to court birth certificate for minors, marriage cert if needed
A9: =IFERROR(__xludf.DUMMYFUNCTION("""COMPUTED_VALUE"""),"United Kingdom") -> United Kingdom | B9: =IFERROR(__xludf.DUMMYFUNCTION("""COMPUTED_VALUE"""),"CONTRACTED") -> CONTRACTED | C9: =IFERROR(__xludf.DUMMYFUNCTION("""COMPUTED_VALUE"""),"2–6 months") -> 2–6 months | D9: =IFERROR(__xludf.DUMMYFUNCTION("""COMPUTED_VALUE"""),"15% of the collected sum or the recovearable costs depending what is higher") -> 15% of the collected sum or the recovearable costs depending what is higher | E9: =IFERROR(__xludf.DUMMYFUNCTION("""COMPUTED_VALUE"""),"£35 (recoverable)") -> £35 (recoverable) | F9: =IFERROR(__xludf.DUMMYFUNCTION("""COMPUTED_VALUE"""),"Claims up to £500 – Recoverable costs = £50 Claims between £500 - £1000 - Recoverable costs = £70 Claims between £1000 - £5000 - Recoverable costs = £80 Claims over £5000 - Recoverable costs = £100") -> Claims up to £500 – Recoverable costs = £50 Claims between £500 - £1000 - Recoverable costs = £70 Claims between £1000 - £5000 - Recoverable costs = £80 Claims over £5000 - Recoverable costs = £100 | G9: =IFERROR(__xludf.DUMMYFUNCTION("""COMPUTED_VALUE"""),"LOVETTS SOLICITORS") -> LOVETTS SOLICITORS | H9: =IFERROR(__xludf.DUMMYFUNCTION("""COMPUTED_VALUE"""),"AndrewD@lovetts.co.uk") -> AndrewD@lovetts.co.uk | I9: =IFERROR(__xludf.DUMMYFUNCTION("""COMPUTED_VALUE"""),"lovetts.co.uk https://casemanager.lovetts.co.uk/ ID: R880BASSANT PW: BASSANTNABIL ") -> lovetts.co.uk https://casemanager.lovetts.co.uk/ ID: R880BASSANT PW: BASSANTNABIL | J9: =IFERROR(__xludf.DUMMYFUNCTION("""COMPUTED_VALUE"""),"UK") -> UK | K9: =IFERROR(__xludf.DUMMYFUNCTION("""COMPUTED_VALUE"""),"Shergroup") -> Shergroup | L9: =IFERROR(__xludf.DUMMYFUNCTION("""COMPUTED_VALUE"""),"s-saluza@shergroup.com l-kirkham@shergroup.com") -> s-saluza@shergroup.com l-kirkham@shergroup.com | N9: =IFERROR(__xludf.DUMMYFUNCTION("""COMPUTED_VALUE"""),"Share group") -> Share group | O9: =IFERROR(__xludf.DUMMYFUNCTION("""COMPUTED_VALUE"""),8.0) -> 8 | P9: =IFERROR(__xludf.DUMMYFUNCTION("""COMPUTED_VALUE"""),"6 years") -> 6 years | Q9: =IFERROR(__xludf.DUMMYFUNCTION("""COMPUTED_VALUE"""),"Yes") -> Yes | R9: =IFERROR(__xludf.DUMMYFUNCTION("""COMPUTED_VALUE"""),"Yes") -> Yes | S9: =IFERROR(__xludf.DUMMYFUNCTION("""COMPUTED_VALUE"""),"No") -> No | T9: =IFERROR(__xludf.DUMMYFUNCTION("""COMPUTED_VALUE"""),"Yes") -> Yes | U9: =IFERROR(__xludf.DUMMYFUNCTION("""COMPUTED_VALUE"""),"Yes") -> Yes | V9: =IFERROR(__xludf.DUMMYFUNCTION("""COMPUTED_VALUE"""),"No") -> No | W9: =IFERROR(__xludf.DUMMYFUNCTION("""COMPUTED_VALUE"""),"- Lovetts: No Ajet - Share group:Needs ID/Passport, and disruption proof Send cases with risky airports status and weather ") -> - Lovetts: No Ajet - Share group:Needs ID/Passport, and disruption proof Send cases with risky airports status and weather
A10: =IFERROR(__xludf.DUMMYFUNCTION("""COMPUTED_VALUE"""),"Belgium") -> Belgium | B10: =IFERROR(__xludf.DUMMYFUNCTION("""COMPUTED_VALUE"""),"CONTRACTED") -> CONTRACTED | C10: =IFERROR(__xludf.DUMMYFUNCTION("""COMPUTED_VALUE"""),"2-6 months") -> 2-6 months | G10: =IFERROR(__xludf.DUMMYFUNCTION("""COMPUTED_VALUE"""),"David") -> David | H10: =IFERROR(__xludf.DUMMYFUNCTION("""COMPUTED_VALUE"""),"david@davidleys.com") -> david@davidleys.com | J10: =IFERROR(__xludf.DUMMYFUNCTION("""COMPUTED_VALUE"""),"Belgium") -> Belgium | O10: =IFERROR(__xludf.DUMMYFUNCTION("""COMPUTED_VALUE"""),9.0) -> 9 | P10: =IFERROR(__xludf.DUMMYFUNCTION("""COMPUTED_VALUE"""),"5 years") -> 5 years | Q10: =IFERROR(__xludf.DUMMYFUNCTION("""COMPUTED_VALUE"""),"Yes") -> Yes | R10: =IFERROR(__xludf.DUMMYFUNCTION("""COMPUTED_VALUE"""),"Yes") -> Yes | S10: =IFERROR(__xludf.DUMMYFUNCTION("""COMPUTED_VALUE"""),"Yes") -> Yes | T10: =IFERROR(__xludf.DUMMYFUNCTION("""COMPUTED_VALUE"""),"Yes") -> Yes | U10: =IFERROR(__xludf.DUMMYFUNCTION("""COMPUTED_VALUE"""),"Yes") -> Yes | V10: =IFERROR(__xludf.DUMMYFUNCTION("""COMPUTED_VALUE"""),"Yes") -> Yes
A11: =IFERROR(__xludf.DUMMYFUNCTION("""COMPUTED_VALUE"""),"Germany") -> Germany | B11: =IFERROR(__xludf.DUMMYFUNCTION("""COMPUTED_VALUE"""),"CONTRACTED") -> CONTRACTED | C11: =IFERROR(__xludf.DUMMYFUNCTION("""COMPUTED_VALUE"""),"~1 year") -> ~1 year | D11: =IFERROR(__xludf.DUMMYFUNCTION("""COMPUTED_VALUE"""),"250,00 EUR - 142,50 EUR 400,00 EUR - 142,50 EUR 600,00 EUR - 240,00 EUR") -> 250,00 EUR - 142,50 EUR 400,00 EUR - 142,50 EUR 600,00 EUR - 240,00 EUR | E11: =IFERROR(__xludf.DUMMYFUNCTION("""COMPUTED_VALUE"""),"250,00 EUR - 114,00 EUR 400,00 EUR - 114,00 EUR 600,00 EUR - 174,00 EUR ") -> 250,00 EUR - 114,00 EUR 400,00 EUR - 114,00 EUR 600,00 EUR - 174,00 EUR | F11: =IFERROR(__xludf.DUMMYFUNCTION("""COMPUTED_VALUE"""),"250,00 EUR - 142,50 EUR 400,00 EUR - 142,50 EUR 600,00 EUR - 240,00 EUR") -> 250,00 EUR - 142,50 EUR 400,00 EUR - 142,50 EUR 600,00 EUR - 240,00 EUR | G11: =IFERROR(__xludf.DUMMYFUNCTION("""COMPUTED_VALUE"""),"MORITZ DIEKMANN") -> MORITZ DIEKMANN | H11: =IFERROR(__xludf.DUMMYFUNCTION("""COMPUTED_VALUE"""),"moritz.diekmann@diekmann-rechtsanwaelte.de") -> moritz.diekmann@diekmann-rechtsanwaelte.de | J11: =IFERROR(__xludf.DUMMYFUNCTION("""COMPUTED_VALUE"""),"Germany") -> Germany | O11: =IFERROR(__xludf.DUMMYFUNCTION("""COMPUTED_VALUE"""),10.0) -> 10 | P11: =IFERROR(__xludf.DUMMYFUNCTION("""COMPUTED_VALUE"""),"3 years (The last day of the third year)") -> 3 years (The last day of the third year) | Q11: =IFERROR(__xludf.DUMMYFUNCTION("""COMPUTED_VALUE"""),"Yes") -> Yes | R11: =IFERROR(__xludf.DUMMYFUNCTION("""COMPUTED_VALUE"""),"Yes") -> Yes | S11: =IFERROR(__xludf.DUMMYFUNCTION("""COMPUTED_VALUE"""),"Yes") -> Yes | T11: =IFERROR(__xludf.DUMMYFUNCTION("""COMPUTED_VALUE"""),"Yes") -> Yes | U11: =IFERROR(__xludf.DUMMYFUNCTION("""COMPUTED_VALUE"""),"Yes") -> Yes | V11: =IFERROR(__xludf.DUMMYFUNCTION("""COMPUTED_VALUE"""),"No") -> No | W11: =IFERROR(__xludf.DUMMYFUNCTION("""COMPUTED_VALUE"""),"- Only for Non German - The limitation period expires on the last day of the third year (for example, the limitation period for a flight on 25/2/2016 expires on 31/12/2019).") -> - Only for Non German - The limitation period expires on the last day of the third year (for example, the limitation period for a flight on 25/2/2016 expires on 31/12/2019).
A12: =IFERROR(__xludf.DUMMYFUNCTION("""COMPUTED_VALUE"""),"Hungary") -> Hungary | B12: =IFERROR(__xludf.DUMMYFUNCTION("""COMPUTED_VALUE"""),"TEST PHASE") -> TEST PHASE | C12: =IFERROR(__xludf.DUMMYFUNCTION("""COMPUTED_VALUE"""),"Unknown") -> Unknown | G12: =IFERROR(__xludf.DUMMYFUNCTION("""COMPUTED_VALUE"""),"BOGLÁR SZERVATIUSZ") -> BOGLÁR SZERVATIUSZ | H12: =IFERROR(__xludf.DUMMYFUNCTION("""COMPUTED_VALUE"""),"b.szervatiusz@llf.hu") -> b.szervatiusz@llf.hu | J12: =IFERROR(__xludf.DUMMYFUNCTION("""COMPUTED_VALUE"""),"Hungary") -> Hungary | O12: =IFERROR(__xludf.DUMMYFUNCTION("""COMPUTED_VALUE"""),11.0) -> 11 | P12: =IFERROR(__xludf.DUMMYFUNCTION("""COMPUTED_VALUE"""),"2 years") -> 2 years | Q12: =IFERROR(__xludf.DUMMYFUNCTION("""COMPUTED_VALUE"""),"Yes") -> Yes | R12: =IFERROR(__xludf.DUMMYFUNCTION("""COMPUTED_VALUE"""),"Yes") -> Yes | S12: =IFERROR(__xludf.DUMMYFUNCTION("""COMPUTED_VALUE"""),"No") -> No | T12: =IFERROR(__xludf.DUMMYFUNCTION("""COMPUTED_VALUE"""),"No") -> No | U12: =IFERROR(__xludf.DUMMYFUNCTION("""COMPUTED_VALUE"""),"Yes") -> Yes | V12: =IFERROR(__xludf.DUMMYFUNCTION("""COMPUTED_VALUE"""),"Yes") -> Yes | W12: =IFERROR(__xludf.DUMMYFUNCTION("""COMPUTED_VALUE"""),"[NO RYANAIR!!!]") -> [NO RYANAIR!!!]
A13: =IFERROR(__xludf.DUMMYFUNCTION("""COMPUTED_VALUE"""),"Turkey") -> Turkey | B13: =IFERROR(__xludf.DUMMYFUNCTION("""COMPUTED_VALUE"""),"TEST PHASE") -> TEST PHASE | C13: =IFERROR(__xludf.DUMMYFUNCTION("""COMPUTED_VALUE"""),"8-10 months") -> 8-10 months | E13: =IFERROR(__xludf.DUMMYFUNCTION("""COMPUTED_VALUE"""),"220 Euros (discounted in bulks)") -> 220 Euros (discounted in bulks) | F13: =IFERROR(__xludf.DUMMYFUNCTION("""COMPUTED_VALUE"""),"arround 15% of won claims or fixed amount ") -> arround 15% of won claims or fixed amount | G13: =IFERROR(__xludf.DUMMYFUNCTION("""COMPUTED_VALUE"""),"EDA AKGUL") -> EDA AKGUL | H13: =IFERROR(__xludf.DUMMYFUNCTION("""COMPUTED_VALUE"""),"eda.akgul@erten.av.tr") -> eda.akgul@erten.av.tr | J13: =IFERROR(__xludf.DUMMYFUNCTION("""COMPUTED_VALUE"""),"Turkish Jurisdiction") -> Turkish Jurisdiction | O13: =IFERROR(__xludf.DUMMYFUNCTION("""COMPUTED_VALUE"""),12.0) -> 12 | P13: =IFERROR(__xludf.DUMMYFUNCTION("""COMPUTED_VALUE"""),"2 years") -> 2 years | Q13: =IFERROR(__xludf.DUMMYFUNCTION("""COMPUTED_VALUE"""),"Yes") -> Yes | R13: =IFERROR(__xludf.DUMMYFUNCTION("""COMPUTED_VALUE"""),"Yes") -> Yes | S13: =IFERROR(__xludf.DUMMYFUNCTION("""COMPUTED_VALUE"""),"Yes") -> Yes | T13: =IFERROR(__xludf.DUMMYFUNCTION("""COMPUTED_VALUE"""),"No") -> No | U13: =IFERROR(__xludf.DUMMYFUNCTION("""COMPUTED_VALUE"""),"Yes") -> Yes | V13: =IFERROR(__xludf.DUMMYFUNCTION("""COMPUTED_VALUE"""),"No") -> No
A14: =IFERROR(__xludf.DUMMYFUNCTION("""COMPUTED_VALUE"""),"Denmark") -> Denmark | B14: =IFERROR(__xludf.DUMMYFUNCTION("""COMPUTED_VALUE"""),"TEST PHASE") -> TEST PHASE | C14: =IFERROR(__xludf.DUMMYFUNCTION("""COMPUTED_VALUE"""),"2–6 months") -> 2–6 months | D14: =IFERROR(__xludf.DUMMYFUNCTION("""COMPUTED_VALUE"""),"15% of the collected sum") -> 15% of the collected sum | J14: =IFERROR(__xludf.DUMMYFUNCTION("""COMPUTED_VALUE"""),"Denmark") -> Denmark | O14: =IFERROR(__xludf.DUMMYFUNCTION("""COMPUTED_VALUE"""),13.0) -> 13 | P14: =IFERROR(__xludf.DUMMYFUNCTION("""COMPUTED_VALUE"""),"3 years") -> 3 years | Q14: =IFERROR(__xludf.DUMMYFUNCTION("""COMPUTED_VALUE"""),"Yes") -> Yes | R14: =IFERROR(__xludf.DUMMYFUNCTION("""COMPUTED_VALUE"""),"Yes") -> Yes | S14: =IFERROR(__xludf.DUMMYFUNCTION("""COMPUTED_VALUE"""),"No") -> No | T14: =IFERROR(__xludf.DUMMYFUNCTION("""COMPUTED_VALUE"""),"Yes") -> Yes | U14: =IFERROR(__xludf.DUMMYFUNCTION("""COMPUTED_VALUE"""),"Yes") -> Yes | V14: =IFERROR(__xludf.DUMMYFUNCTION("""COMPUTED_VALUE"""),"No") -> No
A15: =IFERROR(__xludf.DUMMYFUNCTION("""COMPUTED_VALUE"""),"Norway") -> Norway | B15: =IFERROR(__xludf.DUMMYFUNCTION("""COMPUTED_VALUE"""),"TEST PHASE") -> TEST PHASE | C15: =IFERROR(__xludf.DUMMYFUNCTION("""COMPUTED_VALUE"""),"2–6 months") -> 2–6 months | D15: =IFERROR(__xludf.DUMMYFUNCTION("""COMPUTED_VALUE"""),"15% of the collected sum") -> 15% of the collected sum | J15: =IFERROR(__xludf.DUMMYFUNCTION("""COMPUTED_VALUE"""),"Norway") -> Norway | O15: =IFERROR(__xludf.DUMMYFUNCTION("""COMPUTED_VALUE"""),14.0) -> 14 | P15: =IFERROR(__xludf.DUMMYFUNCTION("""COMPUTED_VALUE"""),"3 years (check exp. time?) ") -> 3 years (check exp. time?) | Q15: =IFERROR(__xludf.DUMMYFUNCTION("""COMPUTED_VALUE"""),"Yes") -> Yes | R15: =IFERROR(__xludf.DUMMYFUNCTION("""COMPUTED_VALUE"""),"Yes") -> Yes | S15: =IFERROR(__xludf.DUMMYFUNCTION("""COMPUTED_VALUE"""),"No") -> No | T15: =IFERROR(__xludf.DUMMYFUNCTION("""COMPUTED_VALUE"""),"Yes") -> Yes | U15: =IFERROR(__xludf.DUMMYFUNCTION("""COMPUTED_VALUE"""),"Yes") -> Yes | V15: =IFERROR(__xludf.DUMMYFUNCTION("""COMPUTED_VALUE"""),"No") -> No
A16: =IFERROR(__xludf.DUMMYFUNCTION("""COMPUTED_VALUE"""),"Finland") -> Finland | B16: =IFERROR(__xludf.DUMMYFUNCTION("""COMPUTED_VALUE"""),"NO LAWYER") -> NO LAWYER | O16: =IFERROR(__xludf.DUMMYFUNCTION("""COMPUTED_VALUE"""),15.0) -> 15 | P16: =IFERROR(__xludf.DUMMYFUNCTION("""COMPUTED_VALUE"""),"3 years") -> 3 years | Q16: =IFERROR(__xludf.DUMMYFUNCTION("""COMPUTED_VALUE"""),"Yes") -> Yes | R16: =IFERROR(__xludf.DUMMYFUNCTION("""COMPUTED_VALUE"""),"Yes") -> Yes | S16: =IFERROR(__xludf.DUMMYFUNCTION("""COMPUTED_VALUE"""),"No") -> No | T16: =IFERROR(__xludf.DUMMYFUNCTION("""COMPUTED_VALUE"""),"Yes") -> Yes | U16: =IFERROR(__xludf.DUMMYFUNCTION("""COMPUTED_VALUE"""),"Yes") -> Yes | V16: =IFERROR(__xludf.DUMMYFUNCTION("""COMPUTED_VALUE"""),"No") -> No
A17: =IFERROR(__xludf.DUMMYFUNCTION("""COMPUTED_VALUE"""),"Portugal") -> Portugal | B17: =IFERROR(__xludf.DUMMYFUNCTION("""COMPUTED_VALUE"""),"NO LAWYER") -> NO LAWYER | C17: =IFERROR(__xludf.DUMMYFUNCTION("""COMPUTED_VALUE"""),"2–6 months") -> 2–6 months | E17: =IFERROR(__xludf.DUMMYFUNCTION("""COMPUTED_VALUE"""),"claims up to 5000 EUR - 102 EUR, 5000 EUR-15000 EUR - 204 EUR") -> claims up to 5000 EUR - 102 EUR, 5000 EUR-15000 EUR - 204 EUR | G17: =IFERROR(__xludf.DUMMYFUNCTION("""COMPUTED_VALUE"""),"ANDRÉ FIALHO") -> ANDRÉ FIALHO | H17: =IFERROR(__xludf.DUMMYFUNCTION("""COMPUTED_VALUE"""),"andrefialho-20648l@adv.oa.pt") -> andrefialho-20648l@adv.oa.pt | J17: =IFERROR(__xludf.DUMMYFUNCTION("""COMPUTED_VALUE"""),"Portugal") -> Portugal | O17: =IFERROR(__xludf.DUMMYFUNCTION("""COMPUTED_VALUE"""),16.0) -> 16 | P17: =IFERROR(__xludf.DUMMYFUNCTION("""COMPUTED_VALUE"""),"2 years") -> 2 years | Q17: =IFERROR(__xludf.DUMMYFUNCTION("""COMPUTED_VALUE"""),"Yes") -> Yes | R17: =IFERROR(__xludf.DUMMYFUNCTION("""COMPUTED_VALUE"""),"Yes") -> Yes | S17: =IFERROR(__xludf.DUMMYFUNCTION("""COMPUTED_VALUE"""),"Yes (ID or TAX ID number)") -> Yes (ID or TAX ID number) | T17: =IFERROR(__xludf.DUMMYFUNCTION("""COMPUTED_VALUE"""),"Yes") -> Yes | U17: =IFERROR(__xludf.DUMMYFUNCTION("""COMPUTED_VALUE"""),"Yes") -> Yes | V17: =IFERROR(__xludf.DUMMYFUNCTION("""COMPUTED_VALUE"""),"Yes") -> Yes
A18: =IFERROR(__xludf.DUMMYFUNCTION("""COMPUTED_VALUE"""),"Netherlands") -> Netherlands | B18: =IFERROR(__xludf.DUMMYFUNCTION("""COMPUTED_VALUE"""),"ACTIVELY SEARCHING") -> ACTIVELY SEARCHING | E18: =IFERROR(__xludf.DUMMYFUNCTION("""COMPUTED_VALUE"""),"claims under 500 euro - € 130 claims between 500 and 1500 euro - € 328") -> claims under 500 euro - € 130 claims between 500 and 1500 euro - € 328 | O18: =IFERROR(__xludf.DUMMYFUNCTION("""COMPUTED_VALUE"""),17.0) -> 17 | P18: =IFERROR(__xludf.DUMMYFUNCTION("""COMPUTED_VALUE"""),"2 years") -> 2 years | Q18: =IFERROR(__xludf.DUMMYFUNCTION("""COMPUTED_VALUE"""),"Yes") -> Yes | R18: =IFERROR(__xludf.DUMMYFUNCTION("""COMPUTED_VALUE"""),"Yes") -> Yes | S18: =IFERROR(__xludf.DUMMYFUNCTION("""COMPUTED_VALUE"""),"Yes") -> Yes | T18: =IFERROR(__xludf.DUMMYFUNCTION("""COMPUTED_VALUE"""),"Yes") -> Yes | U18: =IFERROR(__xludf.DUMMYFUNCTION("""COMPUTED_VALUE"""),"Yes") -> Yes | V18: =IFERROR(__xludf.DUMMYFUNCTION("""COMPUTED_VALUE"""),"Yes") -> Yes
A19: =IFERROR(__xludf.DUMMYFUNCTION("""COMPUTED_VALUE"""),"Latvia") -> Latvia | B19: =IFERROR(__xludf.DUMMYFUNCTION("""COMPUTED_VALUE"""),"NO LAWYER") -> NO LAWYER | O19: =IFERROR(__xludf.DUMMYFUNCTION("""COMPUTED_VALUE"""),18.0) -> 18 | P19: =IFERROR(__xludf.DUMMYFUNCTION("""COMPUTED_VALUE"""),"1 year") -> 1 year | Q19: =IFERROR(__xludf.DUMMYFUNCTION("""COMPUTED_VALUE"""),"Yes") -> Yes | R19: =IFERROR(__xludf.DUMMYFUNCTION("""COMPUTED_VALUE"""),"Yes") -> Yes | S19: =IFERROR(__xludf.DUMMYFUNCTION("""COMPUTED_VALUE"""),"Yes (Wizz), other No") -> Yes (Wizz), other No | T19: =IFERROR(__xludf.DUMMYFUNCTION("""COMPUTED_VALUE"""),"Yes") -> Yes | U19: =IFERROR(__xludf.DUMMYFUNCTION("""COMPUTED_VALUE"""),"No") -> No | V19: =IFERROR(__xludf.DUMMYFUNCTION("""COMPUTED_VALUE"""),"Yes") -> Yes
A20: =IFERROR(__xludf.DUMMYFUNCTION("""COMPUTED_VALUE"""),"LITHUANIA") -> LITHUANIA | B20: =IFERROR(__xludf.DUMMYFUNCTION("""COMPUTED_VALUE"""),"NO LAWYER") -> NO LAWYER | O20: =IFERROR(__xludf.DUMMYFUNCTION("""COMPUTED_VALUE"""),19.0) -> 19 | P20: =IFERROR(__xludf.DUMMYFUNCTION("""COMPUTED_VALUE"""),"3 years") -> 3 years | Q20: =IFERROR(__xludf.DUMMYFUNCTION("""COMPUTED_VALUE"""),"Yes") -> Yes | R20: =IFERROR(__xludf.DUMMYFUNCTION("""COMPUTED_VALUE"""),"Yes") -> Yes | S20: =IFERROR(__xludf.DUMMYFUNCTION("""COMPUTED_VALUE"""),"Yes (Wizz), other No") -> Yes (Wizz), other No | T20: =IFERROR(__xludf.DUMMYFUNCTION("""COMPUTED_VALUE"""),"Yes") -> Yes | U20: =IFERROR(__xludf.DUMMYFUNCTION("""COMPUTED_VALUE"""),"No") -> No | V20: =IFERROR(__xludf.DUMMYFUNCTION("""COMPUTED_VALUE"""),"Yes") -> Yes
A21: =IFERROR(__xludf.DUMMYFUNCTION("""COMPUTED_VALUE"""),"ESTONIA") -> ESTONIA | B21: =IFERROR(__xludf.DUMMYFUNCTION("""COMPUTED_VALUE"""),"NO LAWYER") -> NO LAWYER | O21: =IFERROR(__xludf.DUMMYFUNCTION("""COMPUTED_VALUE"""),20.0) -> 20 | P21: =IFERROR(__xludf.DUMMYFUNCTION("""COMPUTED_VALUE"""),"3 years") -> 3 years | Q21: =IFERROR(__xludf.DUMMYFUNCTION("""COMPUTED_VALUE"""),"Yes") -> Yes | R21: =IFERROR(__xludf.DUMMYFUNCTION("""COMPUTED_VALUE"""),"Yes") -> Yes | S21: =IFERROR(__xludf.DUMMYFUNCTION("""COMPUTED_VALUE"""),"Yes (Wizz), other No") -> Yes (Wizz), other No | T21: =IFERROR(__xludf.DUMMYFUNCTION("""COMPUTED_VALUE"""),"Yes") -> Yes | U21: =IFERROR(__xludf.DUMMYFUNCTION("""COMPUTED_VALUE"""),"No") -> No | V21: =IFERROR(__xludf.DUMMYFUNCTION("""COMPUTED_VALUE"""),"Yes") -> Yes
A22: =IFERROR(__xludf.DUMMYFUNCTION("""COMPUTED_VALUE"""),"Ireland") -> Ireland | B22: =IFERROR(__xludf.DUMMYFUNCTION("""COMPUTED_VALUE"""),"NO LAWYER") -> NO LAWYER | O22: =IFERROR(__xludf.DUMMYFUNCTION("""COMPUTED_VALUE"""),21.0) -> 21 | P22: =IFERROR(__xludf.DUMMYFUNCTION("""COMPUTED_VALUE"""),"6 years") -> 6 years | Q22: =IFERROR(__xludf.DUMMYFUNCTION("""COMPUTED_VALUE"""),"Yes") -> Yes | R22: =IFERROR(__xludf.DUMMYFUNCTION("""COMPUTED_VALUE"""),"Yes") -> Yes | S22: =IFERROR(__xludf.DUMMYFUNCTION("""COMPUTED_VALUE"""),"Yes") -> Yes | T22: =IFERROR(__xludf.DUMMYFUNCTION("""COMPUTED_VALUE"""),"Yes") -> Yes | U22: =IFERROR(__xludf.DUMMYFUNCTION("""COMPUTED_VALUE"""),"Yes") -> Yes | V22: =IFERROR(__xludf.DUMMYFUNCTION("""COMPUTED_VALUE"""),"Yes") -> Yes
A23: =IFERROR(__xludf.DUMMYFUNCTION("""COMPUTED_VALUE"""),"GREECE") -> GREECE | B23: =IFERROR(__xludf.DUMMYFUNCTION("""COMPUTED_VALUE"""),"ACTIVELY SEARCHING") -> ACTIVELY SEARCHING | C23: =IFERROR(__xludf.DUMMYFUNCTION("""COMPUTED_VALUE"""),"up to 2 years") -> up to 2 years | O23: =IFERROR(__xludf.DUMMYFUNCTION("""COMPUTED_VALUE"""),22.0) -> 22 | P23: =IFERROR(__xludf.DUMMYFUNCTION("""COMPUTED_VALUE"""),"5 years") -> 5 years | Q23: =IFERROR(__xludf.DUMMYFUNCTION("""COMPUTED_VALUE"""),"Yes") -> Yes | R23: =IFERROR(__xludf.DUMMYFUNCTION("""COMPUTED_VALUE"""),"Yes") -> Yes | S23: =IFERROR(__xludf.DUMMYFUNCTION("""COMPUTED_VALUE"""),"Yes") -> Yes | T23: =IFERROR(__xludf.DUMMYFUNCTION("""COMPUTED_VALUE"""),"Yes") -> Yes | U23: =IFERROR(__xludf.DUMMYFUNCTION("""COMPUTED_VALUE"""),"Yes") -> Yes | V23: =IFERROR(__xludf.DUMMYFUNCTION("""COMPUTED_VALUE"""),"Yes") -> Yes
A24: =IFERROR(__xludf.DUMMYFUNCTION("""COMPUTED_VALUE"""),"BULGARIA") -> BULGARIA | B24: =IFERROR(__xludf.DUMMYFUNCTION("""COMPUTED_VALUE"""),"NO LAWYER") -> NO LAWYER | O24: =IFERROR(__xludf.DUMMYFUNCTION("""COMPUTED_VALUE"""),23.0) -> 23 | P24: =IFERROR(__xludf.DUMMYFUNCTION("""COMPUTED_VALUE"""),"1 year") -> 1 year | Q24: =IFERROR(__xludf.DUMMYFUNCTION("""COMPUTED_VALUE"""),"Yes") -> Yes | R24: =IFERROR(__xludf.DUMMYFUNCTION("""COMPUTED_VALUE"""),"Yes") -> Yes | S24: =IFERROR(__xludf.DUMMYFUNCTION("""COMPUTED_VALUE"""),"Yes") -> Yes | T24: =IFERROR(__xludf.DUMMYFUNCTION("""COMPUTED_VALUE"""),"No") -> No | U24: =IFERROR(__xludf.DUMMYFUNCTION("""COMPUTED_VALUE"""),"Yes") -> Yes | V24: =IFERROR(__xludf.DUMMYFUNCTION("""COMPUTED_VALUE"""),"Yes") -> Yes
A25: =IFERROR(__xludf.DUMMYFUNCTION("""COMPUTED_VALUE"""),"ALBANIA") -> ALBANIA | B25: =IFERROR(__xludf.DUMMYFUNCTION("""COMPUTED_VALUE"""),"NO LAWYER") -> NO LAWYER | O25: =IFERROR(__xludf.DUMMYFUNCTION("""COMPUTED_VALUE"""),24.0) -> 24 | P25: =IFERROR(__xludf.DUMMYFUNCTION("""COMPUTED_VALUE"""),"3 years") -> 3 years | Q25: =IFERROR(__xludf.DUMMYFUNCTION("""COMPUTED_VALUE"""),"Yes") -> Yes | R25: =IFERROR(__xludf.DUMMYFUNCTION("""COMPUTED_VALUE"""),"Yes") -> Yes | S25: =IFERROR(__xludf.DUMMYFUNCTION("""COMPUTED_VALUE"""),"Yes") -> Yes | T25: =IFERROR(__xludf.DUMMYFUNCTION("""COMPUTED_VALUE"""),"Yes") -> Yes | U25: =IFERROR(__xludf.DUMMYFUNCTION("""COMPUTED_VALUE"""),"Yes") -> Yes | V25: =IFERROR(__xludf.DUMMYFUNCTION("""COMPUTED_VALUE"""),"Yes") -> Yes
A26: =IFERROR(__xludf.DUMMYFUNCTION("""COMPUTED_VALUE"""),"Croatia") -> Croatia | B26: =IFERROR(__xludf.DUMMYFUNCTION("""COMPUTED_VALUE"""),"NO LAWYER") -> NO LAWYER | O26: =IFERROR(__xludf.DUMMYFUNCTION("""COMPUTED_VALUE"""),25.0) -> 25 | P26: =IFERROR(__xludf.DUMMYFUNCTION("""COMPUTED_VALUE"""),"3 years") -> 3 years | Q26: =IFERROR(__xludf.DUMMYFUNCTION("""COMPUTED_VALUE"""),"Yes") -> Yes | R26: =IFERROR(__xludf.DUMMYFUNCTION("""COMPUTED_VALUE"""),"Yes") -> Yes | S26: =IFERROR(__xludf.DUMMYFUNCTION("""COMPUTED_VALUE"""),"Yes") -> Yes | T26: =IFERROR(__xludf.DUMMYFUNCTION("""COMPUTED_VALUE"""),"Yes") -> Yes | U26: =IFERROR(__xludf.DUMMYFUNCTION("""COMPUTED_VALUE"""),"Yes") -> Yes | V26: =IFERROR(__xludf.DUMMYFUNCTION("""COMPUTED_VALUE"""),"Yes") -> Yes
A27: =IFERROR(__xludf.DUMMYFUNCTION("""COMPUTED_VALUE"""),"Cyprus") -> Cyprus | B27: =IFERROR(__xludf.DUMMYFUNCTION("""COMPUTED_VALUE"""),"NO LAWYER") -> NO LAWYER | O27: =IFERROR(__xludf.DUMMYFUNCTION("""COMPUTED_VALUE"""),26.0) -> 26 | P27: =IFERROR(__xludf.DUMMYFUNCTION("""COMPUTED_VALUE"""),"6 years") -> 6 years | Q27: =IFERROR(__xludf.DUMMYFUNCTION("""COMPUTED_VALUE"""),"Yes") -> Yes | R27: =IFERROR(__xludf.DUMMYFUNCTION("""COMPUTED_VALUE"""),"Yes") -> Yes | S27: =IFERROR(__xludf.DUMMYFUNCTION("""COMPUTED_VALUE"""),"Yes") -> Yes | T27: =IFERROR(__xludf.DUMMYFUNCTION("""COMPUTED_VALUE"""),"Yes") -> Yes | U27: =IFERROR(__xludf.DUMMYFUNCTION("""COMPUTED_VALUE"""),"Yes") -> Yes | V27: =IFERROR(__xludf.DUMMYFUNCTION("""COMPUTED_VALUE"""),"Yes") -> Yes
A28: =IFERROR(__xludf.DUMMYFUNCTION("""COMPUTED_VALUE"""),"Czech Republic") -> Czech Republic | B28: =IFERROR(__xludf.DUMMYFUNCTION("""COMPUTED_VALUE"""),"NO LAWYER") -> NO LAWYER | O28: =IFERROR(__xludf.DUMMYFUNCTION("""COMPUTED_VALUE"""),27.0) -> 27 | P28: =IFERROR(__xludf.DUMMYFUNCTION("""COMPUTED_VALUE"""),"6 Months - 3 years") -> 6 Months - 3 years | Q28: =IFERROR(__xludf.DUMMYFUNCTION("""COMPUTED_VALUE"""),"Yes") -> Yes | R28: =IFERROR(__xludf.DUMMYFUNCTION("""COMPUTED_VALUE"""),"Yes") -> Yes | S28: =IFERROR(__xludf.DUMMYFUNCTION("""COMPUTED_VALUE"""),"Yes") -> Yes | T28: =IFERROR(__xludf.DUMMYFUNCTION("""COMPUTED_VALUE"""),"Yes") -> Yes | U28: =IFERROR(__xludf.DUMMYFUNCTION("""COMPUTED_VALUE"""),"Yes") -> Yes | V28: =IFERROR(__xludf.DUMMYFUNCTION("""COMPUTED_VALUE"""),"Yes") -> Yes | W28: =IFERROR(__xludf.DUMMYFUNCTION("""COMPUTED_VALUE"""),"if a passenger notifies the airline within the first 6 months after flight disruption, the claim should be eligible for 3 years.") -> if a passenger notifies the airline within the first 6 months after flight disruption, the claim should be eligible for 3 years.
A29: =IFERROR(__xludf.DUMMYFUNCTION("""COMPUTED_VALUE"""),"Iceland") -> Iceland | B29: =IFERROR(__xludf.DUMMYFUNCTION("""COMPUTED_VALUE"""),"NO LAWYER") -> NO LAWYER | O29: =IFERROR(__xludf.DUMMYFUNCTION("""COMPUTED_VALUE"""),28.0) -> 28 | P29: =IFERROR(__xludf.DUMMYFUNCTION("""COMPUTED_VALUE"""),"2 years") -> 2 years | Q29: =IFERROR(__xludf.DUMMYFUNCTION("""COMPUTED_VALUE"""),"Yes") -> Yes | R29: =IFERROR(__xludf.DUMMYFUNCTION("""COMPUTED_VALUE"""),"Yes") -> Yes | S29: =IFERROR(__xludf.DUMMYFUNCTION("""COMPUTED_VALUE"""),"Yes") -> Yes | T29: =IFERROR(__xludf.DUMMYFUNCTION("""COMPUTED_VALUE"""),"Yes") -> Yes | U29: =IFERROR(__xludf.DUMMYFUNCTION("""COMPUTED_VALUE"""),"Yes") -> Yes | V29: =IFERROR(__xludf.DUMMYFUNCTION("""COMPUTED_VALUE"""),"Yes") -> Yes
A30: =IFERROR(__xludf.DUMMYFUNCTION("""COMPUTED_VALUE"""),"Luxembourg") -> Luxembourg | B30: =IFERROR(__xludf.DUMMYFUNCTION("""COMPUTED_VALUE"""),"NO LAWYER") -> NO LAWYER | O30: =IFERROR(__xludf.DUMMYFUNCTION("""COMPUTED_VALUE"""),29.0) -> 29 | P30: =IFERROR(__xludf.DUMMYFUNCTION("""COMPUTED_VALUE"""),"10 years") -> 10 years | Q30: =IFERROR(__xludf.DUMMYFUNCTION("""COMPUTED_VALUE"""),"Yes") -> Yes | R30: =IFERROR(__xludf.DUMMYFUNCTION("""COMPUTED_VALUE"""),"Yes") -> Yes | S30: =IFERROR(__xludf.DUMMYFUNCTION("""COMPUTED_VALUE"""),"Yes") -> Yes | T30: =IFERROR(__xludf.DUMMYFUNCTION("""COMPUTED_VALUE"""),"Yes") -> Yes | U30: =IFERROR(__xludf.DUMMYFUNCTION("""COMPUTED_VALUE"""),"Yes") -> Yes | V30: =IFERROR(__xludf.DUMMYFUNCTION("""COMPUTED_VALUE"""),"Yes") -> Yes
A31: =IFERROR(__xludf.DUMMYFUNCTION("""COMPUTED_VALUE"""),"Malta") -> Malta | B31: =IFERROR(__xludf.DUMMYFUNCTION("""COMPUTED_VALUE"""),"NO LAWYER") -> NO LAWYER | O31: =IFERROR(__xludf.DUMMYFUNCTION("""COMPUTED_VALUE"""),30.0) -> 30 | P31: =IFERROR(__xludf.DUMMYFUNCTION("""COMPUTED_VALUE"""),"No limit") -> No limit | Q31: =IFERROR(__xludf.DUMMYFUNCTION("""COMPUTED_VALUE"""),"Yes") -> Yes | R31: =IFERROR(__xludf.DUMMYFUNCTION("""COMPUTED_VALUE"""),"Yes") -> Yes | S31: =IFERROR(__xludf.DUMMYFUNCTION("""COMPUTED_VALUE"""),"Yes") -> Yes | T31: =IFERROR(__xludf.DUMMYFUNCTION("""COMPUTED_VALUE"""),"Yes") -> Yes | U31: =IFERROR(__xludf.DUMMYFUNCTION("""COMPUTED_VALUE"""),"Yes") -> Yes | V31: =IFERROR(__xludf.DUMMYFUNCTION("""COMPUTED_VALUE"""),"Yes") -> Yes
A32: =IFERROR(__xludf.DUMMYFUNCTION("""COMPUTED_VALUE"""),"Slovakia") -> Slovakia | B32: =IFERROR(__xludf.DUMMYFUNCTION("""COMPUTED_VALUE"""),"NO LAWYER") -> NO LAWYER | O32: =IFERROR(__xludf.DUMMYFUNCTION("""COMPUTED_VALUE"""),31.0) -> 31 | P32: =IFERROR(__xludf.DUMMYFUNCTION("""COMPUTED_VALUE"""),"2 years") -> 2 years | Q32: =IFERROR(__xludf.DUMMYFUNCTION("""COMPUTED_VALUE"""),"Yes") -> Yes | R32: =IFERROR(__xludf.DUMMYFUNCTION("""COMPUTED_VALUE"""),"Yes") -> Yes | S32: =IFERROR(__xludf.DUMMYFUNCTION("""COMPUTED_VALUE"""),"Yes") -> Yes | T32: =IFERROR(__xludf.DUMMYFUNCTION("""COMPUTED_VALUE"""),"Yes") -> Yes | U32: =IFERROR(__xludf.DUMMYFUNCTION("""COMPUTED_VALUE"""),"Yes") -> Yes | V32: =IFERROR(__xludf.DUMMYFUNCTION("""COMPUTED_VALUE"""),"Yes") -> Yes
A33: =IFERROR(__xludf.DUMMYFUNCTION("""COMPUTED_VALUE"""),"Slovenia") -> Slovenia | B33: =IFERROR(__xludf.DUMMYFUNCTION("""COMPUTED_VALUE"""),"NO LAWYER") -> NO LAWYER | O33: =IFERROR(__xludf.DUMMYFUNCTION("""COMPUTED_VALUE"""),32.0) -> 32 | P33: =IFERROR(__xludf.DUMMYFUNCTION("""COMPUTED_VALUE"""),"2 years") -> 2 years | Q33: =IFERROR(__xludf.DUMMYFUNCTION("""COMPUTED_VALUE"""),"Yes") -> Yes | R33: =IFERROR(__xludf.DUMMYFUNCTION("""COMPUTED_VALUE"""),"Yes") -> Yes | S33: =IFERROR(__xludf.DUMMYFUNCTION("""COMPUTED_VALUE"""),"Yes") -> Yes | T33: =IFERROR(__xludf.DUMMYFUNCTION("""COMPUTED_VALUE"""),"Yes") -> Yes | U33: =IFERROR(__xludf.DUMMYFUNCTION("""COMPUTED_VALUE"""),"Yes") -> Yes | V33: =IFERROR(__xludf.DUMMYFUNCTION("""COMPUTED_VALUE"""),"Yes") -> Yes
A34: =IFERROR(__xludf.DUMMYFUNCTION("""COMPUTED_VALUE"""),"Switzerland") -> Switzerland | B34: =IFERROR(__xludf.DUMMYFUNCTION("""COMPUTED_VALUE"""),"NO LAWYER") -> NO LAWYER | O34: =IFERROR(__xludf.DUMMYFUNCTION("""COMPUTED_VALUE"""),33.0) -> 33 | P34: =IFERROR(__xludf.DUMMYFUNCTION("""COMPUTED_VALUE"""),"2 years") -> 2 years | Q34: =IFERROR(__xludf.DUMMYFUNCTION("""COMPUTED_VALUE"""),"Yes") -> Yes | R34: =IFERROR(__xludf.DUMMYFUNCTION("""COMPUTED_VALUE"""),"Yes") -> Yes | S34: =IFERROR(__xludf.DUMMYFUNCTION("""COMPUTED_VALUE"""),"Yes") -> Yes | T34: =IFERROR(__xludf.DUMMYFUNCTION("""COMPUTED_VALUE"""),"Yes") -> Yes | U34: =IFERROR(__xludf.DUMMYFUNCTION("""COMPUTED_VALUE"""),"Yes") -> Yes | V34: =IFERROR(__xludf.DUMMYFUNCTION("""COMPUTED_VALUE"""),"Yes") -> Yes
A35: =IFERROR(__xludf.DUMMYFUNCTION("""COMPUTED_VALUE"""),"Other") -> Other | B35: =IFERROR(__xludf.DUMMYFUNCTION("""COMPUTED_VALUE"""),"NO LAWYER") -> NO LAWYER | P35: =IFERROR(__xludf.DUMMYFUNCTION("""COMPUTED_VALUE"""),"2 years") -> 2 years | Q35: =IFERROR(__xludf.DUMMYFUNCTION("""COMPUTED_VALUE"""),"Yes") -> Yes | R35: =IFERROR(__xludf.DUMMYFUNCTION("""COMPUTED_VALUE"""),"Yes") -> Yes | S35: =IFERROR(__xludf.DUMMYFUNCTION("""COMPUTED_VALUE"""),"Yes") -> Yes | T35: =IFERROR(__xludf.DUMMYFUNCTION("""COMPUTED_VALUE"""),"Yes") -> Yes | U35: =IFERROR(__xludf.DUMMYFUNCTION("""COMPUTED_VALUE"""),"Yes") -> Yes | V35: =IFERROR(__xludf.DUMMYFUNCTION("""COMPUTED_VALUE"""),"Yes") -> Yes

Sheet EOC DB
A1: =IFERROR(__xludf.DUMMYFUNCTION("IMPORTRANGE(""https://docs.google.com/spreadsheets/d/1v24u0ycDMAN6KyPmcvGCkhszdC0i8StNaYU-fRzJxvM/edit?gid=818865393#gid=818865393"",""EOC DB!A:Q"")"),"World Wide") -> World Wide | D1: =IFERROR(__xludf.DUMMYFUNCTION("""COMPUTED_VALUE"""),"Ongoing issues") -> Ongoing issues | H1: =IFERROR(__xludf.DUMMYFUNCTION("""COMPUTED_VALUE"""),"Country wide issues") -> Country wide issues | M1: =IFERROR(__xludf.DUMMYFUNCTION("""COMPUTED_VALUE"""),"Airport issues") -> Airport issues
A2: =IFERROR(__xludf.DUMMYFUNCTION("""COMPUTED_VALUE"""),"Date") -> Date | B2: =IFERROR(__xludf.DUMMYFUNCTION("""COMPUTED_VALUE"""),"EVENT ") -> EVENT | C2: =IFERROR(__xludf.DUMMYFUNCTION("""COMPUTED_VALUE"""),"DECISION") -> DECISION | D2: =IFERROR(__xludf.DUMMYFUNCTION("""COMPUTED_VALUE"""),"Start Date") -> Start Date | E2: =IFERROR(__xludf.DUMMYFUNCTION("""COMPUTED_VALUE"""),"Country Affected") -> Country Affected | F2: =IFERROR(__xludf.DUMMYFUNCTION("""COMPUTED_VALUE"""),"EVENT ") -> EVENT | G2: =IFERROR(__xludf.DUMMYFUNCTION("""COMPUTED_VALUE"""),"DECISION") -> DECISION | H2: =IFERROR(__xludf.DUMMYFUNCTION("""COMPUTED_VALUE"""),"DATEAirport") -> DATEAirport | I2: =IFERROR(__xludf.DUMMYFUNCTION("""COMPUTED_VALUE"""),"Country Affected") -> Country Affected | J2: =IFERROR(__xludf.DUMMYFUNCTION("""COMPUTED_VALUE"""),"DATE") -> DATE | K2: =IFERROR(__xludf.DUMMYFUNCTION("""COMPUTED_VALUE"""),"EVENT ") -> EVENT | L2: =IFERROR(__xludf.DUMMYFUNCTION("""COMPUTED_VALUE"""),"DECISION") -> DECISION | M2: =IFERROR(__xludf.DUMMYFUNCTION("""COMPUTED_VALUE"""),"DATEAirport") -> DATEAirport | N2: =IFERROR(__xludf.DUMMYFUNCTION("""COMPUTED_VALUE"""),"Airport") -> Airport | O2: =IFERROR(__xludf.DUMMYFUNCTION("""COMPUTED_VALUE"""),"DATE") -> DATE | P2: =IFERROR(__xludf.DUMMYFUNCTION("""COMPUTED_VALUE"""),"EVENT ") -> EVENT | Q2: =IFERROR(__xludf.DUMMYFUNCTION("""COMPUTED_VALUE"""),"DECISION") -> DECISION
A3: =IFERROR(__xludf.DUMMYFUNCTION("""COMPUTED_VALUE"""),45492.0) -> 45492 | B3: =IFERROR(__xludf.DUMMYFUNCTION("""COMPUTED_VALUE"""),"Global IT Failure (Microsoft)") -> Global IT Failure (Microsoft) | C3: =IFERROR(__xludf.DUMMYFUNCTION("""COMPUTED_VALUE"""),"REJECT") -> REJECT | D3: =IFERROR(__xludf.DUMMYFUNCTION("""COMPUTED_VALUE"""),45505.0) -> 45505 | E3: =IFERROR(__xludf.DUMMYFUNCTION("""COMPUTED_VALUE"""),"Israel") -> Israel | F3: =IFERROR(__xludf.DUMMYFUNCTION("""COMPUTED_VALUE"""),"Political instability ") -> Political instability | G3: =IFERROR(__xludf.DUMMYFUNCTION("""COMPUTED_VALUE"""),"REJECT") -> REJECT | H3: =IFERROR(__xludf.DUMMYFUNCTION("""COMPUTED_VALUE"""),"45198Italy") -> 45198Italy | I3: =IFERROR(__xludf.DUMMYFUNCTION("""COMPUTED_VALUE"""),"Italy") -> Italy | J3: =IFERROR(__xludf.DUMMYFUNCTION("""COMPUTED_VALUE"""),45198.0) -> 45198 | K3: =IFERROR(__xludf.DUMMYFUNCTION("""COMPUTED_VALUE"""),"Labor unions plan aviation sector strikes") -> Labor unions plan aviation sector strikes | L3: =IFERROR(__xludf.DUMMYFUNCTION("""COMPUTED_VALUE"""),"REJECT") -> REJECT | M3: =IFERROR(__xludf.DUMMYFUNCTION("""COMPUTED_VALUE"""),"45365BER") -> 45365BER | N3: =IFERROR(__xludf.DUMMYFUNCTION("""COMPUTED_VALUE"""),"BER") -> BER | O3: =IFERROR(__xludf.DUMMYFUNCTION("""COMPUTED_VALUE"""),45365.0) -> 45365 | P3: =IFERROR(__xludf.DUMMYFUNCTION("""COMPUTED_VALUE"""),"Unionized ground staff and security employees") -> Unionized ground staff and security employees | Q3: =IFERROR(__xludf.DUMMYFUNCTION("""COMPUTED_VALUE"""),"REJECT") -> REJECT
A4: =IFERROR(__xludf.DUMMYFUNCTION("""COMPUTED_VALUE"""),45493.0) -> 45493 | B4: =IFERROR(__xludf.DUMMYFUNCTION("""COMPUTED_VALUE"""),"Global IT Failure (Microsoft)") -> Global IT Failure (Microsoft) | C4: =IFERROR(__xludf.DUMMYFUNCTION("""COMPUTED_VALUE"""),"REJECT") -> REJECT | D4: =IFERROR(__xludf.DUMMYFUNCTION("""COMPUTED_VALUE"""),45107.0) -> 45107 | E4: =IFERROR(__xludf.DUMMYFUNCTION("""COMPUTED_VALUE"""),"Syria") -> Syria | F4: =IFERROR(__xludf.DUMMYFUNCTION("""COMPUTED_VALUE"""),"Political instability ") -> Political instability | G4: =IFERROR(__xludf.DUMMYFUNCTION("""COMPUTED_VALUE"""),"REJECT") -> REJECT | H4: =IFERROR(__xludf.DUMMYFUNCTION("""COMPUTED_VALUE"""),"45585Italy") -> 45585Italy | I4: =IFERROR(__xludf.DUMMYFUNCTION("""COMPUTED_VALUE"""),"Italy") -> Italy | J4: =IFERROR(__xludf.DUMMYFUNCTION("""COMPUTED_VALUE"""),45585.0) -> 45585 | K4: =IFERROR(__xludf.DUMMYFUNCTION("""COMPUTED_VALUE"""),"ATC Strikes") -> ATC Strikes | L4: =IFERROR(__xludf.DUMMYFUNCTION("""COMPUTED_VALUE"""),"REJECT") -> REJECT | M4: =IFERROR(__xludf.DUMMYFUNCTION("""COMPUTED_VALUE"""),"45365CGN") -> 45365CGN | N4: =IFERROR(__xludf.DUMMYFUNCTION("""COMPUTED_VALUE"""),"CGN") -> CGN | O4: =IFERROR(__xludf.DUMMYFUNCTION("""COMPUTED_VALUE"""),45365.0) -> 45365 | P4: =IFERROR(__xludf.DUMMYFUNCTION("""COMPUTED_VALUE"""),"Unionized ground staff and security employees") -> Unionized ground staff and security employees | Q4: =IFERROR(__xludf.DUMMYFUNCTION("""COMPUTED_VALUE"""),"REJECT") -> REJECT
D5: =IFERROR(__xludf.DUMMYFUNCTION("""COMPUTED_VALUE"""),45107.0) -> 45107 | E5: =IFERROR(__xludf.DUMMYFUNCTION("""COMPUTED_VALUE"""),"Iraq") -> Iraq | F5: =IFERROR(__xludf.DUMMYFUNCTION("""COMPUTED_VALUE"""),"Political instability ") -> Political instability | G5: =IFERROR(__xludf.DUMMYFUNCTION("""COMPUTED_VALUE"""),"REJECT") -> REJECT | H5: =IFERROR(__xludf.DUMMYFUNCTION("""COMPUTED_VALUE"""),"45747Belgium") -> 45747Belgium | I5: =IFERROR(__xludf.DUMMYFUNCTION("""COMPUTED_VALUE"""),"Belgium") -> Belgium | J5: =IFERROR(__xludf.DUMMYFUNCTION("""COMPUTED_VALUE"""),45747.0) -> 45747 | K5: =IFERROR(__xludf.DUMMYFUNCTION("""COMPUTED_VALUE"""),"Nationwide Strike") -> Nationwide Strike | L5: =IFERROR(__xludf.DUMMYFUNCTION("""COMPUTED_VALUE"""),"REJECT") -> REJECT | M5: =IFERROR(__xludf.DUMMYFUNCTION("""COMPUTED_VALUE"""),"45365STR") -> 45365STR | N5: =IFERROR(__xludf.DUMMYFUNCTION("""COMPUTED_VALUE"""),"STR") -> STR | O5: =IFERROR(__xludf.DUMMYFUNCTION("""COMPUTED_VALUE"""),45365.0) -> 45365 | P5: =IFERROR(__xludf.DUMMYFUNCTION("""COMPUTED_VALUE"""),"Unionized ground staff and security employees") -> Unionized ground staff and security employees | Q5: =IFERROR(__xludf.DUMMYFUNCTION("""COMPUTED_VALUE"""),"REJECT") -> REJECT
D6: =IFERROR(__xludf.DUMMYFUNCTION("""COMPUTED_VALUE"""),45107.0) -> 45107 | E6: =IFERROR(__xludf.DUMMYFUNCTION("""COMPUTED_VALUE"""),"Iran") -> Iran | F6: =IFERROR(__xludf.DUMMYFUNCTION("""COMPUTED_VALUE"""),"Political instability ") -> Political instability | G6: =IFERROR(__xludf.DUMMYFUNCTION("""COMPUTED_VALUE"""),"REJECT") -> REJECT | H6: =IFERROR(__xludf.DUMMYFUNCTION("""COMPUTED_VALUE"""),"45726Germany") -> 45726Germany | I6: =IFERROR(__xludf.DUMMYFUNCTION("""COMPUTED_VALUE"""),"Germany") -> Germany | J6: =IFERROR(__xludf.DUMMYFUNCTION("""COMPUTED_VALUE"""),45726.0) -> 45726 | K6: =IFERROR(__xludf.DUMMYFUNCTION("""COMPUTED_VALUE"""),"ATC Strike") -> ATC Strike | L6: =IFERROR(__xludf.DUMMYFUNCTION("""COMPUTED_VALUE"""),"REJECT") -> REJECT | M6: =IFERROR(__xludf.DUMMYFUNCTION("""COMPUTED_VALUE"""),"45365FKB") -> 45365FKB | N6: =IFERROR(__xludf.DUMMYFUNCTION("""COMPUTED_VALUE"""),"FKB") -> FKB | O6: =IFERROR(__xludf.DUMMYFUNCTION("""COMPUTED_VALUE"""),45365.0) -> 45365 | P6: =IFERROR(__xludf.DUMMYFUNCTION("""COMPUTED_VALUE"""),"Unionized ground staff and security employees") -> Unionized ground staff and security employees | Q6: =IFERROR(__xludf.DUMMYFUNCTION("""COMPUTED_VALUE"""),"REJECT") -> REJECT
D7: =IFERROR(__xludf.DUMMYFUNCTION("""COMPUTED_VALUE"""),45107.0) -> 45107 | E7: =IFERROR(__xludf.DUMMYFUNCTION("""COMPUTED_VALUE"""),"Lebanon") -> Lebanon | F7: =IFERROR(__xludf.DUMMYFUNCTION("""COMPUTED_VALUE"""),"Political instability ") -> Political instability | G7: =IFERROR(__xludf.DUMMYFUNCTION("""COMPUTED_VALUE"""),"REJECT") -> REJECT | H7: =IFERROR(__xludf.DUMMYFUNCTION("""COMPUTED_VALUE"""),"45081Italy") -> 45081Italy | I7: =IFERROR(__xludf.DUMMYFUNCTION("""COMPUTED_VALUE"""),"Italy") -> Italy | J7: =IFERROR(__xludf.DUMMYFUNCTION("""COMPUTED_VALUE"""),45081.0) -> 45081 | K7: =IFERROR(__xludf.DUMMYFUNCTION("""COMPUTED_VALUE"""),"Air Transport Sector Strike") -> Air Transport Sector Strike | L7: =IFERROR(__xludf.DUMMYFUNCTION("""COMPUTED_VALUE"""),"REJECT") -> REJECT | M7: =IFERROR(__xludf.DUMMYFUNCTION("""COMPUTED_VALUE"""),"45323FRA") -> 45323FRA | N7: =IFERROR(__xludf.DUMMYFUNCTION("""COMPUTED_VALUE"""),"FRA") -> FRA | O7: =IFERROR(__xludf.DUMMYFUNCTION("""COMPUTED_VALUE"""),45323.0) -> 45323 | P7: =IFERROR(__xludf.DUMMYFUNCTION("""COMPUTED_VALUE"""),"Security Staff Strike") -> Security Staff Strike | Q7: =IFERROR(__xludf.DUMMYFUNCTION("""COMPUTED_VALUE"""),"REJECT") -> REJECT
D8: =IFERROR(__xludf.DUMMYFUNCTION("""COMPUTED_VALUE"""),45031.0) -> 45031 | E8: =IFERROR(__xludf.DUMMYFUNCTION("""COMPUTED_VALUE"""),"Sudan") -> Sudan | F8: =IFERROR(__xludf.DUMMYFUNCTION("""COMPUTED_VALUE"""),"Political instability ") -> Political instability | G8: =IFERROR(__xludf.DUMMYFUNCTION("""COMPUTED_VALUE"""),"REJECT") -> REJECT | H8: =IFERROR(__xludf.DUMMYFUNCTION("""COMPUTED_VALUE"""),"45701belgium") -> 45701belgium | I8: =IFERROR(__xludf.DUMMYFUNCTION("""COMPUTED_VALUE"""),"belgium") -> belgium | J8: =IFERROR(__xludf.DUMMYFUNCTION("""COMPUTED_VALUE"""),45701.0) -> 45701 | K8: =IFERROR(__xludf.DUMMYFUNCTION("""COMPUTED_VALUE"""),"Nationwide strike") -> Nationwide strike | L8: =IFERROR(__xludf.DUMMYFUNCTION("""COMPUTED_VALUE"""),"REJECT") -> REJECT | M8: =IFERROR(__xludf.DUMMYFUNCTION("""COMPUTED_VALUE"""),"45602NTE") -> 45602NTE | N8: =IFERROR(__xludf.DUMMYFUNCTION("""COMPUTED_VALUE"""),"NTE") -> NTE | O8: =IFERROR(__xludf.DUMMYFUNCTION("""COMPUTED_VALUE"""),45602.0) -> 45602 | P8: =IFERROR(__xludf.DUMMYFUNCTION("""COMPUTED_VALUE"""),"firefighter and rescue staff strike") -> firefighter and rescue staff strike | Q8: =IFERROR(__xludf.DUMMYFUNCTION("""COMPUTED_VALUE"""),"REJECT") -> REJECT
D9: =IFERROR(__xludf.DUMMYFUNCTION("""COMPUTED_VALUE"""),41699.0) -> 41699 | E9: =IFERROR(__xludf.DUMMYFUNCTION("""COMPUTED_VALUE"""),"Libya") -> Libya | F9: =IFERROR(__xludf.DUMMYFUNCTION("""COMPUTED_VALUE"""),"Political instability ") -> Political instability | G9: =IFERROR(__xludf.DUMMYFUNCTION("""COMPUTED_VALUE"""),"REJECT") -> REJECT | H9: =IFERROR(__xludf.DUMMYFUNCTION("""COMPUTED_VALUE"""),"45122Italy") -> 45122Italy | I9: =IFERROR(__xludf.DUMMYFUNCTION("""COMPUTED_VALUE"""),"Italy") -> Italy | J9: =IFERROR(__xludf.DUMMYFUNCTION("""COMPUTED_VALUE"""),45122.0) -> 45122 | K9: =IFERROR(__xludf.DUMMYFUNCTION("""COMPUTED_VALUE"""),"Labor unions aviation sector nationwide strikes") -> Labor unions aviation sector nationwide strikes | L9: =IFERROR(__xludf.DUMMYFUNCTION("""COMPUTED_VALUE"""),"REJECT") -> REJECT | M9: =IFERROR(__xludf.DUMMYFUNCTION("""COMPUTED_VALUE"""),"45603NTE") -> 45603NTE | N9: =IFERROR(__xludf.DUMMYFUNCTION("""COMPUTED_VALUE"""),"NTE") -> NTE | O9: =IFERROR(__xludf.DUMMYFUNCTION("""COMPUTED_VALUE"""),45603.0) -> 45603 | P9: =IFERROR(__xludf.DUMMYFUNCTION("""COMPUTED_VALUE"""),"firefighter and rescue staff strike") -> firefighter and rescue staff strike | Q9: =IFERROR(__xludf.DUMMYFUNCTION("""COMPUTED_VALUE"""),"REJECT") -> REJECT
D10: =IFERROR(__xludf.DUMMYFUNCTION("""COMPUTED_VALUE"""),44616.0) -> 44616 | E10: =IFERROR(__xludf.DUMMYFUNCTION("""COMPUTED_VALUE"""),"ukraine") -> ukraine | F10: =IFERROR(__xludf.DUMMYFUNCTION("""COMPUTED_VALUE"""),"Political instability ") -> Political instability | G10: =IFERROR(__xludf.DUMMYFUNCTION("""COMPUTED_VALUE"""),"REJECT") -> REJECT | H10: =IFERROR(__xludf.DUMMYFUNCTION("""COMPUTED_VALUE"""),"45595Argentina") -> 45595Argentina | I10: =IFERROR(__xludf.DUMMYFUNCTION("""COMPUTED_VALUE"""),"Argentina") -> Argentina | J10: =IFERROR(__xludf.DUMMYFUNCTION("""COMPUTED_VALUE"""),45595.0) -> 45595 | K10: =IFERROR(__xludf.DUMMYFUNCTION("""COMPUTED_VALUE"""),"Strike") -> Strike | L10: =IFERROR(__xludf.DUMMYFUNCTION("""COMPUTED_VALUE"""),"REJECT") -> REJECT | M10: =IFERROR(__xludf.DUMMYFUNCTION("""COMPUTED_VALUE"""),"45124CTA") -> 45124CTA | N10: =IFERROR(__xludf.DUMMYFUNCTION("""COMPUTED_VALUE"""),"CTA") -> CTA | O10: =IFERROR(__xludf.DUMMYFUNCTION("""COMPUTED_VALUE"""),45124.0) -> 45124 | P10: =IFERROR(__xludf.DUMMYFUNCTION("""COMPUTED_VALUE"""),"Volcanic Ash eruption of Mount Etna") -> Volcanic Ash eruption of Mount Etna | Q10: =IFERROR(__xludf.DUMMYFUNCTION("""COMPUTED_VALUE"""),"REJECT") -> REJECT
D11: =IFERROR(__xludf.DUMMYFUNCTION("""COMPUTED_VALUE"""),45992.0) -> 45992 | E11: =IFERROR(__xludf.DUMMYFUNCTION("""COMPUTED_VALUE"""),"venezuela") -> venezuela | F11: =IFERROR(__xludf.DUMMYFUNCTION("""COMPUTED_VALUE"""),"Political instability ") -> Political instability | G11: =IFERROR(__xludf.DUMMYFUNCTION("""COMPUTED_VALUE"""),"REJECT") -> REJECT | H11: =IFERROR(__xludf.DUMMYFUNCTION("""COMPUTED_VALUE"""),"45716Greece") -> 45716Greece | I11: =IFERROR(__xludf.DUMMYFUNCTION("""COMPUTED_VALUE"""),"Greece") -> Greece | J11: =IFERROR(__xludf.DUMMYFUNCTION("""COMPUTED_VALUE"""),45716.0) -> 45716 | K11: =IFERROR(__xludf.DUMMYFUNCTION("""COMPUTED_VALUE"""),"Strike") -> Strike | L11: =IFERROR(__xludf.DUMMYFUNCTION("""COMPUTED_VALUE"""),"REJECT") -> REJECT | M11: =IFERROR(__xludf.DUMMYFUNCTION("""COMPUTED_VALUE"""),"45125CTA") -> 45125CTA | N11: =IFERROR(__xludf.DUMMYFUNCTION("""COMPUTED_VALUE"""),"CTA") -> CTA | O11: =IFERROR(__xludf.DUMMYFUNCTION("""COMPUTED_VALUE"""),45125.0) -> 45125 | P11: =IFERROR(__xludf.DUMMYFUNCTION("""COMPUTED_VALUE"""),"Volcanic Ash eruption of Mount Etna") -> Volcanic Ash eruption of Mount Etna | Q11: =IFERROR(__xludf.DUMMYFUNCTION("""COMPUTED_VALUE"""),"REJECT") -> REJECT
D12: =IFERROR(__xludf.DUMMYFUNCTION("""COMPUTED_VALUE"""),46081.0) -> 46081 | E12: =IFERROR(__xludf.DUMMYFUNCTION("""COMPUTED_VALUE"""),"United Arab Emirates") -> United Arab Emirates | F12: =IFERROR(__xludf.DUMMYFUNCTION("""COMPUTED_VALUE"""),"Political instability ") -> Political instability | G12: =IFERROR(__xludf.DUMMYFUNCTION("""COMPUTED_VALUE"""),"REJECT") -> REJECT | H12: =IFERROR(__xludf.DUMMYFUNCTION("""COMPUTED_VALUE"""),"45756Greece") -> 45756Greece | I12: =IFERROR(__xludf.DUMMYFUNCTION("""COMPUTED_VALUE"""),"Greece") -> Greece | J12: =IFERROR(__xludf.DUMMYFUNCTION("""COMPUTED_VALUE"""),45756.0) -> 45756 | K12: =IFERROR(__xludf.DUMMYFUNCTION("""COMPUTED_VALUE"""),"Strike") -> Strike | L12: =IFERROR(__xludf.DUMMYFUNCTION("""COMPUTED_VALUE"""),"REJECT") -> REJECT | M12: =IFERROR(__xludf.DUMMYFUNCTION("""COMPUTED_VALUE"""),"45126CTA") -> 45126CTA | N12: =IFERROR(__xludf.DUMMYFUNCTION("""COMPUTED_VALUE"""),"CTA") -> CTA | O12: =IFERROR(__xludf.DUMMYFUNCTION("""COMPUTED_VALUE"""),45126.0) -> 45126 | P12: =IFERROR(__xludf.DUMMYFUNCTION("""COMPUTED_VALUE"""),"Volcanic Ash eruption of Mount Etna") -> Volcanic Ash eruption of Mount Etna | Q12: =IFERROR(__xludf.DUMMYFUNCTION("""COMPUTED_VALUE"""),"REJECT") -> REJECT
D13: =IFERROR(__xludf.DUMMYFUNCTION("""COMPUTED_VALUE"""),46081.0) -> 46081 | E13: =IFERROR(__xludf.DUMMYFUNCTION("""COMPUTED_VALUE"""),"Qatar") -> Qatar | F13: =IFERROR(__xludf.DUMMYFUNCTION("""COMPUTED_VALUE"""),"Political instability ") -> Political instability | G13: =IFERROR(__xludf.DUMMYFUNCTION("""COMPUTED_VALUE"""),"REJECT") -> REJECT | H13: =IFERROR(__xludf.DUMMYFUNCTION("""COMPUTED_VALUE"""),"45757Argentina") -> 45757Argentina | I13: =IFERROR(__xludf.DUMMYFUNCTION("""COMPUTED_VALUE"""),"Argentina") -> Argentina | J13: =IFERROR(__xludf.DUMMYFUNCTION("""COMPUTED_VALUE"""),45757.0) -> 45757 | K13: =IFERROR(__xludf.DUMMYFUNCTION("""COMPUTED_VALUE"""),"Strike") -> Strike | L13: =IFERROR(__xludf.DUMMYFUNCTION("""COMPUTED_VALUE"""),"REJECT") -> REJECT | M13: =IFERROR(__xludf.DUMMYFUNCTION("""COMPUTED_VALUE"""),"45127CTA") -> 45127CTA | N13: =IFERROR(__xludf.DUMMYFUNCTION("""COMPUTED_VALUE"""),"CTA") -> CTA | O13: =IFERROR(__xludf.DUMMYFUNCTION("""COMPUTED_VALUE"""),45127.0) -> 45127 | P13: =IFERROR(__xludf.DUMMYFUNCTION("""COMPUTED_VALUE"""),"Volcanic Ash eruption of Mount Etna") -> Volcanic Ash eruption of Mount Etna | Q13: =IFERROR(__xludf.DUMMYFUNCTION("""COMPUTED_VALUE"""),"REJECT") -> REJECT
D14: =IFERROR(__xludf.DUMMYFUNCTION("""COMPUTED_VALUE"""),46081.0) -> 46081 | E14: =IFERROR(__xludf.DUMMYFUNCTION("""COMPUTED_VALUE"""),"Kuwait") -> Kuwait | F14: =IFERROR(__xludf.DUMMYFUNCTION("""COMPUTED_VALUE"""),"Political instability ") -> Political instability | G14: =IFERROR(__xludf.DUMMYFUNCTION("""COMPUTED_VALUE"""),"REJECT") -> REJECT | H14: =IFERROR(__xludf.DUMMYFUNCTION("""COMPUTED_VALUE"""),"45509Bangladesh") -> 45509Bangladesh | I14: =IFERROR(__xludf.DUMMYFUNCTION("""COMPUTED_VALUE"""),"Bangladesh") -> Bangladesh | J14: =IFERROR(__xludf.DUMMYFUNCTION("""COMPUTED_VALUE"""),45509.0) -> 45509 | K14: =IFERROR(__xludf.DUMMYFUNCTION("""COMPUTED_VALUE"""),"Political instability") -> Political instability | L14: =IFERROR(__xludf.DUMMYFUNCTION("""COMPUTED_VALUE"""),"REJECT") -> REJECT | M14: =IFERROR(__xludf.DUMMYFUNCTION("""COMPUTED_VALUE"""),"45128CTA") -> 45128CTA | N14: =IFERROR(__xludf.DUMMYFUNCTION("""COMPUTED_VALUE"""),"CTA") -> CTA | O14: =IFERROR(__xludf.DUMMYFUNCTION("""COMPUTED_VALUE"""),45128.0) -> 45128 | P14: =IFERROR(__xludf.DUMMYFUNCTION("""COMPUTED_VALUE"""),"Volcanic Ash eruption of Mount Etna") -> Volcanic Ash eruption of Mount Etna | Q14: =IFERROR(__xludf.DUMMYFUNCTION("""COMPUTED_VALUE"""),"REJECT") -> REJECT
D15: =IFERROR(__xludf.DUMMYFUNCTION("""COMPUTED_VALUE"""),46081.0) -> 46081 | E15: =IFERROR(__xludf.DUMMYFUNCTION("""COMPUTED_VALUE"""),"Jordan") -> Jordan | F15: =IFERROR(__xludf.DUMMYFUNCTION("""COMPUTED_VALUE"""),"Political instability ") -> Political instability | G15: =IFERROR(__xludf.DUMMYFUNCTION("""COMPUTED_VALUE"""),"REJECT") -> REJECT | H15: =IFERROR(__xludf.DUMMYFUNCTION("""COMPUTED_VALUE"""),"45510Bangladesh") -> 45510Bangladesh | I15: =IFERROR(__xludf.DUMMYFUNCTION("""COMPUTED_VALUE"""),"Bangladesh") -> Bangladesh | J15: =IFERROR(__xludf.DUMMYFUNCTION("""COMPUTED_VALUE"""),45510.0) -> 45510 | K15: =IFERROR(__xludf.DUMMYFUNCTION("""COMPUTED_VALUE"""),"Political instability") -> Political instability | L15: =IFERROR(__xludf.DUMMYFUNCTION("""COMPUTED_VALUE"""),"REJECT") -> REJECT | M15: =IFERROR(__xludf.DUMMYFUNCTION("""COMPUTED_VALUE"""),"45129CTA") -> 45129CTA | N15: =IFERROR(__xludf.DUMMYFUNCTION("""COMPUTED_VALUE"""),"CTA") -> CTA | O15: =IFERROR(__xludf.DUMMYFUNCTION("""COMPUTED_VALUE"""),45129.0) -> 45129 | P15: =IFERROR(__xludf.DUMMYFUNCTION("""COMPUTED_VALUE"""),"Volcanic Ash eruption of Mount Etna") -> Volcanic Ash eruption of Mount Etna | Q15: =IFERROR(__xludf.DUMMYFUNCTION("""COMPUTED_VALUE"""),"REJECT") -> REJECT
D16: =IFERROR(__xludf.DUMMYFUNCTION("""COMPUTED_VALUE"""),46081.0) -> 46081 | E16: =IFERROR(__xludf.DUMMYFUNCTION("""COMPUTED_VALUE"""),"Bahrain") -> Bahrain | F16: =IFERROR(__xludf.DUMMYFUNCTION("""COMPUTED_VALUE"""),"Political instability ") -> Political instability | G16: =IFERROR(__xludf.DUMMYFUNCTION("""COMPUTED_VALUE"""),"REJECT") -> REJECT | H16: =IFERROR(__xludf.DUMMYFUNCTION("""COMPUTED_VALUE"""),"45511Bangladesh") -> 45511Bangladesh | I16: =IFERROR(__xludf.DUMMYFUNCTION("""COMPUTED_VALUE"""),"Bangladesh") -> Bangladesh | J16: =IFERROR(__xludf.DUMMYFUNCTION("""COMPUTED_VALUE"""),45511.0) -> 45511 | K16: =IFERROR(__xludf.DUMMYFUNCTION("""COMPUTED_VALUE"""),"Political instability") -> Political instability | L16: =IFERROR(__xludf.DUMMYFUNCTION("""COMPUTED_VALUE"""),"REJECT") -> REJECT | M16: =IFERROR(__xludf.DUMMYFUNCTION("""COMPUTED_VALUE"""),"45130CTA") -> 45130CTA | N16: =IFERROR(__xludf.DUMMYFUNCTION("""COMPUTED_VALUE"""),"CTA") -> CTA | O16: =IFERROR(__xludf.DUMMYFUNCTION("""COMPUTED_VALUE"""),45130.0) -> 45130 | P16: =IFERROR(__xludf.DUMMYFUNCTION("""COMPUTED_VALUE"""),"Volcanic Ash eruption of Mount Etna") -> Volcanic Ash eruption of Mount Etna | Q16: =IFERROR(__xludf.DUMMYFUNCTION("""COMPUTED_VALUE"""),"REJECT") -> REJECT
D17: =IFERROR(__xludf.DUMMYFUNCTION("""COMPUTED_VALUE"""),46081.0) -> 46081 | E17: =IFERROR(__xludf.DUMMYFUNCTION("""COMPUTED_VALUE"""),"Iran") -> Iran | F17: =IFERROR(__xludf.DUMMYFUNCTION("""COMPUTED_VALUE"""),"Political instability ") -> Political instability | G17: =IFERROR(__xludf.DUMMYFUNCTION("""COMPUTED_VALUE"""),"REJECT") -> REJECT | H17: =IFERROR(__xludf.DUMMYFUNCTION("""COMPUTED_VALUE"""),"45512Bangladesh") -> 45512Bangladesh | I17: =IFERROR(__xludf.DUMMYFUNCTION("""COMPUTED_VALUE"""),"Bangladesh") -> Bangladesh | J17: =IFERROR(__xludf.DUMMYFUNCTION("""COMPUTED_VALUE"""),45512.0) -> 45512 | K17: =IFERROR(__xludf.DUMMYFUNCTION("""COMPUTED_VALUE"""),"Political instability") -> Political instability | L17: =IFERROR(__xludf.DUMMYFUNCTION("""COMPUTED_VALUE"""),"REJECT") -> REJECT | M17: =IFERROR(__xludf.DUMMYFUNCTION("""COMPUTED_VALUE"""),"45131CTA") -> 45131CTA | N17: =IFERROR(__xludf.DUMMYFUNCTION("""COMPUTED_VALUE"""),"CTA") -> CTA | O17: =IFERROR(__xludf.DUMMYFUNCTION("""COMPUTED_VALUE"""),45131.0) -> 45131 | P17: =IFERROR(__xludf.DUMMYFUNCTION("""COMPUTED_VALUE"""),"Volcanic Ash eruption of Mount Etna") -> Volcanic Ash eruption of Mount Etna | Q17: =IFERROR(__xludf.DUMMYFUNCTION("""COMPUTED_VALUE"""),"REJECT") -> REJECT
D18: =IFERROR(__xludf.DUMMYFUNCTION("""COMPUTED_VALUE"""),46081.0) -> 46081 | E18: =IFERROR(__xludf.DUMMYFUNCTION("""COMPUTED_VALUE"""),"Saudi Arabia") -> Saudi Arabia | F18: =IFERROR(__xludf.DUMMYFUNCTION("""COMPUTED_VALUE"""),"Political instability ") -> Political instability | G18: =IFERROR(__xludf.DUMMYFUNCTION("""COMPUTED_VALUE"""),"REJECT") -> REJECT | H18: =IFERROR(__xludf.DUMMYFUNCTION("""COMPUTED_VALUE"""),"45513Bangladesh") -> 45513Bangladesh | I18: =IFERROR(__xludf.DUMMYFUNCTION("""COMPUTED_VALUE"""),"Bangladesh") -> Bangladesh | J18: =IFERROR(__xludf.DUMMYFUNCTION("""COMPUTED_VALUE"""),45513.0) -> 45513 | K18: =IFERROR(__xludf.DUMMYFUNCTION("""COMPUTED_VALUE"""),"Political instability") -> Political instability | L18: =IFERROR(__xludf.DUMMYFUNCTION("""COMPUTED_VALUE"""),"REJECT") -> REJECT | M18: =IFERROR(__xludf.DUMMYFUNCTION("""COMPUTED_VALUE"""),"45132CTA") -> 45132CTA | N18: =IFERROR(__xludf.DUMMYFUNCTION("""COMPUTED_VALUE"""),"CTA") -> CTA | O18: =IFERROR(__xludf.DUMMYFUNCTION("""COMPUTED_VALUE"""),45132.0) -> 45132 | P18: =IFERROR(__xludf.DUMMYFUNCTION("""COMPUTED_VALUE"""),"Volcanic Ash eruption of Mount Etna") -> Volcanic Ash eruption of Mount Etna | Q18: =IFERROR(__xludf.DUMMYFUNCTION("""COMPUTED_VALUE"""),"REJECT") -> REJECT
H19: =IFERROR(__xludf.DUMMYFUNCTION("""COMPUTED_VALUE"""),"45821Jordan") -> 45821Jordan | I19: =IFERROR(__xludf.DUMMYFUNCTION("""COMPUTED_VALUE"""),"Jordan") -> Jordan | J19: =IFERROR(__xludf.DUMMYFUNCTION("""COMPUTED_VALUE"""),45821.0) -> 45821 | K19: =IFERROR(__xludf.DUMMYFUNCTION("""COMPUTED_VALUE"""),"Political instability") -> Political instability | L19: =IFERROR(__xludf.DUMMYFUNCTION("""COMPUTED_VALUE"""),"REJECT") -> REJECT | M19: =IFERROR(__xludf.DUMMYFUNCTION("""COMPUTED_VALUE"""),"45133CTA") -> 45133CTA | N19: =IFERROR(__xludf.DUMMYFUNCTION("""COMPUTED_VALUE"""),"CTA") -> CTA | O19: =IFERROR(__xludf.DUMMYFUNCTION("""COMPUTED_VALUE"""),45133.0) -> 45133 | P19: =IFERROR(__xludf.DUMMYFUNCTION("""COMPUTED_VALUE"""),"Volcanic Ash eruption of Mount Etna") -> Volcanic Ash eruption of Mount Etna | Q19: =IFERROR(__xludf.DUMMYFUNCTION("""COMPUTED_VALUE"""),"REJECT") -> REJECT
H20: =IFERROR(__xludf.DUMMYFUNCTION("""COMPUTED_VALUE"""),"45822Jordan") -> 45822Jordan | I20: =IFERROR(__xludf.DUMMYFUNCTION("""COMPUTED_VALUE"""),"Jordan") -> Jordan | J20: =IFERROR(__xludf.DUMMYFUNCTION("""COMPUTED_VALUE"""),45822.0) -> 45822 | K20: =IFERROR(__xludf.DUMMYFUNCTION("""COMPUTED_VALUE"""),"Political instability") -> Political instability | L20: =IFERROR(__xludf.DUMMYFUNCTION("""COMPUTED_VALUE"""),"REJECT") -> REJECT | M20: =IFERROR(__xludf.DUMMYFUNCTION("""COMPUTED_VALUE"""),"45134CTA") -> 45134CTA | N20: =IFERROR(__xludf.DUMMYFUNCTION("""COMPUTED_VALUE"""),"CTA") -> CTA | O20: =IFERROR(__xludf.DUMMYFUNCTION("""COMPUTED_VALUE"""),45134.0) -> 45134 | P20: =IFERROR(__xludf.DUMMYFUNCTION("""COMPUTED_VALUE"""),"Volcanic Ash eruption of Mount Etna") -> Volcanic Ash eruption of Mount Etna | Q20: =IFERROR(__xludf.DUMMYFUNCTION("""COMPUTED_VALUE"""),"REJECT") -> REJECT
H21: =IFERROR(__xludf.DUMMYFUNCTION("""COMPUTED_VALUE"""),"45823Jordan") -> 45823Jordan | I21: =IFERROR(__xludf.DUMMYFUNCTION("""COMPUTED_VALUE"""),"Jordan") -> Jordan | J21: =IFERROR(__xludf.DUMMYFUNCTION("""COMPUTED_VALUE"""),45823.0) -> 45823 | K21: =IFERROR(__xludf.DUMMYFUNCTION("""COMPUTED_VALUE"""),"Political instability") -> Political instability | L21: =IFERROR(__xludf.DUMMYFUNCTION("""COMPUTED_VALUE"""),"REJECT") -> REJECT | M21: =IFERROR(__xludf.DUMMYFUNCTION("""COMPUTED_VALUE"""),"45135CTA") -> 45135CTA | N21: =IFERROR(__xludf.DUMMYFUNCTION("""COMPUTED_VALUE"""),"CTA") -> CTA | O21: =IFERROR(__xludf.DUMMYFUNCTION("""COMPUTED_VALUE"""),45135.0) -> 45135 | P21: =IFERROR(__xludf.DUMMYFUNCTION("""COMPUTED_VALUE"""),"Volcanic Ash eruption of Mount Etna") -> Volcanic Ash eruption of Mount Etna | Q21: =IFERROR(__xludf.DUMMYFUNCTION("""COMPUTED_VALUE"""),"REJECT") -> REJECT
H22: =IFERROR(__xludf.DUMMYFUNCTION("""COMPUTED_VALUE"""),"45824Jordan") -> 45824Jordan | I22: =IFERROR(__xludf.DUMMYFUNCTION("""COMPUTED_VALUE"""),"Jordan") -> Jordan | J22: =IFERROR(__xludf.DUMMYFUNCTION("""COMPUTED_VALUE"""),45824.0) -> 45824 | K22: =IFERROR(__xludf.DUMMYFUNCTION("""COMPUTED_VALUE"""),"Political instability") -> Political instability | L22: =IFERROR(__xludf.DUMMYFUNCTION("""COMPUTED_VALUE"""),"REJECT") -> REJECT | M22: =IFERROR(__xludf.DUMMYFUNCTION("""COMPUTED_VALUE"""),"45136CTA") -> 45136CTA | N22: =IFERROR(__xludf.DUMMYFUNCTION("""COMPUTED_VALUE"""),"CTA") -> CTA | O22: =IFERROR(__xludf.DUMMYFUNCTION("""COMPUTED_VALUE"""),45136.0) -> 45136 | P22: =IFERROR(__xludf.DUMMYFUNCTION("""COMPUTED_VALUE"""),"Volcanic Ash eruption of Mount Etna") -> Volcanic Ash eruption of Mount Etna | Q22: =IFERROR(__xludf.DUMMYFUNCTION("""COMPUTED_VALUE"""),"REJECT") -> REJECT
H23: =IFERROR(__xludf.DUMMYFUNCTION("""COMPUTED_VALUE"""),"45825Jordan") -> 45825Jordan | I23: =IFERROR(__xludf.DUMMYFUNCTION("""COMPUTED_VALUE"""),"Jordan") -> Jordan | J23: =IFERROR(__xludf.DUMMYFUNCTION("""COMPUTED_VALUE"""),45825.0) -> 45825 | K23: =IFERROR(__xludf.DUMMYFUNCTION("""COMPUTED_VALUE"""),"Political instability") -> Political instability | L23: =IFERROR(__xludf.DUMMYFUNCTION("""COMPUTED_VALUE"""),"REJECT") -> REJECT | M23: =IFERROR(__xludf.DUMMYFUNCTION("""COMPUTED_VALUE"""),"45137CTA") -> 45137CTA | N23: =IFERROR(__xludf.DUMMYFUNCTION("""COMPUTED_VALUE"""),"CTA") -> CTA | O23: =IFERROR(__xludf.DUMMYFUNCTION("""COMPUTED_VALUE"""),45137.0) -> 45137 | P23: =IFERROR(__xludf.DUMMYFUNCTION("""COMPUTED_VALUE"""),"Volcanic Ash eruption of Mount Etna") -> Volcanic Ash eruption of Mount Etna | Q23: =IFERROR(__xludf.DUMMYFUNCTION("""COMPUTED_VALUE"""),"REJECT") -> REJECT
H24: =IFERROR(__xludf.DUMMYFUNCTION("""COMPUTED_VALUE"""),"45826Jordan") -> 45826Jordan | I24: =IFERROR(__xludf.DUMMYFUNCTION("""COMPUTED_VALUE"""),"Jordan") -> Jordan | J24: =IFERROR(__xludf.DUMMYFUNCTION("""COMPUTED_VALUE"""),45826.0) -> 45826 | K24: =IFERROR(__xludf.DUMMYFUNCTION("""COMPUTED_VALUE"""),"Political instability") -> Political instability | L24: =IFERROR(__xludf.DUMMYFUNCTION("""COMPUTED_VALUE"""),"REJECT") -> REJECT | M24: =IFERROR(__xludf.DUMMYFUNCTION("""COMPUTED_VALUE"""),"45138CTA") -> 45138CTA | N24: =IFERROR(__xludf.DUMMYFUNCTION("""COMPUTED_VALUE"""),"CTA") -> CTA | O24: =IFERROR(__xludf.DUMMYFUNCTION("""COMPUTED_VALUE"""),45138.0) -> 45138 | P24: =IFERROR(__xludf.DUMMYFUNCTION("""COMPUTED_VALUE"""),"Volcanic Ash eruption of Mount Etna") -> Volcanic Ash eruption of Mount Etna | Q24: =IFERROR(__xludf.DUMMYFUNCTION("""COMPUTED_VALUE"""),"REJECT") -> REJECT
H25: =IFERROR(__xludf.DUMMYFUNCTION("""COMPUTED_VALUE"""),"45827Jordan") -> 45827Jordan | I25: =IFERROR(__xludf.DUMMYFUNCTION("""COMPUTED_VALUE"""),"Jordan") -> Jordan | J25: =IFERROR(__xludf.DUMMYFUNCTION("""COMPUTED_VALUE"""),45827.0) -> 45827 | K25: =IFERROR(__xludf.DUMMYFUNCTION("""COMPUTED_VALUE"""),"Political instability") -> Political instability | L25: =IFERROR(__xludf.DUMMYFUNCTION("""COMPUTED_VALUE"""),"REJECT") -> REJECT | M25: =IFERROR(__xludf.DUMMYFUNCTION("""COMPUTED_VALUE"""),"45139CTA") -> 45139CTA | N25: =IFERROR(__xludf.DUMMYFUNCTION("""COMPUTED_VALUE"""),"CTA") -> CTA | O25: =IFERROR(__xludf.DUMMYFUNCTION("""COMPUTED_VALUE"""),45139.0) -> 45139 | P25: =IFERROR(__xludf.DUMMYFUNCTION("""COMPUTED_VALUE"""),"Volcanic Ash eruption of Mount Etna") -> Volcanic Ash eruption of Mount Etna | Q25: =IFERROR(__xludf.DUMMYFUNCTION("""COMPUTED_VALUE"""),"REJECT") -> REJECT
H26: =IFERROR(__xludf.DUMMYFUNCTION("""COMPUTED_VALUE"""),"45828Jordan") -> 45828Jordan | I26: =IFERROR(__xludf.DUMMYFUNCTION("""COMPUTED_VALUE"""),"Jordan") -> Jordan | J26: =IFERROR(__xludf.DUMMYFUNCTION("""COMPUTED_VALUE"""),45828.0) -> 45828 | K26: =IFERROR(__xludf.DUMMYFUNCTION("""COMPUTED_VALUE"""),"Political instability") -> Political instability | L26: =IFERROR(__xludf.DUMMYFUNCTION("""COMPUTED_VALUE"""),"REJECT") -> REJECT | M26: =IFERROR(__xludf.DUMMYFUNCTION("""COMPUTED_VALUE"""),"45140CTA") -> 45140CTA | N26: =IFERROR(__xludf.DUMMYFUNCTION("""COMPUTED_VALUE"""),"CTA") -> CTA | O26: =IFERROR(__xludf.DUMMYFUNCTION("""COMPUTED_VALUE"""),45140.0) -> 45140 | P26: =IFERROR(__xludf.DUMMYFUNCTION("""COMPUTED_VALUE"""),"Volcanic Ash eruption of Mount Etna") -> Volcanic Ash eruption of Mount Etna | Q26: =IFERROR(__xludf.DUMMYFUNCTION("""COMPUTED_VALUE"""),"REJECT") -> REJECT
H27: =IFERROR(__xludf.DUMMYFUNCTION("""COMPUTED_VALUE"""),"45829Jordan") -> 45829Jordan | I27: =IFERROR(__xludf.DUMMYFUNCTION("""COMPUTED_VALUE"""),"Jordan") -> Jordan | J27: =IFERROR(__xludf.DUMMYFUNCTION("""COMPUTED_VALUE"""),45829.0) -> 45829 | K27: =IFERROR(__xludf.DUMMYFUNCTION("""COMPUTED_VALUE"""),"Political instability") -> Political instability | L27: =IFERROR(__xludf.DUMMYFUNCTION("""COMPUTED_VALUE"""),"REJECT") -> REJECT | M27: =IFERROR(__xludf.DUMMYFUNCTION("""COMPUTED_VALUE"""),"45141CTA") -> 45141CTA | N27: =IFERROR(__xludf.DUMMYFUNCTION("""COMPUTED_VALUE"""),"CTA") -> CTA | O27: =IFERROR(__xludf.DUMMYFUNCTION("""COMPUTED_VALUE"""),45141.0) -> 45141 | P27: =IFERROR(__xludf.DUMMYFUNCTION("""COMPUTED_VALUE"""),"Volcanic Ash eruption of Mount Etna") -> Volcanic Ash eruption of Mount Etna | Q27: =IFERROR(__xludf.DUMMYFUNCTION("""COMPUTED_VALUE"""),"REJECT") -> REJECT
H28: =IFERROR(__xludf.DUMMYFUNCTION("""COMPUTED_VALUE"""),"45830Jordan") -> 45830Jordan | I28: =IFERROR(__xludf.DUMMYFUNCTION("""COMPUTED_VALUE"""),"Jordan") -> Jordan | J28: =IFERROR(__xludf.DUMMYFUNCTION("""COMPUTED_VALUE"""),45830.0) -> 45830 | K28: =IFERROR(__xludf.DUMMYFUNCTION("""COMPUTED_VALUE"""),"Political instability") -> Political instability | L28: =IFERROR(__xludf.DUMMYFUNCTION("""COMPUTED_VALUE"""),"REJECT") -> REJECT | M28: =IFERROR(__xludf.DUMMYFUNCTION("""COMPUTED_VALUE"""),"45142CTA") -> 45142CTA | N28: =IFERROR(__xludf.DUMMYFUNCTION("""COMPUTED_VALUE"""),"CTA") -> CTA | O28: =IFERROR(__xludf.DUMMYFUNCTION("""COMPUTED_VALUE"""),45142.0) -> 45142 | P28: =IFERROR(__xludf.DUMMYFUNCTION("""COMPUTED_VALUE"""),"Volcanic Ash eruption of Mount Etna") -> Volcanic Ash eruption of Mount Etna | Q28: =IFERROR(__xludf.DUMMYFUNCTION("""COMPUTED_VALUE"""),"REJECT") -> REJECT
H29: =IFERROR(__xludf.DUMMYFUNCTION("""COMPUTED_VALUE"""),"45831Jordan") -> 45831Jordan | I29: =IFERROR(__xludf.DUMMYFUNCTION("""COMPUTED_VALUE"""),"Jordan") -> Jordan | J29: =IFERROR(__xludf.DUMMYFUNCTION("""COMPUTED_VALUE"""),45831.0) -> 45831 | K29: =IFERROR(__xludf.DUMMYFUNCTION("""COMPUTED_VALUE"""),"Political instability") -> Political instability | L29: =IFERROR(__xludf.DUMMYFUNCTION("""COMPUTED_VALUE"""),"REJECT") -> REJECT | M29: =IFERROR(__xludf.DUMMYFUNCTION("""COMPUTED_VALUE"""),"45143CTA") -> 45143CTA | N29: =IFERROR(__xludf.DUMMYFUNCTION("""COMPUTED_VALUE"""),"CTA") -> CTA | O29: =IFERROR(__xludf.DUMMYFUNCTION("""COMPUTED_VALUE"""),45143.0) -> 45143 | P29: =IFERROR(__xludf.DUMMYFUNCTION("""COMPUTED_VALUE"""),"Volcanic Ash eruption of Mount Etna") -> Volcanic Ash eruption of Mount Etna | Q29: =IFERROR(__xludf.DUMMYFUNCTION("""COMPUTED_VALUE"""),"REJECT") -> REJECT
H30: =IFERROR(__xludf.DUMMYFUNCTION("""COMPUTED_VALUE"""),"45832Jordan") -> 45832Jordan | I30: =IFERROR(__xludf.DUMMYFUNCTION("""COMPUTED_VALUE"""),"Jordan") -> Jordan | J30: =IFERROR(__xludf.DUMMYFUNCTION("""COMPUTED_VALUE"""),45832.0) -> 45832 | K30: =IFERROR(__xludf.DUMMYFUNCTION("""COMPUTED_VALUE"""),"Political instability") -> Political instability | L30: =IFERROR(__xludf.DUMMYFUNCTION("""COMPUTED_VALUE"""),"REJECT") -> REJECT | M30: =IFERROR(__xludf.DUMMYFUNCTION("""COMPUTED_VALUE"""),"45602HAV") -> 45602HAV | N30: =IFERROR(__xludf.DUMMYFUNCTION("""COMPUTED_VALUE"""),"HAV") -> HAV | O30: =IFERROR(__xludf.DUMMYFUNCTION("""COMPUTED_VALUE"""),45602.0) -> 45602 | P30: =IFERROR(__xludf.DUMMYFUNCTION("""COMPUTED_VALUE"""),"ATC") -> ATC | Q30: =IFERROR(__xludf.DUMMYFUNCTION("""COMPUTED_VALUE"""),"REJECT") -> REJECT
H31: =IFERROR(__xludf.DUMMYFUNCTION("""COMPUTED_VALUE"""),"45833Jordan") -> 45833Jordan | I31: =IFERROR(__xludf.DUMMYFUNCTION("""COMPUTED_VALUE"""),"Jordan") -> Jordan | J31: =IFERROR(__xludf.DUMMYFUNCTION("""COMPUTED_VALUE"""),45833.0) -> 45833 | K31: =IFERROR(__xludf.DUMMYFUNCTION("""COMPUTED_VALUE"""),"Political instability") -> Political instability | L31: =IFERROR(__xludf.DUMMYFUNCTION("""COMPUTED_VALUE"""),"REJECT") -> REJECT | M31: =IFERROR(__xludf.DUMMYFUNCTION("""COMPUTED_VALUE"""),"45660BER") -> 45660BER | N31: =IFERROR(__xludf.DUMMYFUNCTION("""COMPUTED_VALUE"""),"BER") -> BER | O31: =IFERROR(__xludf.DUMMYFUNCTION("""COMPUTED_VALUE"""),45660.0) -> 45660 | P31: =IFERROR(__xludf.DUMMYFUNCTION("""COMPUTED_VALUE"""),"Nationwide IT outage (Major German airports (BER - DUS - FRA - MUC-DTM-CGN) (except Leipzig and Dresden was not affected))") -> Nationwide IT outage (Major German airports (BER - DUS - FRA - MUC-DTM-CGN) (except Leipzig and Dresden was not affected)) | Q31: =IFERROR(__xludf.DUMMYFUNCTION("""COMPUTED_VALUE"""),"REJECT") -> REJECT
H32: =IFERROR(__xludf.DUMMYFUNCTION("""COMPUTED_VALUE"""),"45831Qatar") -> 45831Qatar | I32: =IFERROR(__xludf.DUMMYFUNCTION("""COMPUTED_VALUE"""),"Qatar") -> Qatar | J32: =IFERROR(__xludf.DUMMYFUNCTION("""COMPUTED_VALUE"""),45831.0) -> 45831 | K32: =IFERROR(__xludf.DUMMYFUNCTION("""COMPUTED_VALUE"""),"Political instability") -> Political instability | L32: =IFERROR(__xludf.DUMMYFUNCTION("""COMPUTED_VALUE"""),"REJECT") -> REJECT | M32: =IFERROR(__xludf.DUMMYFUNCTION("""COMPUTED_VALUE"""),"45660DUS") -> 45660DUS | N32: =IFERROR(__xludf.DUMMYFUNCTION("""COMPUTED_VALUE"""),"DUS") -> DUS | O32: =IFERROR(__xludf.DUMMYFUNCTION("""COMPUTED_VALUE"""),45660.0) -> 45660 | P32: =IFERROR(__xludf.DUMMYFUNCTION("""COMPUTED_VALUE"""),"Nationwide IT outage (Major German airports (BER - DUS - FRA - MUC-DTM-CGN) (except Leipzig and Dresden was not affected))") -> Nationwide IT outage (Major German airports (BER - DUS - FRA - MUC-DTM-CGN) (except Leipzig and Dresden was not affected)) | Q32: =IFERROR(__xludf.DUMMYFUNCTION("""COMPUTED_VALUE"""),"REJECT") -> REJECT
H33: =IFERROR(__xludf.DUMMYFUNCTION("""COMPUTED_VALUE"""),"45832Qatar") -> 45832Qatar | I33: =IFERROR(__xludf.DUMMYFUNCTION("""COMPUTED_VALUE"""),"Qatar") -> Qatar | J33: =IFERROR(__xludf.DUMMYFUNCTION("""COMPUTED_VALUE"""),45832.0) -> 45832 | K33: =IFERROR(__xludf.DUMMYFUNCTION("""COMPUTED_VALUE"""),"Political instability") -> Political instability | L33: =IFERROR(__xludf.DUMMYFUNCTION("""COMPUTED_VALUE"""),"REJECT") -> REJECT | M33: =IFERROR(__xludf.DUMMYFUNCTION("""COMPUTED_VALUE"""),"45660FRA") -> 45660FRA | N33: =IFERROR(__xludf.DUMMYFUNCTION("""COMPUTED_VALUE"""),"FRA") -> FRA | O33: =IFERROR(__xludf.DUMMYFUNCTION("""COMPUTED_VALUE"""),45660.0) -> 45660 | P33: =IFERROR(__xludf.DUMMYFUNCTION("""COMPUTED_VALUE"""),"Nationwide IT outage (Major German airports (BER - DUS - FRA - MUC-DTM-CGN) (except Leipzig and Dresden was not affected))") -> Nationwide IT outage (Major German airports (BER - DUS - FRA - MUC-DTM-CGN) (except Leipzig and Dresden was not affected)) | Q33: =IFERROR(__xludf.DUMMYFUNCTION("""COMPUTED_VALUE"""),"REJECT") -> REJECT
H34: =IFERROR(__xludf.DUMMYFUNCTION("""COMPUTED_VALUE"""),"45833Qatar") -> 45833Qatar | I34: =IFERROR(__xludf.DUMMYFUNCTION("""COMPUTED_VALUE"""),"Qatar") -> Qatar | J34: =IFERROR(__xludf.DUMMYFUNCTION("""COMPUTED_VALUE"""),45833.0) -> 45833 | K34: =IFERROR(__xludf.DUMMYFUNCTION("""COMPUTED_VALUE"""),"Political instability") -> Political instability | L34: =IFERROR(__xludf.DUMMYFUNCTION("""COMPUTED_VALUE"""),"REJECT") -> REJECT | M34: =IFERROR(__xludf.DUMMYFUNCTION("""COMPUTED_VALUE"""),"45660MUC") -> 45660MUC | N34: =IFERROR(__xludf.DUMMYFUNCTION("""COMPUTED_VALUE"""),"MUC") -> MUC | O34: =IFERROR(__xludf.DUMMYFUNCTION("""COMPUTED_VALUE"""),45660.0) -> 45660 | P34: =IFERROR(__xludf.DUMMYFUNCTION("""COMPUTED_VALUE"""),"Nationwide IT outage (Major German airports (BER - DUS - FRA - MUC-DTM-CGN) (except Leipzig and Dresden was not affected))") -> Nationwide IT outage (Major German airports (BER - DUS - FRA - MUC-DTM-CGN) (except Leipzig and Dresden was not affected)) | Q34: =IFERROR(__xludf.DUMMYFUNCTION("""COMPUTED_VALUE"""),"REJECT") -> REJECT
H35: =IFERROR(__xludf.DUMMYFUNCTION("""COMPUTED_VALUE"""),"45831Kuwait") -> 45831Kuwait | I35: =IFERROR(__xludf.DUMMYFUNCTION("""COMPUTED_VALUE"""),"Kuwait") -> Kuwait | J35: =IFERROR(__xludf.DUMMYFUNCTION("""COMPUTED_VALUE"""),45831.0) -> 45831 | K35: =IFERROR(__xludf.DUMMYFUNCTION("""COMPUTED_VALUE"""),"Political instability") -> Political instability | L35: =IFERROR(__xludf.DUMMYFUNCTION("""COMPUTED_VALUE"""),"REJECT") -> REJECT | M35: =IFERROR(__xludf.DUMMYFUNCTION("""COMPUTED_VALUE"""),"45660DTM") -> 45660DTM | N35: =IFERROR(__xludf.DUMMYFUNCTION("""COMPUTED_VALUE"""),"DTM") -> DTM | O35: =IFERROR(__xludf.DUMMYFUNCTION("""COMPUTED_VALUE"""),45660.0) -> 45660 | P35: =IFERROR(__xludf.DUMMYFUNCTION("""COMPUTED_VALUE"""),"Nationwide IT outage (Major German airports (BER - DUS - FRA - MUC-DTM-CGN) (except Leipzig and Dresden was not affected))") -> Nationwide IT outage (Major German airports (BER - DUS - FRA - MUC-DTM-CGN) (except Leipzig and Dresden was not affected)) | Q35: =IFERROR(__xludf.DUMMYFUNCTION("""COMPUTED_VALUE"""),"REJECT") -> REJECT
H36: =IFERROR(__xludf.DUMMYFUNCTION("""COMPUTED_VALUE"""),"45832Kuwait") -> 45832Kuwait | I36: =IFERROR(__xludf.DUMMYFUNCTION("""COMPUTED_VALUE"""),"Kuwait") -> Kuwait | J36: =IFERROR(__xludf.DUMMYFUNCTION("""COMPUTED_VALUE"""),45832.0) -> 45832 | K36: =IFERROR(__xludf.DUMMYFUNCTION("""COMPUTED_VALUE"""),"Political instability") -> Political instability | L36: =IFERROR(__xludf.DUMMYFUNCTION("""COMPUTED_VALUE"""),"REJECT") -> REJECT | M36: =IFERROR(__xludf.DUMMYFUNCTION("""COMPUTED_VALUE"""),"45660CGN") -> 45660CGN | N36: =IFERROR(__xludf.DUMMYFUNCTION("""COMPUTED_VALUE"""),"CGN") -> CGN | O36: =IFERROR(__xludf.DUMMYFUNCTION("""COMPUTED_VALUE"""),45660.0) -> 45660 | P36: =IFERROR(__xludf.DUMMYFUNCTION("""COMPUTED_VALUE"""),"Nationwide IT outage (Major German airports (BER - DUS - FRA - MUC-DTM-CGN) (except Leipzig and Dresden was not affected))") -> Nationwide IT outage (Major German airports (BER - DUS - FRA - MUC-DTM-CGN) (except Leipzig and Dresden was not affected)) | Q36: =IFERROR(__xludf.DUMMYFUNCTION("""COMPUTED_VALUE"""),"REJECT") -> REJECT
H37: =IFERROR(__xludf.DUMMYFUNCTION("""COMPUTED_VALUE"""),"45831bahrain") -> 45831bahrain | I37: =IFERROR(__xludf.DUMMYFUNCTION("""COMPUTED_VALUE"""),"bahrain") -> bahrain | J37: =IFERROR(__xludf.DUMMYFUNCTION("""COMPUTED_VALUE"""),45831.0) -> 45831 | K37: =IFERROR(__xludf.DUMMYFUNCTION("""COMPUTED_VALUE"""),"Political instability") -> Political instability | L37: =IFERROR(__xludf.DUMMYFUNCTION("""COMPUTED_VALUE"""),"REJECT") -> REJECT | M37: =IFERROR(__xludf.DUMMYFUNCTION("""COMPUTED_VALUE"""),"45398DXB") -> 45398DXB | N37: =IFERROR(__xludf.DUMMYFUNCTION("""COMPUTED_VALUE"""),"DXB") -> DXB | O37: =IFERROR(__xludf.DUMMYFUNCTION("""COMPUTED_VALUE"""),45398.0) -> 45398 | P37: =IFERROR(__xludf.DUMMYFUNCTION("""COMPUTED_VALUE"""),"Heavy Rainfall") -> Heavy Rainfall | Q37: =IFERROR(__xludf.DUMMYFUNCTION("""COMPUTED_VALUE"""),"REJECT") -> REJECT
H38: =IFERROR(__xludf.DUMMYFUNCTION("""COMPUTED_VALUE"""),"45832bahrain") -> 45832bahrain | I38: =IFERROR(__xludf.DUMMYFUNCTION("""COMPUTED_VALUE"""),"bahrain") -> bahrain | J38: =IFERROR(__xludf.DUMMYFUNCTION("""COMPUTED_VALUE"""),45832.0) -> 45832 | K38: =IFERROR(__xludf.DUMMYFUNCTION("""COMPUTED_VALUE"""),"Political instability") -> Political instability | L38: =IFERROR(__xludf.DUMMYFUNCTION("""COMPUTED_VALUE"""),"REJECT") -> REJECT | M38: =IFERROR(__xludf.DUMMYFUNCTION("""COMPUTED_VALUE"""),"45398DWC") -> 45398DWC | N38: =IFERROR(__xludf.DUMMYFUNCTION("""COMPUTED_VALUE"""),"DWC") -> DWC | O38: =IFERROR(__xludf.DUMMYFUNCTION("""COMPUTED_VALUE"""),45398.0) -> 45398 | P38: =IFERROR(__xludf.DUMMYFUNCTION("""COMPUTED_VALUE"""),"Heavy Rainfall") -> Heavy Rainfall | Q38: =IFERROR(__xludf.DUMMYFUNCTION("""COMPUTED_VALUE"""),"REJECT") -> REJECT
H39: =IFERROR(__xludf.DUMMYFUNCTION("""COMPUTED_VALUE"""),"45831Oman") -> 45831Oman | I39: =IFERROR(__xludf.DUMMYFUNCTION("""COMPUTED_VALUE"""),"Oman") -> Oman | J39: =IFERROR(__xludf.DUMMYFUNCTION("""COMPUTED_VALUE"""),45831.0) -> 45831 | K39: =IFERROR(__xludf.DUMMYFUNCTION("""COMPUTED_VALUE"""),"Political instability") -> Political instability | L39: =IFERROR(__xludf.DUMMYFUNCTION("""COMPUTED_VALUE"""),"REJECT") -> REJECT | M39: =IFERROR(__xludf.DUMMYFUNCTION("""COMPUTED_VALUE"""),"45399DXB") -> 45399DXB | N39: =IFERROR(__xludf.DUMMYFUNCTION("""COMPUTED_VALUE"""),"DXB") -> DXB | O39: =IFERROR(__xludf.DUMMYFUNCTION("""COMPUTED_VALUE"""),45399.0) -> 45399 | P39: =IFERROR(__xludf.DUMMYFUNCTION("""COMPUTED_VALUE"""),"Heavy Rainfall") -> Heavy Rainfall | Q39: =IFERROR(__xludf.DUMMYFUNCTION("""COMPUTED_VALUE"""),"REJECT") -> REJECT
H40: =IFERROR(__xludf.DUMMYFUNCTION("""COMPUTED_VALUE"""),"45832Oman") -> 45832Oman | I40: =IFERROR(__xludf.DUMMYFUNCTION("""COMPUTED_VALUE"""),"Oman") -> Oman | J40: =IFERROR(__xludf.DUMMYFUNCTION("""COMPUTED_VALUE"""),45832.0) -> 45832 | K40: =IFERROR(__xludf.DUMMYFUNCTION("""COMPUTED_VALUE"""),"Political instability") -> Political instability | L40: =IFERROR(__xludf.DUMMYFUNCTION("""COMPUTED_VALUE"""),"REJECT") -> REJECT | M40: =IFERROR(__xludf.DUMMYFUNCTION("""COMPUTED_VALUE"""),"45399DWC") -> 45399DWC | N40: =IFERROR(__xludf.DUMMYFUNCTION("""COMPUTED_VALUE"""),"DWC") -> DWC | O40: =IFERROR(__xludf.DUMMYFUNCTION("""COMPUTED_VALUE"""),45399.0) -> 45399 | P40: =IFERROR(__xludf.DUMMYFUNCTION("""COMPUTED_VALUE"""),"Heavy Rainfall") -> Heavy Rainfall | Q40: =IFERROR(__xludf.DUMMYFUNCTION("""COMPUTED_VALUE"""),"REJECT") -> REJECT
H41: =IFERROR(__xludf.DUMMYFUNCTION("""COMPUTED_VALUE"""),"45831United Arab Emirates") -> 45831United Arab Emirates | I41: =IFERROR(__xludf.DUMMYFUNCTION("""COMPUTED_VALUE"""),"United Arab Emirates") -> United Arab Emirates | J41: =IFERROR(__xludf.DUMMYFUNCTION("""COMPUTED_VALUE"""),45831.0) -> 45831 | K41: =IFERROR(__xludf.DUMMYFUNCTION("""COMPUTED_VALUE"""),"Political instability") -> Political instability | L41: =IFERROR(__xludf.DUMMYFUNCTION("""COMPUTED_VALUE"""),"REJECT") -> REJECT | M41: =IFERROR(__xludf.DUMMYFUNCTION("""COMPUTED_VALUE"""),"45400DXB") -> 45400DXB | N41: =IFERROR(__xludf.DUMMYFUNCTION("""COMPUTED_VALUE"""),"DXB") -> DXB | O41: =IFERROR(__xludf.DUMMYFUNCTION("""COMPUTED_VALUE"""),45400.0) -> 45400 | P41: =IFERROR(__xludf.DUMMYFUNCTION("""COMPUTED_VALUE"""),"Heavy Rainfall") -> Heavy Rainfall | Q41: =IFERROR(__xludf.DUMMYFUNCTION("""COMPUTED_VALUE"""),"REJECT") -> REJECT
H42: =IFERROR(__xludf.DUMMYFUNCTION("""COMPUTED_VALUE"""),"45832United Arab Emirates") -> 45832United Arab Emirates | I42: =IFERROR(__xludf.DUMMYFUNCTION("""COMPUTED_VALUE"""),"United Arab Emirates") -> United Arab Emirates | J42: =IFERROR(__xludf.DUMMYFUNCTION("""COMPUTED_VALUE"""),45832.0) -> 45832 | K42: =IFERROR(__xludf.DUMMYFUNCTION("""COMPUTED_VALUE"""),"Political instability") -> Political instability | L42: =IFERROR(__xludf.DUMMYFUNCTION("""COMPUTED_VALUE"""),"REJECT") -> REJECT | M42: =IFERROR(__xludf.DUMMYFUNCTION("""COMPUTED_VALUE"""),"45400DWC") -> 45400DWC | N42: =IFERROR(__xludf.DUMMYFUNCTION("""COMPUTED_VALUE"""),"DWC") -> DWC | O42: =IFERROR(__xludf.DUMMYFUNCTION("""COMPUTED_VALUE"""),45400.0) -> 45400 | P42: =IFERROR(__xludf.DUMMYFUNCTION("""COMPUTED_VALUE"""),"Heavy Rainfall") -> Heavy Rainfall | Q42: =IFERROR(__xludf.DUMMYFUNCTION("""COMPUTED_VALUE"""),"REJECT") -> REJECT
H43: =IFERROR(__xludf.DUMMYFUNCTION("""COMPUTED_VALUE"""),"45841France") -> 45841France | I43: =IFERROR(__xludf.DUMMYFUNCTION("""COMPUTED_VALUE"""),"France") -> France | J43: =IFERROR(__xludf.DUMMYFUNCTION("""COMPUTED_VALUE"""),45841.0) -> 45841 | K43: =IFERROR(__xludf.DUMMYFUNCTION("""COMPUTED_VALUE"""),"Strike (only proceed if client mentioned ""technical problems"")") -> Strike (only proceed if client mentioned "technical problems") | L43: =IFERROR(__xludf.DUMMYFUNCTION("""COMPUTED_VALUE"""),"REJECT") -> REJECT | M43: =IFERROR(__xludf.DUMMYFUNCTION("""COMPUTED_VALUE"""),"45401DXB") -> 45401DXB | N43: =IFERROR(__xludf.DUMMYFUNCTION("""COMPUTED_VALUE"""),"DXB") -> DXB | O43: =IFERROR(__xludf.DUMMYFUNCTION("""COMPUTED_VALUE"""),45401.0) -> 45401 | P43: =IFERROR(__xludf.DUMMYFUNCTION("""COMPUTED_VALUE"""),"Heavy Rainfall") -> Heavy Rainfall | Q43: =IFERROR(__xludf.DUMMYFUNCTION("""COMPUTED_VALUE"""),"REJECT") -> REJECT
H44: =IFERROR(__xludf.DUMMYFUNCTION("""COMPUTED_VALUE"""),"45842France") -> 45842France | I44: =IFERROR(__xludf.DUMMYFUNCTION("""COMPUTED_VALUE"""),"France") -> France | J44: =IFERROR(__xludf.DUMMYFUNCTION("""COMPUTED_VALUE"""),45842.0) -> 45842 | K44: =IFERROR(__xludf.DUMMYFUNCTION("""COMPUTED_VALUE"""),"Strike (only proceed if client mentioned ""technical problems with the aircraft"")") -> Strike (only proceed if client mentioned "technical problems with the aircraft") | L44: =IFERROR(__xludf.DUMMYFUNCTION("""COMPUTED_VALUE"""),"REJECT") -> REJECT | M44: =IFERROR(__xludf.DUMMYFUNCTION("""COMPUTED_VALUE"""),"45401DWC") -> 45401DWC | N44: =IFERROR(__xludf.DUMMYFUNCTION("""COMPUTED_VALUE"""),"DWC") -> DWC | O44: =IFERROR(__xludf.DUMMYFUNCTION("""COMPUTED_VALUE"""),45401.0) -> 45401 | P44: =IFERROR(__xludf.DUMMYFUNCTION("""COMPUTED_VALUE"""),"Heavy Rainfall") -> Heavy Rainfall | Q44: =IFERROR(__xludf.DUMMYFUNCTION("""COMPUTED_VALUE"""),"REJECT") -> REJECT
H45: =IFERROR(__xludf.DUMMYFUNCTION("""COMPUTED_VALUE"""),"45841Spain") -> 45841Spain | I45: =IFERROR(__xludf.DUMMYFUNCTION("""COMPUTED_VALUE"""),"Spain") -> Spain | J45: =IFERROR(__xludf.DUMMYFUNCTION("""COMPUTED_VALUE"""),45841.0) -> 45841 | K45: =IFERROR(__xludf.DUMMYFUNCTION("""COMPUTED_VALUE"""),"ATC strike in France affected airport's operations proceed if the client didn't mention (strike/Force majeure /Problems at the airport/Influence by other flights)") -> ATC strike in France affected airport's operations proceed if the client didn't mention (strike/Force majeure /Problems at the airport/Influence by other flights) | L45: =IFERROR(__xludf.DUMMYFUNCTION("""COMPUTED_VALUE"""),"REJECT") -> REJECT | M45: =IFERROR(__xludf.DUMMYFUNCTION("""COMPUTED_VALUE"""),"45402DXB") -> 45402DXB | N45: =IFERROR(__xludf.DUMMYFUNCTION("""COMPUTED_VALUE"""),"DXB") -> DXB | O45: =IFERROR(__xludf.DUMMYFUNCTION("""COMPUTED_VALUE"""),45402.0) -> 45402 | P45: =IFERROR(__xludf.DUMMYFUNCTION("""COMPUTED_VALUE"""),"Heavy Rainfall") -> Heavy Rainfall | Q45: =IFERROR(__xludf.DUMMYFUNCTION("""COMPUTED_VALUE"""),"REJECT") -> REJECT
H46: =IFERROR(__xludf.DUMMYFUNCTION("""COMPUTED_VALUE"""),"45842Spain") -> 45842Spain | I46: =IFERROR(__xludf.DUMMYFUNCTION("""COMPUTED_VALUE"""),"Spain") -> Spain | J46: =IFERROR(__xludf.DUMMYFUNCTION("""COMPUTED_VALUE"""),45842.0) -> 45842 | K46: =IFERROR(__xludf.DUMMYFUNCTION("""COMPUTED_VALUE"""),"ATC strike in France affected airport's operations proceed if the client didn't mention (strike/Force majeure /Problems at the airport/Influence by other flights)") -> ATC strike in France affected airport's operations proceed if the client didn't mention (strike/Force majeure /Problems at the airport/Influence by other flights) | L46: =IFERROR(__xludf.DUMMYFUNCTION("""COMPUTED_VALUE"""),"REJECT") -> REJECT | M46: =IFERROR(__xludf.DUMMYFUNCTION("""COMPUTED_VALUE"""),"45402DWC") -> 45402DWC | N46: =IFERROR(__xludf.DUMMYFUNCTION("""COMPUTED_VALUE"""),"DWC") -> DWC | O46: =IFERROR(__xludf.DUMMYFUNCTION("""COMPUTED_VALUE"""),45402.0) -> 45402 | P46: =IFERROR(__xludf.DUMMYFUNCTION("""COMPUTED_VALUE"""),"Heavy Rainfall") -> Heavy Rainfall | Q46: =IFERROR(__xludf.DUMMYFUNCTION("""COMPUTED_VALUE"""),"REJECT") -> REJECT
H47: =IFERROR(__xludf.DUMMYFUNCTION("""COMPUTED_VALUE"""),"45910Poland") -> 45910Poland | I47: =IFERROR(__xludf.DUMMYFUNCTION("""COMPUTED_VALUE"""),"Poland") -> Poland | J47: =IFERROR(__xludf.DUMMYFUNCTION("""COMPUTED_VALUE"""),45910.0) -> 45910 | K47: =IFERROR(__xludf.DUMMYFUNCTION("""COMPUTED_VALUE"""),"Political instability") -> Political instability | L47: =IFERROR(__xludf.DUMMYFUNCTION("""COMPUTED_VALUE"""),"REJECT") -> REJECT | M47: =IFERROR(__xludf.DUMMYFUNCTION("""COMPUTED_VALUE"""),"45585DUB") -> 45585DUB | N47: =IFERROR(__xludf.DUMMYFUNCTION("""COMPUTED_VALUE"""),"DUB") -> DUB | O47: =IFERROR(__xludf.DUMMYFUNCTION("""COMPUTED_VALUE"""),45585.0) -> 45585 | P47: =IFERROR(__xludf.DUMMYFUNCTION("""COMPUTED_VALUE"""),"Storm Ashley") -> Storm Ashley | Q47: =IFERROR(__xludf.DUMMYFUNCTION("""COMPUTED_VALUE"""),"REJECT") -> REJECT
H48: =IFERROR(__xludf.DUMMYFUNCTION("""COMPUTED_VALUE"""),"45910France") -> 45910France | I48: =IFERROR(__xludf.DUMMYFUNCTION("""COMPUTED_VALUE"""),"France") -> France | J48: =IFERROR(__xludf.DUMMYFUNCTION("""COMPUTED_VALUE"""),45910.0) -> 45910 | K48: =IFERROR(__xludf.DUMMYFUNCTION("""COMPUTED_VALUE"""),"Strike (proceed if the client didn't mention (strike/Force majeure /Problems at the airport/Influence by other flights)") -> Strike (proceed if the client didn't mention (strike/Force majeure /Problems at the airport/Influence by other flights) | L48: =IFERROR(__xludf.DUMMYFUNCTION("""COMPUTED_VALUE"""),"REJECT") -> REJECT | M48: =IFERROR(__xludf.DUMMYFUNCTION("""COMPUTED_VALUE"""),"44771FRA") -> 44771FRA | N48: =IFERROR(__xludf.DUMMYFUNCTION("""COMPUTED_VALUE"""),"FRA") -> FRA | O48: =IFERROR(__xludf.DUMMYFUNCTION("""COMPUTED_VALUE"""),44771.0) -> 44771 | P48: =IFERROR(__xludf.DUMMYFUNCTION("""COMPUTED_VALUE"""),"ATC") -> ATC | Q48: =IFERROR(__xludf.DUMMYFUNCTION("""COMPUTED_VALUE"""),"REJECT") -> REJECT
H49: =IFERROR(__xludf.DUMMYFUNCTION("""COMPUTED_VALUE"""),"45925Madagascar") -> 45925Madagascar | I49: =IFERROR(__xludf.DUMMYFUNCTION("""COMPUTED_VALUE"""),"Madagascar") -> Madagascar | J49: =IFERROR(__xludf.DUMMYFUNCTION("""COMPUTED_VALUE"""),45925.0) -> 45925 | K49: =IFERROR(__xludf.DUMMYFUNCTION("""COMPUTED_VALUE"""),"Political instability") -> Political instability | L49: =IFERROR(__xludf.DUMMYFUNCTION("""COMPUTED_VALUE"""),"REJECT") -> REJECT | M49: =IFERROR(__xludf.DUMMYFUNCTION("""COMPUTED_VALUE"""),"45107GVA") -> 45107GVA | N49: =IFERROR(__xludf.DUMMYFUNCTION("""COMPUTED_VALUE"""),"GVA") -> GVA | O49: =IFERROR(__xludf.DUMMYFUNCTION("""COMPUTED_VALUE"""),45107.0) -> 45107 | P49: =IFERROR(__xludf.DUMMYFUNCTION("""COMPUTED_VALUE"""),"workers strike") -> workers strike | Q49: =IFERROR(__xludf.DUMMYFUNCTION("""COMPUTED_VALUE"""),"REJECT") -> REJECT
H50: =IFERROR(__xludf.DUMMYFUNCTION("""COMPUTED_VALUE"""),"45926Madagascar") -> 45926Madagascar | I50: =IFERROR(__xludf.DUMMYFUNCTION("""COMPUTED_VALUE"""),"Madagascar") -> Madagascar | J50: =IFERROR(__xludf.DUMMYFUNCTION("""COMPUTED_VALUE"""),45926.0) -> 45926 | K50: =IFERROR(__xludf.DUMMYFUNCTION("""COMPUTED_VALUE"""),"Political instability") -> Political instability | L50: =IFERROR(__xludf.DUMMYFUNCTION("""COMPUTED_VALUE"""),"REJECT") -> REJECT | M50: =IFERROR(__xludf.DUMMYFUNCTION("""COMPUTED_VALUE"""),"45323STR") -> 45323STR | N50: =IFERROR(__xludf.DUMMYFUNCTION("""COMPUTED_VALUE"""),"STR") -> STR | O50: =IFERROR(__xludf.DUMMYFUNCTION("""COMPUTED_VALUE"""),45323.0) -> 45323 | P50: =IFERROR(__xludf.DUMMYFUNCTION("""COMPUTED_VALUE"""),"Verdi trade union strike") -> Verdi trade union strike | Q50: =IFERROR(__xludf.DUMMYFUNCTION("""COMPUTED_VALUE"""),"REJECT") -> REJECT
H51: =IFERROR(__xludf.DUMMYFUNCTION("""COMPUTED_VALUE"""),"45927Madagascar") -> 45927Madagascar | I51: =IFERROR(__xludf.DUMMYFUNCTION("""COMPUTED_VALUE"""),"Madagascar") -> Madagascar | J51: =IFERROR(__xludf.DUMMYFUNCTION("""COMPUTED_VALUE"""),45927.0) -> 45927 | K51: =IFERROR(__xludf.DUMMYFUNCTION("""COMPUTED_VALUE"""),"Political instability") -> Political instability | L51: =IFERROR(__xludf.DUMMYFUNCTION("""COMPUTED_VALUE"""),"REJECT") -> REJECT | M51: =IFERROR(__xludf.DUMMYFUNCTION("""COMPUTED_VALUE"""),"45358FRA") -> 45358FRA | N51: =IFERROR(__xludf.DUMMYFUNCTION("""COMPUTED_VALUE"""),"FRA") -> FRA | O51: =IFERROR(__xludf.DUMMYFUNCTION("""COMPUTED_VALUE"""),45358.0) -> 45358 | P51: =IFERROR(__xludf.DUMMYFUNCTION("""COMPUTED_VALUE"""),"Security Staff Strike") -> Security Staff Strike | Q51: =IFERROR(__xludf.DUMMYFUNCTION("""COMPUTED_VALUE"""),"REJECT") -> REJECT
H52: =IFERROR(__xludf.DUMMYFUNCTION("""COMPUTED_VALUE"""),"45928Madagascar") -> 45928Madagascar | I52: =IFERROR(__xludf.DUMMYFUNCTION("""COMPUTED_VALUE"""),"Madagascar") -> Madagascar | J52: =IFERROR(__xludf.DUMMYFUNCTION("""COMPUTED_VALUE"""),45928.0) -> 45928 | K52: =IFERROR(__xludf.DUMMYFUNCTION("""COMPUTED_VALUE"""),"Political instability") -> Political instability | L52: =IFERROR(__xludf.DUMMYFUNCTION("""COMPUTED_VALUE"""),"REJECT") -> REJECT | M52: =IFERROR(__xludf.DUMMYFUNCTION("""COMPUTED_VALUE"""),"45359FRA") -> 45359FRA | N52: =IFERROR(__xludf.DUMMYFUNCTION("""COMPUTED_VALUE"""),"FRA") -> FRA | O52: =IFERROR(__xludf.DUMMYFUNCTION("""COMPUTED_VALUE"""),45359.0) -> 45359 | P52: =IFERROR(__xludf.DUMMYFUNCTION("""COMPUTED_VALUE"""),"Security Staff Strike") -> Security Staff Strike | Q52: =IFERROR(__xludf.DUMMYFUNCTION("""COMPUTED_VALUE"""),"REJECT") -> REJECT
H53: =IFERROR(__xludf.DUMMYFUNCTION("""COMPUTED_VALUE"""),"45929Madagascar") -> 45929Madagascar | I53: =IFERROR(__xludf.DUMMYFUNCTION("""COMPUTED_VALUE"""),"Madagascar") -> Madagascar | J53: =IFERROR(__xludf.DUMMYFUNCTION("""COMPUTED_VALUE"""),45929.0) -> 45929 | K53: =IFERROR(__xludf.DUMMYFUNCTION("""COMPUTED_VALUE"""),"Political instability") -> Political instability | L53: =IFERROR(__xludf.DUMMYFUNCTION("""COMPUTED_VALUE"""),"REJECT") -> REJECT | M53: =IFERROR(__xludf.DUMMYFUNCTION("""COMPUTED_VALUE"""),"45407CDG ") -> 45407CDG | N53: =IFERROR(__xludf.DUMMYFUNCTION("""COMPUTED_VALUE"""),"CDG ") -> CDG | O53: =IFERROR(__xludf.DUMMYFUNCTION("""COMPUTED_VALUE"""),45407.0) -> 45407 | P53: =IFERROR(__xludf.DUMMYFUNCTION("""COMPUTED_VALUE"""),"Strike") -> Strike | Q53: =IFERROR(__xludf.DUMMYFUNCTION("""COMPUTED_VALUE"""),"REJECT") -> REJECT
H54: =IFERROR(__xludf.DUMMYFUNCTION("""COMPUTED_VALUE"""),"45930Madagascar") -> 45930Madagascar | I54: =IFERROR(__xludf.DUMMYFUNCTION("""COMPUTED_VALUE"""),"Madagascar") -> Madagascar | J54: =IFERROR(__xludf.DUMMYFUNCTION("""COMPUTED_VALUE"""),45930.0) -> 45930 | K54: =IFERROR(__xludf.DUMMYFUNCTION("""COMPUTED_VALUE"""),"Political instability") -> Political instability | L54: =IFERROR(__xludf.DUMMYFUNCTION("""COMPUTED_VALUE"""),"REJECT") -> REJECT | M54: =IFERROR(__xludf.DUMMYFUNCTION("""COMPUTED_VALUE"""),"45407ORY") -> 45407ORY | N54: =IFERROR(__xludf.DUMMYFUNCTION("""COMPUTED_VALUE"""),"ORY") -> ORY | O54: =IFERROR(__xludf.DUMMYFUNCTION("""COMPUTED_VALUE"""),45407.0) -> 45407 | P54: =IFERROR(__xludf.DUMMYFUNCTION("""COMPUTED_VALUE"""),"Strike") -> Strike | Q54: =IFERROR(__xludf.DUMMYFUNCTION("""COMPUTED_VALUE"""),"REJECT") -> REJECT
H55: =IFERROR(__xludf.DUMMYFUNCTION("""COMPUTED_VALUE"""),"45944Belgium") -> 45944Belgium | I55: =IFERROR(__xludf.DUMMYFUNCTION("""COMPUTED_VALUE"""),"Belgium") -> Belgium | J55: =IFERROR(__xludf.DUMMYFUNCTION("""COMPUTED_VALUE"""),45944.0) -> 45944 | K55: =IFERROR(__xludf.DUMMYFUNCTION("""COMPUTED_VALUE"""),"National strike") -> National strike | L55: =IFERROR(__xludf.DUMMYFUNCTION("""COMPUTED_VALUE"""),"REJECT") -> REJECT | M55: =IFERROR(__xludf.DUMMYFUNCTION("""COMPUTED_VALUE"""),"45445LIM") -> 45445LIM | N55: =IFERROR(__xludf.DUMMYFUNCTION("""COMPUTED_VALUE"""),"LIM") -> LIM | O55: =IFERROR(__xludf.DUMMYFUNCTION("""COMPUTED_VALUE"""),45445.0) -> 45445 | P55: =IFERROR(__xludf.DUMMYFUNCTION("""COMPUTED_VALUE"""),"runway light outage") -> runway light outage | Q55: =IFERROR(__xludf.DUMMYFUNCTION("""COMPUTED_VALUE"""),"REJECT") -> REJECT
H56: =IFERROR(__xludf.DUMMYFUNCTION("""COMPUTED_VALUE"""),"45987Belgium") -> 45987Belgium | I56: =IFERROR(__xludf.DUMMYFUNCTION("""COMPUTED_VALUE"""),"Belgium") -> Belgium | J56: =IFERROR(__xludf.DUMMYFUNCTION("""COMPUTED_VALUE"""),45987.0) -> 45987 | K56: =IFERROR(__xludf.DUMMYFUNCTION("""COMPUTED_VALUE"""),"National strike") -> National strike | L56: =IFERROR(__xludf.DUMMYFUNCTION("""COMPUTED_VALUE"""),"REJECT") -> REJECT | M56: =IFERROR(__xludf.DUMMYFUNCTION("""COMPUTED_VALUE"""),"45472JMK") -> 45472JMK | N56: =IFERROR(__xludf.DUMMYFUNCTION("""COMPUTED_VALUE"""),"JMK") -> JMK | O56: =IFERROR(__xludf.DUMMYFUNCTION("""COMPUTED_VALUE"""),45472.0) -> 45472 | P56: =IFERROR(__xludf.DUMMYFUNCTION("""COMPUTED_VALUE"""),"Adverse weather") -> Adverse weather | Q56: =IFERROR(__xludf.DUMMYFUNCTION("""COMPUTED_VALUE"""),"REJECT") -> REJECT
H57: =IFERROR(__xludf.DUMMYFUNCTION("""COMPUTED_VALUE"""),"46002Portugal") -> 46002Portugal | I57: =IFERROR(__xludf.DUMMYFUNCTION("""COMPUTED_VALUE"""),"Portugal") -> Portugal | J57: =IFERROR(__xludf.DUMMYFUNCTION("""COMPUTED_VALUE"""),46002.0) -> 46002 | K57: =IFERROR(__xludf.DUMMYFUNCTION("""COMPUTED_VALUE"""),"National strike") -> National strike | L57: =IFERROR(__xludf.DUMMYFUNCTION("""COMPUTED_VALUE"""),"REJECT") -> REJECT | M57: =IFERROR(__xludf.DUMMYFUNCTION("""COMPUTED_VALUE"""),"45485ZRH") -> 45485ZRH | N57: =IFERROR(__xludf.DUMMYFUNCTION("""COMPUTED_VALUE"""),"ZRH") -> ZRH | O57: =IFERROR(__xludf.DUMMYFUNCTION("""COMPUTED_VALUE"""),45485.0) -> 45485 | P57: =IFERROR(__xludf.DUMMYFUNCTION("""COMPUTED_VALUE"""),"ATC") -> ATC | Q57: =IFERROR(__xludf.DUMMYFUNCTION("""COMPUTED_VALUE"""),"REJECT") -> REJECT
H58: =IFERROR(__xludf.DUMMYFUNCTION("""COMPUTED_VALUE"""),"45968United States") -> 45968United States | I58: =IFERROR(__xludf.DUMMYFUNCTION("""COMPUTED_VALUE"""),"United States") -> United States | J58: =IFERROR(__xludf.DUMMYFUNCTION("""COMPUTED_VALUE"""),45968.0) -> 45968 | K58: =IFERROR(__xludf.DUMMYFUNCTION("""COMPUTED_VALUE"""),"The FAA's emergency") -> The FAA's emergency | L58: =IFERROR(__xludf.DUMMYFUNCTION("""COMPUTED_VALUE"""),"REJECT") -> REJECT | M58: =IFERROR(__xludf.DUMMYFUNCTION("""COMPUTED_VALUE"""),"45495SPU") -> 45495SPU | N58: =IFERROR(__xludf.DUMMYFUNCTION("""COMPUTED_VALUE"""),"SPU") -> SPU | O58: =IFERROR(__xludf.DUMMYFUNCTION("""COMPUTED_VALUE"""),45495.0) -> 45495 | P58: =IFERROR(__xludf.DUMMYFUNCTION("""COMPUTED_VALUE"""),"A cyber attack blocks the system") -> A cyber attack blocks the system | Q58: =IFERROR(__xludf.DUMMYFUNCTION("""COMPUTED_VALUE"""),"REJECT") -> REJECT
H59: =IFERROR(__xludf.DUMMYFUNCTION("""COMPUTED_VALUE"""),"45972United States") -> 45972United States | I59: =IFERROR(__xludf.DUMMYFUNCTION("""COMPUTED_VALUE"""),"United States") -> United States | J59: =IFERROR(__xludf.DUMMYFUNCTION("""COMPUTED_VALUE"""),45972.0) -> 45972 | K59: =IFERROR(__xludf.DUMMYFUNCTION("""COMPUTED_VALUE"""),"The FAA's emergency") -> The FAA's emergency | L59: =IFERROR(__xludf.DUMMYFUNCTION("""COMPUTED_VALUE"""),"REJECT") -> REJECT | M59: =IFERROR(__xludf.DUMMYFUNCTION("""COMPUTED_VALUE"""),"45498FRA") -> 45498FRA | N59: =IFERROR(__xludf.DUMMYFUNCTION("""COMPUTED_VALUE"""),"FRA") -> FRA | O59: =IFERROR(__xludf.DUMMYFUNCTION("""COMPUTED_VALUE"""),45498.0) -> 45498 | P59: =IFERROR(__xludf.DUMMYFUNCTION("""COMPUTED_VALUE"""),"ATC") -> ATC | Q59: =IFERROR(__xludf.DUMMYFUNCTION("""COMPUTED_VALUE"""),"REJECT") -> REJECT
H60: =IFERROR(__xludf.DUMMYFUNCTION("""COMPUTED_VALUE"""),"45974United States") -> 45974United States | I60: =IFERROR(__xludf.DUMMYFUNCTION("""COMPUTED_VALUE"""),"United States") -> United States | J60: =IFERROR(__xludf.DUMMYFUNCTION("""COMPUTED_VALUE"""),45974.0) -> 45974 | K60: =IFERROR(__xludf.DUMMYFUNCTION("""COMPUTED_VALUE"""),"The FAA's emergency") -> The FAA's emergency | L60: =IFERROR(__xludf.DUMMYFUNCTION("""COMPUTED_VALUE"""),"REJECT") -> REJECT | M60: =IFERROR(__xludf.DUMMYFUNCTION("""COMPUTED_VALUE"""),"45499BSL") -> 45499BSL | N60: =IFERROR(__xludf.DUMMYFUNCTION("""COMPUTED_VALUE"""),"BSL") -> BSL | O60: =IFERROR(__xludf.DUMMYFUNCTION("""COMPUTED_VALUE"""),45499.0) -> 45499 | P60: =IFERROR(__xludf.DUMMYFUNCTION("""COMPUTED_VALUE"""),"safety reasons") -> safety reasons | Q60: =IFERROR(__xludf.DUMMYFUNCTION("""COMPUTED_VALUE"""),"REJECT") -> REJECT
H61: =IFERROR(__xludf.DUMMYFUNCTION("""COMPUTED_VALUE"""),"45975United States") -> 45975United States | I61: =IFERROR(__xludf.DUMMYFUNCTION("""COMPUTED_VALUE"""),"United States") -> United States | J61: =IFERROR(__xludf.DUMMYFUNCTION("""COMPUTED_VALUE"""),45975.0) -> 45975 | K61: =IFERROR(__xludf.DUMMYFUNCTION("""COMPUTED_VALUE"""),"The FAA's emergency") -> The FAA's emergency | L61: =IFERROR(__xludf.DUMMYFUNCTION("""COMPUTED_VALUE"""),"REJECT") -> REJECT | M61: =IFERROR(__xludf.DUMMYFUNCTION("""COMPUTED_VALUE"""),"45505BEG") -> 45505BEG | N61: =IFERROR(__xludf.DUMMYFUNCTION("""COMPUTED_VALUE"""),"BEG") -> BEG | O61: =IFERROR(__xludf.DUMMYFUNCTION("""COMPUTED_VALUE"""),45505.0) -> 45505 | P61: =IFERROR(__xludf.DUMMYFUNCTION("""COMPUTED_VALUE"""),"malfunction in Airport's IT system") -> malfunction in Airport's IT system | Q61: =IFERROR(__xludf.DUMMYFUNCTION("""COMPUTED_VALUE"""),"REJECT") -> REJECT
H62: =IFERROR(__xludf.DUMMYFUNCTION("""COMPUTED_VALUE"""),"45989Italy") -> 45989Italy | I62: =IFERROR(__xludf.DUMMYFUNCTION("""COMPUTED_VALUE"""),"Italy") -> Italy | J62: =IFERROR(__xludf.DUMMYFUNCTION("""COMPUTED_VALUE"""),45989.0) -> 45989 | K62: =IFERROR(__xludf.DUMMYFUNCTION("""COMPUTED_VALUE"""),"Strike, Proceed if the client and airline didn't mention strike ") -> Strike, Proceed if the client and airline didn't mention strike | L62: =IFERROR(__xludf.DUMMYFUNCTION("""COMPUTED_VALUE"""),"REJECT") -> REJECT | M62: =IFERROR(__xludf.DUMMYFUNCTION("""COMPUTED_VALUE"""),"45547CRL") -> 45547CRL | N62: =IFERROR(__xludf.DUMMYFUNCTION("""COMPUTED_VALUE"""),"CRL") -> CRL | O62: =IFERROR(__xludf.DUMMYFUNCTION("""COMPUTED_VALUE"""),45547.0) -> 45547 | P62: =IFERROR(__xludf.DUMMYFUNCTION("""COMPUTED_VALUE"""),"Labour Strike") -> Labour Strike | Q62: =IFERROR(__xludf.DUMMYFUNCTION("""COMPUTED_VALUE"""),"REJECT") -> REJECT
H63: =IFERROR(__xludf.DUMMYFUNCTION("""COMPUTED_VALUE"""),"46026Greece") -> 46026Greece | I63: =IFERROR(__xludf.DUMMYFUNCTION("""COMPUTED_VALUE"""),"Greece") -> Greece | J63: =IFERROR(__xludf.DUMMYFUNCTION("""COMPUTED_VALUE"""),46026.0) -> 46026 | K63: =IFERROR(__xludf.DUMMYFUNCTION("""COMPUTED_VALUE"""),"ATC Strike") -> ATC Strike | L63: =IFERROR(__xludf.DUMMYFUNCTION("""COMPUTED_VALUE"""),"REJECT") -> REJECT | M63: =IFERROR(__xludf.DUMMYFUNCTION("""COMPUTED_VALUE"""),"45548CRL") -> 45548CRL | N63: =IFERROR(__xludf.DUMMYFUNCTION("""COMPUTED_VALUE"""),"CRL") -> CRL | O63: =IFERROR(__xludf.DUMMYFUNCTION("""COMPUTED_VALUE"""),45548.0) -> 45548 | P63: =IFERROR(__xludf.DUMMYFUNCTION("""COMPUTED_VALUE"""),"Labour Strike") -> Labour Strike | Q63: =IFERROR(__xludf.DUMMYFUNCTION("""COMPUTED_VALUE"""),"REJECT") -> REJECT
H64: =IFERROR(__xludf.DUMMYFUNCTION("""COMPUTED_VALUE"""),"46071Romania") -> 46071Romania | I64: =IFERROR(__xludf.DUMMYFUNCTION("""COMPUTED_VALUE"""),"Romania") -> Romania | J64: =IFERROR(__xludf.DUMMYFUNCTION("""COMPUTED_VALUE"""),46071.0) -> 46071 | K64: =IFERROR(__xludf.DUMMYFUNCTION("""COMPUTED_VALUE"""),"Snow Storm") -> Snow Storm | L64: =IFERROR(__xludf.DUMMYFUNCTION("""COMPUTED_VALUE"""),"REJECT") -> REJECT | M64: =IFERROR(__xludf.DUMMYFUNCTION("""COMPUTED_VALUE"""),"45551BRU") -> 45551BRU | N64: =IFERROR(__xludf.DUMMYFUNCTION("""COMPUTED_VALUE"""),"BRU") -> BRU | O64: =IFERROR(__xludf.DUMMYFUNCTION("""COMPUTED_VALUE"""),45551.0) -> 45551 | P64: =IFERROR(__xludf.DUMMYFUNCTION("""COMPUTED_VALUE"""),"strike") -> strike | Q64: =IFERROR(__xludf.DUMMYFUNCTION("""COMPUTED_VALUE"""),"REJECT") -> REJECT
H65: =IFERROR(__xludf.DUMMYFUNCTION("""COMPUTED_VALUE"""),"46072Romania") -> 46072Romania | I65: =IFERROR(__xludf.DUMMYFUNCTION("""COMPUTED_VALUE"""),"Romania") -> Romania | J65: =IFERROR(__xludf.DUMMYFUNCTION("""COMPUTED_VALUE"""),46072.0) -> 46072 | K65: =IFERROR(__xludf.DUMMYFUNCTION("""COMPUTED_VALUE"""),"Snow Storm") -> Snow Storm | L65: =IFERROR(__xludf.DUMMYFUNCTION("""COMPUTED_VALUE"""),"REJECT") -> REJECT | M65: =IFERROR(__xludf.DUMMYFUNCTION("""COMPUTED_VALUE"""),"45566BGY") -> 45566BGY | N65: =IFERROR(__xludf.DUMMYFUNCTION("""COMPUTED_VALUE"""),"BGY") -> BGY | O65: =IFERROR(__xludf.DUMMYFUNCTION("""COMPUTED_VALUE"""),45566.0) -> 45566 | P65: =IFERROR(__xludf.DUMMYFUNCTION("""COMPUTED_VALUE"""),"Runway incident") -> Runway incident | Q65: =IFERROR(__xludf.DUMMYFUNCTION("""COMPUTED_VALUE"""),"REJECT") -> REJECT
H66: =IFERROR(__xludf.DUMMYFUNCTION("""COMPUTED_VALUE"""),"46081United Arab Emirates") -> 46081United Arab Emirates | I66: =IFERROR(__xludf.DUMMYFUNCTION("""COMPUTED_VALUE"""),"United Arab Emirates") -> United Arab Emirates | J66: =IFERROR(__xludf.DUMMYFUNCTION("""COMPUTED_VALUE"""),46081.0) -> 46081 | K66: =IFERROR(__xludf.DUMMYFUNCTION("""COMPUTED_VALUE"""),"Closed post-strikes") -> Closed post-strikes | L66: =IFERROR(__xludf.DUMMYFUNCTION("""COMPUTED_VALUE"""),"REJECT") -> REJECT | M66: =IFERROR(__xludf.DUMMYFUNCTION("""COMPUTED_VALUE"""),"45573DAB") -> 45573DAB | N66: =IFERROR(__xludf.DUMMYFUNCTION("""COMPUTED_VALUE"""),"DAB") -> DAB | O66: =IFERROR(__xludf.DUMMYFUNCTION("""COMPUTED_VALUE"""),45573.0) -> 45573 | P66: =IFERROR(__xludf.DUMMYFUNCTION("""COMPUTED_VALUE"""),"Hurricane Milton") -> Hurricane Milton | Q66: =IFERROR(__xludf.DUMMYFUNCTION("""COMPUTED_VALUE"""),"REJECT") -> REJECT
H67: =IFERROR(__xludf.DUMMYFUNCTION("""COMPUTED_VALUE"""),"46082United Arab Emirates") -> 46082United Arab Emirates | I67: =IFERROR(__xludf.DUMMYFUNCTION("""COMPUTED_VALUE"""),"United Arab Emirates") -> United Arab Emirates | J67: =IFERROR(__xludf.DUMMYFUNCTION("""COMPUTED_VALUE"""),46082.0) -> 46082 | K67: =IFERROR(__xludf.DUMMYFUNCTION("""COMPUTED_VALUE"""),"Closed post-strikes") -> Closed post-strikes | L67: =IFERROR(__xludf.DUMMYFUNCTION("""COMPUTED_VALUE"""),"REJECT") -> REJECT | M67: =IFERROR(__xludf.DUMMYFUNCTION("""COMPUTED_VALUE"""),"45573LAL") -> 45573LAL | N67: =IFERROR(__xludf.DUMMYFUNCTION("""COMPUTED_VALUE"""),"LAL") -> LAL | O67: =IFERROR(__xludf.DUMMYFUNCTION("""COMPUTED_VALUE"""),45573.0) -> 45573 | P67: =IFERROR(__xludf.DUMMYFUNCTION("""COMPUTED_VALUE"""),"Hurricane Milton") -> Hurricane Milton | Q67: =IFERROR(__xludf.DUMMYFUNCTION("""COMPUTED_VALUE"""),"REJECT") -> REJECT
H68: =IFERROR(__xludf.DUMMYFUNCTION("""COMPUTED_VALUE"""),"46083United Arab Emirates") -> 46083United Arab Emirates | I68: =IFERROR(__xludf.DUMMYFUNCTION("""COMPUTED_VALUE"""),"United Arab Emirates") -> United Arab Emirates | J68: =IFERROR(__xludf.DUMMYFUNCTION("""COMPUTED_VALUE"""),46083.0) -> 46083 | K68: =IFERROR(__xludf.DUMMYFUNCTION("""COMPUTED_VALUE"""),"Closed post-strikes") -> Closed post-strikes | L68: =IFERROR(__xludf.DUMMYFUNCTION("""COMPUTED_VALUE"""),"REJECT") -> REJECT | M68: =IFERROR(__xludf.DUMMYFUNCTION("""COMPUTED_VALUE"""),"45573MCO") -> 45573MCO | N68: =IFERROR(__xludf.DUMMYFUNCTION("""COMPUTED_VALUE"""),"MCO") -> MCO | O68: =IFERROR(__xludf.DUMMYFUNCTION("""COMPUTED_VALUE"""),45573.0) -> 45573 | P68: =IFERROR(__xludf.DUMMYFUNCTION("""COMPUTED_VALUE"""),"Hurricane Milton") -> Hurricane Milton | Q68: =IFERROR(__xludf.DUMMYFUNCTION("""COMPUTED_VALUE"""),"REJECT") -> REJECT
H69: =IFERROR(__xludf.DUMMYFUNCTION("""COMPUTED_VALUE"""),"46081Qatar") -> 46081Qatar | I69: =IFERROR(__xludf.DUMMYFUNCTION("""COMPUTED_VALUE"""),"Qatar") -> Qatar | J69: =IFERROR(__xludf.DUMMYFUNCTION("""COMPUTED_VALUE"""),46081.0) -> 46081 | K69: =IFERROR(__xludf.DUMMYFUNCTION("""COMPUTED_VALUE"""),"Closed post-strikes") -> Closed post-strikes | L69: =IFERROR(__xludf.DUMMYFUNCTION("""COMPUTED_VALUE"""),"REJECT") -> REJECT | M69: =IFERROR(__xludf.DUMMYFUNCTION("""COMPUTED_VALUE"""),"45573MLB") -> 45573MLB | N69: =IFERROR(__xludf.DUMMYFUNCTION("""COMPUTED_VALUE"""),"MLB") -> MLB | O69: =IFERROR(__xludf.DUMMYFUNCTION("""COMPUTED_VALUE"""),45573.0) -> 45573 | P69: =IFERROR(__xludf.DUMMYFUNCTION("""COMPUTED_VALUE"""),"Hurricane Milton") -> Hurricane Milton | Q69: =IFERROR(__xludf.DUMMYFUNCTION("""COMPUTED_VALUE"""),"REJECT") -> REJECT
H70: =IFERROR(__xludf.DUMMYFUNCTION("""COMPUTED_VALUE"""),"46082Qatar") -> 46082Qatar | I70: =IFERROR(__xludf.DUMMYFUNCTION("""COMPUTED_VALUE"""),"Qatar") -> Qatar | J70: =IFERROR(__xludf.DUMMYFUNCTION("""COMPUTED_VALUE"""),46082.0) -> 46082 | K70: =IFERROR(__xludf.DUMMYFUNCTION("""COMPUTED_VALUE"""),"Closed post-strikes") -> Closed post-strikes | L70: =IFERROR(__xludf.DUMMYFUNCTION("""COMPUTED_VALUE"""),"REJECT") -> REJECT | M70: =IFERROR(__xludf.DUMMYFUNCTION("""COMPUTED_VALUE"""),"45573ORL") -> 45573ORL | N70: =IFERROR(__xludf.DUMMYFUNCTION("""COMPUTED_VALUE"""),"ORL") -> ORL | O70: =IFERROR(__xludf.DUMMYFUNCTION("""COMPUTED_VALUE"""),45573.0) -> 45573 | P70: =IFERROR(__xludf.DUMMYFUNCTION("""COMPUTED_VALUE"""),"Hurricane Milton") -> Hurricane Milton | Q70: =IFERROR(__xludf.DUMMYFUNCTION("""COMPUTED_VALUE"""),"REJECT") -> REJECT
H71: =IFERROR(__xludf.DUMMYFUNCTION("""COMPUTED_VALUE"""),"46083Qatar") -> 46083Qatar | I71: =IFERROR(__xludf.DUMMYFUNCTION("""COMPUTED_VALUE"""),"Qatar") -> Qatar | J71: =IFERROR(__xludf.DUMMYFUNCTION("""COMPUTED_VALUE"""),46083.0) -> 46083 | K71: =IFERROR(__xludf.DUMMYFUNCTION("""COMPUTED_VALUE"""),"Closed post-strikes") -> Closed post-strikes | L71: =IFERROR(__xludf.DUMMYFUNCTION("""COMPUTED_VALUE"""),"REJECT") -> REJECT | M71: =IFERROR(__xludf.DUMMYFUNCTION("""COMPUTED_VALUE"""),"45573PCM") -> 45573PCM | N71: =IFERROR(__xludf.DUMMYFUNCTION("""COMPUTED_VALUE"""),"PCM") -> PCM | O71: =IFERROR(__xludf.DUMMYFUNCTION("""COMPUTED_VALUE"""),45573.0) -> 45573 | P71: =IFERROR(__xludf.DUMMYFUNCTION("""COMPUTED_VALUE"""),"Hurricane Milton") -> Hurricane Milton | Q71: =IFERROR(__xludf.DUMMYFUNCTION("""COMPUTED_VALUE"""),"REJECT") -> REJECT
H72: =IFERROR(__xludf.DUMMYFUNCTION("""COMPUTED_VALUE"""),"46081Kuwait") -> 46081Kuwait | I72: =IFERROR(__xludf.DUMMYFUNCTION("""COMPUTED_VALUE"""),"Kuwait") -> Kuwait | J72: =IFERROR(__xludf.DUMMYFUNCTION("""COMPUTED_VALUE"""),46081.0) -> 46081 | K72: =IFERROR(__xludf.DUMMYFUNCTION("""COMPUTED_VALUE"""),"Closed post-strikes") -> Closed post-strikes | L72: =IFERROR(__xludf.DUMMYFUNCTION("""COMPUTED_VALUE"""),"REJECT") -> REJECT | M72: =IFERROR(__xludf.DUMMYFUNCTION("""COMPUTED_VALUE"""),"45573PIE") -> 45573PIE | N72: =IFERROR(__xludf.DUMMYFUNCTION("""COMPUTED_VALUE"""),"PIE") -> PIE | O72: =IFERROR(__xludf.DUMMYFUNCTION("""COMPUTED_VALUE"""),45573.0) -> 45573 | P72: =IFERROR(__xludf.DUMMYFUNCTION("""COMPUTED_VALUE"""),"Hurricane Milton") -> Hurricane Milton | Q72: =IFERROR(__xludf.DUMMYFUNCTION("""COMPUTED_VALUE"""),"REJECT") -> REJECT
H73: =IFERROR(__xludf.DUMMYFUNCTION("""COMPUTED_VALUE"""),"46082Kuwait") -> 46082Kuwait | I73: =IFERROR(__xludf.DUMMYFUNCTION("""COMPUTED_VALUE"""),"Kuwait") -> Kuwait | J73: =IFERROR(__xludf.DUMMYFUNCTION("""COMPUTED_VALUE"""),46082.0) -> 46082 | K73: =IFERROR(__xludf.DUMMYFUNCTION("""COMPUTED_VALUE"""),"Closed post-strikes") -> Closed post-strikes | L73: =IFERROR(__xludf.DUMMYFUNCTION("""COMPUTED_VALUE"""),"REJECT") -> REJECT | M73: =IFERROR(__xludf.DUMMYFUNCTION("""COMPUTED_VALUE"""),"45573RSW") -> 45573RSW | N73: =IFERROR(__xludf.DUMMYFUNCTION("""COMPUTED_VALUE"""),"RSW") -> RSW | O73: =IFERROR(__xludf.DUMMYFUNCTION("""COMPUTED_VALUE"""),45573.0) -> 45573 | P73: =IFERROR(__xludf.DUMMYFUNCTION("""COMPUTED_VALUE"""),"Hurricane Milton") -> Hurricane Milton | Q73: =IFERROR(__xludf.DUMMYFUNCTION("""COMPUTED_VALUE"""),"REJECT") -> REJECT
H74: =IFERROR(__xludf.DUMMYFUNCTION("""COMPUTED_VALUE"""),"46083Kuwait") -> 46083Kuwait | I74: =IFERROR(__xludf.DUMMYFUNCTION("""COMPUTED_VALUE"""),"Kuwait") -> Kuwait | J74: =IFERROR(__xludf.DUMMYFUNCTION("""COMPUTED_VALUE"""),46083.0) -> 46083 | K74: =IFERROR(__xludf.DUMMYFUNCTION("""COMPUTED_VALUE"""),"Closed post-strikes") -> Closed post-strikes | L74: =IFERROR(__xludf.DUMMYFUNCTION("""COMPUTED_VALUE"""),"REJECT") -> REJECT | M74: =IFERROR(__xludf.DUMMYFUNCTION("""COMPUTED_VALUE"""),"45573SFB") -> 45573SFB | N74: =IFERROR(__xludf.DUMMYFUNCTION("""COMPUTED_VALUE"""),"SFB") -> SFB | O74: =IFERROR(__xludf.DUMMYFUNCTION("""COMPUTED_VALUE"""),45573.0) -> 45573 | P74: =IFERROR(__xludf.DUMMYFUNCTION("""COMPUTED_VALUE"""),"Hurricane Milton") -> Hurricane Milton | Q74: =IFERROR(__xludf.DUMMYFUNCTION("""COMPUTED_VALUE"""),"REJECT") -> REJECT
H75: =IFERROR(__xludf.DUMMYFUNCTION("""COMPUTED_VALUE"""),"46081Jordan") -> 46081Jordan | I75: =IFERROR(__xludf.DUMMYFUNCTION("""COMPUTED_VALUE"""),"Jordan") -> Jordan | J75: =IFERROR(__xludf.DUMMYFUNCTION("""COMPUTED_VALUE"""),46081.0) -> 46081 | K75: =IFERROR(__xludf.DUMMYFUNCTION("""COMPUTED_VALUE"""),"Closed post-strikes") -> Closed post-strikes | L75: =IFERROR(__xludf.DUMMYFUNCTION("""COMPUTED_VALUE"""),"REJECT") -> REJECT | M75: =IFERROR(__xludf.DUMMYFUNCTION("""COMPUTED_VALUE"""),"45573SRQ") -> 45573SRQ | N75: =IFERROR(__xludf.DUMMYFUNCTION("""COMPUTED_VALUE"""),"SRQ") -> SRQ | O75: =IFERROR(__xludf.DUMMYFUNCTION("""COMPUTED_VALUE"""),45573.0) -> 45573 | P75: =IFERROR(__xludf.DUMMYFUNCTION("""COMPUTED_VALUE"""),"Hurricane Milton") -> Hurricane Milton | Q75: =IFERROR(__xludf.DUMMYFUNCTION("""COMPUTED_VALUE"""),"REJECT") -> REJECT
H76: =IFERROR(__xludf.DUMMYFUNCTION("""COMPUTED_VALUE"""),"46082Jordan") -> 46082Jordan | I76: =IFERROR(__xludf.DUMMYFUNCTION("""COMPUTED_VALUE"""),"Jordan") -> Jordan | J76: =IFERROR(__xludf.DUMMYFUNCTION("""COMPUTED_VALUE"""),46082.0) -> 46082 | K76: =IFERROR(__xludf.DUMMYFUNCTION("""COMPUTED_VALUE"""),"Closed post-strikes") -> Closed post-strikes | L76: =IFERROR(__xludf.DUMMYFUNCTION("""COMPUTED_VALUE"""),"REJECT") -> REJECT | M76: =IFERROR(__xludf.DUMMYFUNCTION("""COMPUTED_VALUE"""),"45573TPA") -> 45573TPA | N76: =IFERROR(__xludf.DUMMYFUNCTION("""COMPUTED_VALUE"""),"TPA") -> TPA | O76: =IFERROR(__xludf.DUMMYFUNCTION("""COMPUTED_VALUE"""),45573.0) -> 45573 | P76: =IFERROR(__xludf.DUMMYFUNCTION("""COMPUTED_VALUE"""),"Hurricane Milton") -> Hurricane Milton | Q76: =IFERROR(__xludf.DUMMYFUNCTION("""COMPUTED_VALUE"""),"REJECT") -> REJECT
H77: =IFERROR(__xludf.DUMMYFUNCTION("""COMPUTED_VALUE"""),"46083Jordan") -> 46083Jordan | I77: =IFERROR(__xludf.DUMMYFUNCTION("""COMPUTED_VALUE"""),"Jordan") -> Jordan | J77: =IFERROR(__xludf.DUMMYFUNCTION("""COMPUTED_VALUE"""),46083.0) -> 46083 | K77: =IFERROR(__xludf.DUMMYFUNCTION("""COMPUTED_VALUE"""),"Closed post-strikes") -> Closed post-strikes | L77: =IFERROR(__xludf.DUMMYFUNCTION("""COMPUTED_VALUE"""),"REJECT") -> REJECT | M77: =IFERROR(__xludf.DUMMYFUNCTION("""COMPUTED_VALUE"""),"45573TPF") -> 45573TPF | N77: =IFERROR(__xludf.DUMMYFUNCTION("""COMPUTED_VALUE"""),"TPF") -> TPF | O77: =IFERROR(__xludf.DUMMYFUNCTION("""COMPUTED_VALUE"""),45573.0) -> 45573 | P77: =IFERROR(__xludf.DUMMYFUNCTION("""COMPUTED_VALUE"""),"Hurricane Milton") -> Hurricane Milton | Q77: =IFERROR(__xludf.DUMMYFUNCTION("""COMPUTED_VALUE"""),"REJECT") -> REJECT
H78: =IFERROR(__xludf.DUMMYFUNCTION("""COMPUTED_VALUE"""),"46081Bahrain") -> 46081Bahrain | I78: =IFERROR(__xludf.DUMMYFUNCTION("""COMPUTED_VALUE"""),"Bahrain") -> Bahrain | J78: =IFERROR(__xludf.DUMMYFUNCTION("""COMPUTED_VALUE"""),46081.0) -> 46081 | K78: =IFERROR(__xludf.DUMMYFUNCTION("""COMPUTED_VALUE"""),"Closed post-strikes") -> Closed post-strikes | L78: =IFERROR(__xludf.DUMMYFUNCTION("""COMPUTED_VALUE"""),"REJECT") -> REJECT | M78: =IFERROR(__xludf.DUMMYFUNCTION("""COMPUTED_VALUE"""),"45573VDF") -> 45573VDF | N78: =IFERROR(__xludf.DUMMYFUNCTION("""COMPUTED_VALUE"""),"VDF") -> VDF | O78: =IFERROR(__xludf.DUMMYFUNCTION("""COMPUTED_VALUE"""),45573.0) -> 45573 | P78: =IFERROR(__xludf.DUMMYFUNCTION("""COMPUTED_VALUE"""),"Hurricane Milton") -> Hurricane Milton | Q78: =IFERROR(__xludf.DUMMYFUNCTION("""COMPUTED_VALUE"""),"REJECT") -> REJECT
H79: =IFERROR(__xludf.DUMMYFUNCTION("""COMPUTED_VALUE"""),"46082Bahrain") -> 46082Bahrain | I79: =IFERROR(__xludf.DUMMYFUNCTION("""COMPUTED_VALUE"""),"Bahrain") -> Bahrain | J79: =IFERROR(__xludf.DUMMYFUNCTION("""COMPUTED_VALUE"""),46082.0) -> 46082 | K79: =IFERROR(__xludf.DUMMYFUNCTION("""COMPUTED_VALUE"""),"Closed post-strikes") -> Closed post-strikes | L79: =IFERROR(__xludf.DUMMYFUNCTION("""COMPUTED_VALUE"""),"REJECT") -> REJECT | M79: =IFERROR(__xludf.DUMMYFUNCTION("""COMPUTED_VALUE"""),"45574DAB") -> 45574DAB | N79: =IFERROR(__xludf.DUMMYFUNCTION("""COMPUTED_VALUE"""),"DAB") -> DAB | O79: =IFERROR(__xludf.DUMMYFUNCTION("""COMPUTED_VALUE"""),45574.0) -> 45574 | P79: =IFERROR(__xludf.DUMMYFUNCTION("""COMPUTED_VALUE"""),"Hurricane Milton") -> Hurricane Milton | Q79: =IFERROR(__xludf.DUMMYFUNCTION("""COMPUTED_VALUE"""),"REJECT") -> REJECT
H80: =IFERROR(__xludf.DUMMYFUNCTION("""COMPUTED_VALUE"""),"46083Bahrain") -> 46083Bahrain | I80: =IFERROR(__xludf.DUMMYFUNCTION("""COMPUTED_VALUE"""),"Bahrain") -> Bahrain | J80: =IFERROR(__xludf.DUMMYFUNCTION("""COMPUTED_VALUE"""),46083.0) -> 46083 | K80: =IFERROR(__xludf.DUMMYFUNCTION("""COMPUTED_VALUE"""),"Closed post-strikes") -> Closed post-strikes | L80: =IFERROR(__xludf.DUMMYFUNCTION("""COMPUTED_VALUE"""),"REJECT") -> REJECT | M80: =IFERROR(__xludf.DUMMYFUNCTION("""COMPUTED_VALUE"""),"45574LAL") -> 45574LAL | N80: =IFERROR(__xludf.DUMMYFUNCTION("""COMPUTED_VALUE"""),"LAL") -> LAL | O80: =IFERROR(__xludf.DUMMYFUNCTION("""COMPUTED_VALUE"""),45574.0) -> 45574 | P80: =IFERROR(__xludf.DUMMYFUNCTION("""COMPUTED_VALUE"""),"Hurricane Milton") -> Hurricane Milton | Q80: =IFERROR(__xludf.DUMMYFUNCTION("""COMPUTED_VALUE"""),"REJECT") -> REJECT
H81: =IFERROR(__xludf.DUMMYFUNCTION("""COMPUTED_VALUE"""),"46081Iran") -> 46081Iran | I81: =IFERROR(__xludf.DUMMYFUNCTION("""COMPUTED_VALUE"""),"Iran") -> Iran | J81: =IFERROR(__xludf.DUMMYFUNCTION("""COMPUTED_VALUE"""),46081.0) -> 46081 | K81: =IFERROR(__xludf.DUMMYFUNCTION("""COMPUTED_VALUE"""),"Closed post-strikes") -> Closed post-strikes | L81: =IFERROR(__xludf.DUMMYFUNCTION("""COMPUTED_VALUE"""),"REJECT") -> REJECT | M81: =IFERROR(__xludf.DUMMYFUNCTION("""COMPUTED_VALUE"""),"45574MCO") -> 45574MCO | N81: =IFERROR(__xludf.DUMMYFUNCTION("""COMPUTED_VALUE"""),"MCO") -> MCO | O81: =IFERROR(__xludf.DUMMYFUNCTION("""COMPUTED_VALUE"""),45574.0) -> 45574 | P81: =IFERROR(__xludf.DUMMYFUNCTION("""COMPUTED_VALUE"""),"Hurricane Milton") -> Hurricane Milton | Q81: =IFERROR(__xludf.DUMMYFUNCTION("""COMPUTED_VALUE"""),"REJECT") -> REJECT
H82: =IFERROR(__xludf.DUMMYFUNCTION("""COMPUTED_VALUE"""),"46082Iran") -> 46082Iran | I82: =IFERROR(__xludf.DUMMYFUNCTION("""COMPUTED_VALUE"""),"Iran") -> Iran | J82: =IFERROR(__xludf.DUMMYFUNCTION("""COMPUTED_VALUE"""),46082.0) -> 46082 | K82: =IFERROR(__xludf.DUMMYFUNCTION("""COMPUTED_VALUE"""),"Closed post-strikes") -> Closed post-strikes | L82: =IFERROR(__xludf.DUMMYFUNCTION("""COMPUTED_VALUE"""),"REJECT") -> REJECT | M82: =IFERROR(__xludf.DUMMYFUNCTION("""COMPUTED_VALUE"""),"45574MLB") -> 45574MLB | N82: =IFERROR(__xludf.DUMMYFUNCTION("""COMPUTED_VALUE"""),"MLB") -> MLB | O82: =IFERROR(__xludf.DUMMYFUNCTION("""COMPUTED_VALUE"""),45574.0) -> 45574 | P82: =IFERROR(__xludf.DUMMYFUNCTION("""COMPUTED_VALUE"""),"Hurricane Milton") -> Hurricane Milton | Q82: =IFERROR(__xludf.DUMMYFUNCTION("""COMPUTED_VALUE"""),"REJECT") -> REJECT
H83: =IFERROR(__xludf.DUMMYFUNCTION("""COMPUTED_VALUE"""),"46083Iran") -> 46083Iran | I83: =IFERROR(__xludf.DUMMYFUNCTION("""COMPUTED_VALUE"""),"Iran") -> Iran | J83: =IFERROR(__xludf.DUMMYFUNCTION("""COMPUTED_VALUE"""),46083.0) -> 46083 | K83: =IFERROR(__xludf.DUMMYFUNCTION("""COMPUTED_VALUE"""),"Closed post-strikes") -> Closed post-strikes | L83: =IFERROR(__xludf.DUMMYFUNCTION("""COMPUTED_VALUE"""),"REJECT") -> REJECT | M83: =IFERROR(__xludf.DUMMYFUNCTION("""COMPUTED_VALUE"""),"45574ORL") -> 45574ORL | N83: =IFERROR(__xludf.DUMMYFUNCTION("""COMPUTED_VALUE"""),"ORL") -> ORL | O83: =IFERROR(__xludf.DUMMYFUNCTION("""COMPUTED_VALUE"""),45574.0) -> 45574 | P83: =IFERROR(__xludf.DUMMYFUNCTION("""COMPUTED_VALUE"""),"Hurricane Milton") -> Hurricane Milton | Q83: =IFERROR(__xludf.DUMMYFUNCTION("""COMPUTED_VALUE"""),"REJECT") -> REJECT
H84: =IFERROR(__xludf.DUMMYFUNCTION("""COMPUTED_VALUE"""),"46081Saudi Arabia") -> 46081Saudi Arabia | I84: =IFERROR(__xludf.DUMMYFUNCTION("""COMPUTED_VALUE"""),"Saudi Arabia") -> Saudi Arabia | J84: =IFERROR(__xludf.DUMMYFUNCTION("""COMPUTED_VALUE"""),46081.0) -> 46081 | K84: =IFERROR(__xludf.DUMMYFUNCTION("""COMPUTED_VALUE"""),"Closed post-strikes") -> Closed post-strikes | L84: =IFERROR(__xludf.DUMMYFUNCTION("""COMPUTED_VALUE"""),"REJECT") -> REJECT | M84: =IFERROR(__xludf.DUMMYFUNCTION("""COMPUTED_VALUE"""),"45574PCM") -> 45574PCM | N84: =IFERROR(__xludf.DUMMYFUNCTION("""COMPUTED_VALUE"""),"PCM") -> PCM | O84: =IFERROR(__xludf.DUMMYFUNCTION("""COMPUTED_VALUE"""),45574.0) -> 45574 | P84: =IFERROR(__xludf.DUMMYFUNCTION("""COMPUTED_VALUE"""),"Hurricane Milton") -> Hurricane Milton | Q84: =IFERROR(__xludf.DUMMYFUNCTION("""COMPUTED_VALUE"""),"REJECT") -> REJECT
H85: =IFERROR(__xludf.DUMMYFUNCTION("""COMPUTED_VALUE"""),"46082Saudi Arabia") -> 46082Saudi Arabia | I85: =IFERROR(__xludf.DUMMYFUNCTION("""COMPUTED_VALUE"""),"Saudi Arabia") -> Saudi Arabia | J85: =IFERROR(__xludf.DUMMYFUNCTION("""COMPUTED_VALUE"""),46082.0) -> 46082 | K85: =IFERROR(__xludf.DUMMYFUNCTION("""COMPUTED_VALUE"""),"Closed post-strikes") -> Closed post-strikes | L85: =IFERROR(__xludf.DUMMYFUNCTION("""COMPUTED_VALUE"""),"REJECT") -> REJECT | M85: =IFERROR(__xludf.DUMMYFUNCTION("""COMPUTED_VALUE"""),"45574PIE") -> 45574PIE | N85: =IFERROR(__xludf.DUMMYFUNCTION("""COMPUTED_VALUE"""),"PIE") -> PIE | O85: =IFERROR(__xludf.DUMMYFUNCTION("""COMPUTED_VALUE"""),45574.0) -> 45574 | P85: =IFERROR(__xludf.DUMMYFUNCTION("""COMPUTED_VALUE"""),"Hurricane Milton") -> Hurricane Milton | Q85: =IFERROR(__xludf.DUMMYFUNCTION("""COMPUTED_VALUE"""),"REJECT") -> REJECT
H86: =IFERROR(__xludf.DUMMYFUNCTION("""COMPUTED_VALUE"""),"46083Saudi Arabia") -> 46083Saudi Arabia | I86: =IFERROR(__xludf.DUMMYFUNCTION("""COMPUTED_VALUE"""),"Saudi Arabia") -> Saudi Arabia | J86: =IFERROR(__xludf.DUMMYFUNCTION("""COMPUTED_VALUE"""),46083.0) -> 46083 | K86: =IFERROR(__xludf.DUMMYFUNCTION("""COMPUTED_VALUE"""),"Closed post-strikes") -> Closed post-strikes | L86: =IFERROR(__xludf.DUMMYFUNCTION("""COMPUTED_VALUE"""),"REJECT") -> REJECT | M86: =IFERROR(__xludf.DUMMYFUNCTION("""COMPUTED_VALUE"""),"45574RSW") -> 45574RSW | N86: =IFERROR(__xludf.DUMMYFUNCTION("""COMPUTED_VALUE"""),"RSW") -> RSW | O86: =IFERROR(__xludf.DUMMYFUNCTION("""COMPUTED_VALUE"""),45574.0) -> 45574 | P86: =IFERROR(__xludf.DUMMYFUNCTION("""COMPUTED_VALUE"""),"Hurricane Milton") -> Hurricane Milton | Q86: =IFERROR(__xludf.DUMMYFUNCTION("""COMPUTED_VALUE"""),"REJECT") -> REJECT
H87: =IFERROR(__xludf.DUMMYFUNCTION("""COMPUTED_VALUE"""),"46084United Arab Emirates") -> 46084United Arab Emirates | I87: =IFERROR(__xludf.DUMMYFUNCTION("""COMPUTED_VALUE"""),"United Arab Emirates") -> United Arab Emirates | J87: =IFERROR(__xludf.DUMMYFUNCTION("""COMPUTED_VALUE"""),46084.0) -> 46084 | K87: =IFERROR(__xludf.DUMMYFUNCTION("""COMPUTED_VALUE"""),"Closed post-strikes") -> Closed post-strikes | L87: =IFERROR(__xludf.DUMMYFUNCTION("""COMPUTED_VALUE"""),"REJECT") -> REJECT | M87: =IFERROR(__xludf.DUMMYFUNCTION("""COMPUTED_VALUE"""),"45574SFB") -> 45574SFB | N87: =IFERROR(__xludf.DUMMYFUNCTION("""COMPUTED_VALUE"""),"SFB") -> SFB | O87: =IFERROR(__xludf.DUMMYFUNCTION("""COMPUTED_VALUE"""),45574.0) -> 45574 | P87: =IFERROR(__xludf.DUMMYFUNCTION("""COMPUTED_VALUE"""),"Hurricane Milton") -> Hurricane Milton | Q87: =IFERROR(__xludf.DUMMYFUNCTION("""COMPUTED_VALUE"""),"REJECT") -> REJECT
H88: =IFERROR(__xludf.DUMMYFUNCTION("""COMPUTED_VALUE"""),"46084Qatar") -> 46084Qatar | I88: =IFERROR(__xludf.DUMMYFUNCTION("""COMPUTED_VALUE"""),"Qatar") -> Qatar | J88: =IFERROR(__xludf.DUMMYFUNCTION("""COMPUTED_VALUE"""),46084.0) -> 46084 | K88: =IFERROR(__xludf.DUMMYFUNCTION("""COMPUTED_VALUE"""),"Closed post-strikes") -> Closed post-strikes | L88: =IFERROR(__xludf.DUMMYFUNCTION("""COMPUTED_VALUE"""),"REJECT") -> REJECT | M88: =IFERROR(__xludf.DUMMYFUNCTION("""COMPUTED_VALUE"""),"45574SRQ") -> 45574SRQ | N88: =IFERROR(__xludf.DUMMYFUNCTION("""COMPUTED_VALUE"""),"SRQ") -> SRQ | O88: =IFERROR(__xludf.DUMMYFUNCTION("""COMPUTED_VALUE"""),45574.0) -> 45574 | P88: =IFERROR(__xludf.DUMMYFUNCTION("""COMPUTED_VALUE"""),"Hurricane Milton") -> Hurricane Milton | Q88: =IFERROR(__xludf.DUMMYFUNCTION("""COMPUTED_VALUE"""),"REJECT") -> REJECT
H89: =IFERROR(__xludf.DUMMYFUNCTION("""COMPUTED_VALUE"""),"46084Kuwait") -> 46084Kuwait | I89: =IFERROR(__xludf.DUMMYFUNCTION("""COMPUTED_VALUE"""),"Kuwait") -> Kuwait | J89: =IFERROR(__xludf.DUMMYFUNCTION("""COMPUTED_VALUE"""),46084.0) -> 46084 | K89: =IFERROR(__xludf.DUMMYFUNCTION("""COMPUTED_VALUE"""),"Closed post-strikes") -> Closed post-strikes | L89: =IFERROR(__xludf.DUMMYFUNCTION("""COMPUTED_VALUE"""),"REJECT") -> REJECT | M89: =IFERROR(__xludf.DUMMYFUNCTION("""COMPUTED_VALUE"""),"45574TPA") -> 45574TPA | N89: =IFERROR(__xludf.DUMMYFUNCTION("""COMPUTED_VALUE"""),"TPA") -> TPA | O89: =IFERROR(__xludf.DUMMYFUNCTION("""COMPUTED_VALUE"""),45574.0) -> 45574 | P89: =IFERROR(__xludf.DUMMYFUNCTION("""COMPUTED_VALUE"""),"Hurricane Milton") -> Hurricane Milton | Q89: =IFERROR(__xludf.DUMMYFUNCTION("""COMPUTED_VALUE"""),"REJECT") -> REJECT
H90: =IFERROR(__xludf.DUMMYFUNCTION("""COMPUTED_VALUE"""),"46084Jordan") -> 46084Jordan | I90: =IFERROR(__xludf.DUMMYFUNCTION("""COMPUTED_VALUE"""),"Jordan") -> Jordan | J90: =IFERROR(__xludf.DUMMYFUNCTION("""COMPUTED_VALUE"""),46084.0) -> 46084 | K90: =IFERROR(__xludf.DUMMYFUNCTION("""COMPUTED_VALUE"""),"Closed post-strikes") -> Closed post-strikes | L90: =IFERROR(__xludf.DUMMYFUNCTION("""COMPUTED_VALUE"""),"REJECT") -> REJECT | M90: =IFERROR(__xludf.DUMMYFUNCTION("""COMPUTED_VALUE"""),"45574TPF") -> 45574TPF | N90: =IFERROR(__xludf.DUMMYFUNCTION("""COMPUTED_VALUE"""),"TPF") -> TPF | O90: =IFERROR(__xludf.DUMMYFUNCTION("""COMPUTED_VALUE"""),45574.0) -> 45574 | P90: =IFERROR(__xludf.DUMMYFUNCTION("""COMPUTED_VALUE"""),"Hurricane Milton") -> Hurricane Milton | Q90: =IFERROR(__xludf.DUMMYFUNCTION("""COMPUTED_VALUE"""),"REJECT") -> REJECT
H91: =IFERROR(__xludf.DUMMYFUNCTION("""COMPUTED_VALUE"""),"46084Bahrain") -> 46084Bahrain | I91: =IFERROR(__xludf.DUMMYFUNCTION("""COMPUTED_VALUE"""),"Bahrain") -> Bahrain | J91: =IFERROR(__xludf.DUMMYFUNCTION("""COMPUTED_VALUE"""),46084.0) -> 46084 | K91: =IFERROR(__xludf.DUMMYFUNCTION("""COMPUTED_VALUE"""),"Closed post-strikes") -> Closed post-strikes | L91: =IFERROR(__xludf.DUMMYFUNCTION("""COMPUTED_VALUE"""),"REJECT") -> REJECT | M91: =IFERROR(__xludf.DUMMYFUNCTION("""COMPUTED_VALUE"""),"45574VDF") -> 45574VDF | N91: =IFERROR(__xludf.DUMMYFUNCTION("""COMPUTED_VALUE"""),"VDF") -> VDF | O91: =IFERROR(__xludf.DUMMYFUNCTION("""COMPUTED_VALUE"""),45574.0) -> 45574 | P91: =IFERROR(__xludf.DUMMYFUNCTION("""COMPUTED_VALUE"""),"Hurricane Milton") -> Hurricane Milton | Q91: =IFERROR(__xludf.DUMMYFUNCTION("""COMPUTED_VALUE"""),"REJECT") -> REJECT
H92: =IFERROR(__xludf.DUMMYFUNCTION("""COMPUTED_VALUE"""),"46084Iran") -> 46084Iran | I92: =IFERROR(__xludf.DUMMYFUNCTION("""COMPUTED_VALUE"""),"Iran") -> Iran | J92: =IFERROR(__xludf.DUMMYFUNCTION("""COMPUTED_VALUE"""),46084.0) -> 46084 | K92: =IFERROR(__xludf.DUMMYFUNCTION("""COMPUTED_VALUE"""),"Closed post-strikes") -> Closed post-strikes | L92: =IFERROR(__xludf.DUMMYFUNCTION("""COMPUTED_VALUE"""),"REJECT") -> REJECT | M92: =IFERROR(__xludf.DUMMYFUNCTION("""COMPUTED_VALUE"""),"45575DAB") -> 45575DAB | N92: =IFERROR(__xludf.DUMMYFUNCTION("""COMPUTED_VALUE"""),"DAB") -> DAB | O92: =IFERROR(__xludf.DUMMYFUNCTION("""COMPUTED_VALUE"""),45575.0) -> 45575 | P92: =IFERROR(__xludf.DUMMYFUNCTION("""COMPUTED_VALUE"""),"Hurricane Milton") -> Hurricane Milton | Q92: =IFERROR(__xludf.DUMMYFUNCTION("""COMPUTED_VALUE"""),"REJECT") -> REJECT
H93: =IFERROR(__xludf.DUMMYFUNCTION("""COMPUTED_VALUE"""),"46084Saudi Arabia") -> 46084Saudi Arabia | I93: =IFERROR(__xludf.DUMMYFUNCTION("""COMPUTED_VALUE"""),"Saudi Arabia") -> Saudi Arabia | J93: =IFERROR(__xludf.DUMMYFUNCTION("""COMPUTED_VALUE"""),46084.0) -> 46084 | K93: =IFERROR(__xludf.DUMMYFUNCTION("""COMPUTED_VALUE"""),"Closed post-strikes") -> Closed post-strikes | L93: =IFERROR(__xludf.DUMMYFUNCTION("""COMPUTED_VALUE"""),"REJECT") -> REJECT | M93: =IFERROR(__xludf.DUMMYFUNCTION("""COMPUTED_VALUE"""),"45575LAL") -> 45575LAL | N93: =IFERROR(__xludf.DUMMYFUNCTION("""COMPUTED_VALUE"""),"LAL") -> LAL | O93: =IFERROR(__xludf.DUMMYFUNCTION("""COMPUTED_VALUE"""),45575.0) -> 45575 | P93: =IFERROR(__xludf.DUMMYFUNCTION("""COMPUTED_VALUE"""),"Hurricane Milton") -> Hurricane Milton | Q93: =IFERROR(__xludf.DUMMYFUNCTION("""COMPUTED_VALUE"""),"REJECT") -> REJECT
H94: =IFERROR(__xludf.DUMMYFUNCTION("""COMPUTED_VALUE"""),"46085United Arab Emirates") -> 46085United Arab Emirates | I94: =IFERROR(__xludf.DUMMYFUNCTION("""COMPUTED_VALUE"""),"United Arab Emirates") -> United Arab Emirates | J94: =IFERROR(__xludf.DUMMYFUNCTION("""COMPUTED_VALUE"""),46085.0) -> 46085 | K94: =IFERROR(__xludf.DUMMYFUNCTION("""COMPUTED_VALUE"""),"Closed post-strikes") -> Closed post-strikes | L94: =IFERROR(__xludf.DUMMYFUNCTION("""COMPUTED_VALUE"""),"REJECT") -> REJECT | M94: =IFERROR(__xludf.DUMMYFUNCTION("""COMPUTED_VALUE"""),"45575MCO") -> 45575MCO | N94: =IFERROR(__xludf.DUMMYFUNCTION("""COMPUTED_VALUE"""),"MCO") -> MCO | O94: =IFERROR(__xludf.DUMMYFUNCTION("""COMPUTED_VALUE"""),45575.0) -> 45575 | P94: =IFERROR(__xludf.DUMMYFUNCTION("""COMPUTED_VALUE"""),"Hurricane Milton") -> Hurricane Milton | Q94: =IFERROR(__xludf.DUMMYFUNCTION("""COMPUTED_VALUE"""),"REJECT") -> REJECT
H95: =IFERROR(__xludf.DUMMYFUNCTION("""COMPUTED_VALUE"""),"46085Qatar") -> 46085Qatar | I95: =IFERROR(__xludf.DUMMYFUNCTION("""COMPUTED_VALUE"""),"Qatar") -> Qatar | J95: =IFERROR(__xludf.DUMMYFUNCTION("""COMPUTED_VALUE"""),46085.0) -> 46085 | K95: =IFERROR(__xludf.DUMMYFUNCTION("""COMPUTED_VALUE"""),"Closed post-strikes") -> Closed post-strikes | L95: =IFERROR(__xludf.DUMMYFUNCTION("""COMPUTED_VALUE"""),"REJECT") -> REJECT | M95: =IFERROR(__xludf.DUMMYFUNCTION("""COMPUTED_VALUE"""),"45575MLB") -> 45575MLB | N95: =IFERROR(__xludf.DUMMYFUNCTION("""COMPUTED_VALUE"""),"MLB") -> MLB | O95: =IFERROR(__xludf.DUMMYFUNCTION("""COMPUTED_VALUE"""),45575.0) -> 45575 | P95: =IFERROR(__xludf.DUMMYFUNCTION("""COMPUTED_VALUE"""),"Hurricane Milton") -> Hurricane Milton | Q95: =IFERROR(__xludf.DUMMYFUNCTION("""COMPUTED_VALUE"""),"REJECT") -> REJECT
H96: =IFERROR(__xludf.DUMMYFUNCTION("""COMPUTED_VALUE"""),"46085Kuwait") -> 46085Kuwait | I96: =IFERROR(__xludf.DUMMYFUNCTION("""COMPUTED_VALUE"""),"Kuwait") -> Kuwait | J96: =IFERROR(__xludf.DUMMYFUNCTION("""COMPUTED_VALUE"""),46085.0) -> 46085 | K96: =IFERROR(__xludf.DUMMYFUNCTION("""COMPUTED_VALUE"""),"Closed post-strikes") -> Closed post-strikes | L96: =IFERROR(__xludf.DUMMYFUNCTION("""COMPUTED_VALUE"""),"REJECT") -> REJECT | M96: =IFERROR(__xludf.DUMMYFUNCTION("""COMPUTED_VALUE"""),"45575ORL") -> 45575ORL | N96: =IFERROR(__xludf.DUMMYFUNCTION("""COMPUTED_VALUE"""),"ORL") -> ORL | O96: =IFERROR(__xludf.DUMMYFUNCTION("""COMPUTED_VALUE"""),45575.0) -> 45575 | P96: =IFERROR(__xludf.DUMMYFUNCTION("""COMPUTED_VALUE"""),"Hurricane Milton") -> Hurricane Milton | Q96: =IFERROR(__xludf.DUMMYFUNCTION("""COMPUTED_VALUE"""),"REJECT") -> REJECT
H97: =IFERROR(__xludf.DUMMYFUNCTION("""COMPUTED_VALUE"""),"46085Jordan") -> 46085Jordan | I97: =IFERROR(__xludf.DUMMYFUNCTION("""COMPUTED_VALUE"""),"Jordan") -> Jordan | J97: =IFERROR(__xludf.DUMMYFUNCTION("""COMPUTED_VALUE"""),46085.0) -> 46085 | K97: =IFERROR(__xludf.DUMMYFUNCTION("""COMPUTED_VALUE"""),"Closed post-strikes") -> Closed post-strikes | L97: =IFERROR(__xludf.DUMMYFUNCTION("""COMPUTED_VALUE"""),"REJECT") -> REJECT | M97: =IFERROR(__xludf.DUMMYFUNCTION("""COMPUTED_VALUE"""),"45575PCM") -> 45575PCM | N97: =IFERROR(__xludf.DUMMYFUNCTION("""COMPUTED_VALUE"""),"PCM") -> PCM | O97: =IFERROR(__xludf.DUMMYFUNCTION("""COMPUTED_VALUE"""),45575.0) -> 45575 | P97: =IFERROR(__xludf.DUMMYFUNCTION("""COMPUTED_VALUE"""),"Hurricane Milton") -> Hurricane Milton | Q97: =IFERROR(__xludf.DUMMYFUNCTION("""COMPUTED_VALUE"""),"REJECT") -> REJECT
H98: =IFERROR(__xludf.DUMMYFUNCTION("""COMPUTED_VALUE"""),"46085Bahrain") -> 46085Bahrain | I98: =IFERROR(__xludf.DUMMYFUNCTION("""COMPUTED_VALUE"""),"Bahrain") -> Bahrain | J98: =IFERROR(__xludf.DUMMYFUNCTION("""COMPUTED_VALUE"""),46085.0) -> 46085 | K98: =IFERROR(__xludf.DUMMYFUNCTION("""COMPUTED_VALUE"""),"Closed post-strikes") -> Closed post-strikes | L98: =IFERROR(__xludf.DUMMYFUNCTION("""COMPUTED_VALUE"""),"REJECT") -> REJECT | M98: =IFERROR(__xludf.DUMMYFUNCTION("""COMPUTED_VALUE"""),"45575PIE") -> 45575PIE | N98: =IFERROR(__xludf.DUMMYFUNCTION("""COMPUTED_VALUE"""),"PIE") -> PIE | O98: =IFERROR(__xludf.DUMMYFUNCTION("""COMPUTED_VALUE"""),45575.0) -> 45575 | P98: =IFERROR(__xludf.DUMMYFUNCTION("""COMPUTED_VALUE"""),"Hurricane Milton") -> Hurricane Milton | Q98: =IFERROR(__xludf.DUMMYFUNCTION("""COMPUTED_VALUE"""),"REJECT") -> REJECT
H99: =IFERROR(__xludf.DUMMYFUNCTION("""COMPUTED_VALUE"""),"46085Iran") -> 46085Iran | I99: =IFERROR(__xludf.DUMMYFUNCTION("""COMPUTED_VALUE"""),"Iran") -> Iran | J99: =IFERROR(__xludf.DUMMYFUNCTION("""COMPUTED_VALUE"""),46085.0) -> 46085 | K99: =IFERROR(__xludf.DUMMYFUNCTION("""COMPUTED_VALUE"""),"Closed post-strikes") -> Closed post-strikes | L99: =IFERROR(__xludf.DUMMYFUNCTION("""COMPUTED_VALUE"""),"REJECT") -> REJECT | M99: =IFERROR(__xludf.DUMMYFUNCTION("""COMPUTED_VALUE"""),"45575RSW") -> 45575RSW | N99: =IFERROR(__xludf.DUMMYFUNCTION("""COMPUTED_VALUE"""),"RSW") -> RSW | O99: =IFERROR(__xludf.DUMMYFUNCTION("""COMPUTED_VALUE"""),45575.0) -> 45575 | P99: =IFERROR(__xludf.DUMMYFUNCTION("""COMPUTED_VALUE"""),"Hurricane Milton") -> Hurricane Milton | Q99: =IFERROR(__xludf.DUMMYFUNCTION("""COMPUTED_VALUE"""),"REJECT") -> REJECT
H100: =IFERROR(__xludf.DUMMYFUNCTION("""COMPUTED_VALUE"""),"46085Saudi Arabia") -> 46085Saudi Arabia | I100: =IFERROR(__xludf.DUMMYFUNCTION("""COMPUTED_VALUE"""),"Saudi Arabia") -> Saudi Arabia | J100: =IFERROR(__xludf.DUMMYFUNCTION("""COMPUTED_VALUE"""),46085.0) -> 46085 | K100: =IFERROR(__xludf.DUMMYFUNCTION("""COMPUTED_VALUE"""),"Closed post-strikes") -> Closed post-strikes | L100: =IFERROR(__xludf.DUMMYFUNCTION("""COMPUTED_VALUE"""),"REJECT") -> REJECT | M100: =IFERROR(__xludf.DUMMYFUNCTION("""COMPUTED_VALUE"""),"45575SFB") -> 45575SFB | N100: =IFERROR(__xludf.DUMMYFUNCTION("""COMPUTED_VALUE"""),"SFB") -> SFB | O100: =IFERROR(__xludf.DUMMYFUNCTION("""COMPUTED_VALUE"""),45575.0) -> 45575 | P100: =IFERROR(__xludf.DUMMYFUNCTION("""COMPUTED_VALUE"""),"Hurricane Milton") -> Hurricane Milton | Q100: =IFERROR(__xludf.DUMMYFUNCTION("""COMPUTED_VALUE"""),"REJECT") -> REJECT
...

Sheet Countries DB
A1: =IFERROR(__xludf.DUMMYFUNCTION("IMPORTRANGE(""https://docs.google.com/spreadsheets/d/1v24u0ycDMAN6KyPmcvGCkhszdC0i8StNaYU-fRzJxvM/edit?gid=818865393#gid=818865393"",""Countries DB!A:G"")"),"EU Countries") -> EU Countries | G1: =IFERROR(__xludf.DUMMYFUNCTION("""COMPUTED_VALUE"""),"EU Countries") -> EU Countries
A2: =IFERROR(__xludf.DUMMYFUNCTION("""COMPUTED_VALUE"""),"Austria") -> Austria | B2: =IFERROR(__xludf.DUMMYFUNCTION("""COMPUTED_VALUE"""),"Hungary") -> Hungary | C2: =IFERROR(__xludf.DUMMYFUNCTION("""COMPUTED_VALUE"""),"Poland") -> Poland | G2: =IFERROR(__xludf.DUMMYFUNCTION("""COMPUTED_VALUE"""),"Croatia") -> Croatia
A3: =IFERROR(__xludf.DUMMYFUNCTION("""COMPUTED_VALUE"""),"Belgium") -> Belgium | B3: =IFERROR(__xludf.DUMMYFUNCTION("""COMPUTED_VALUE"""),"Iceland") -> Iceland | C3: =IFERROR(__xludf.DUMMYFUNCTION("""COMPUTED_VALUE"""),"Portugal") -> Portugal | G3: =IFERROR(__xludf.DUMMYFUNCTION("""COMPUTED_VALUE"""),"Austria") -> Austria
